Workbook
Name TICKER: #REF!

Sheet Indicadores
A1: Indicadores | B1: Nome | C1: Fórmula
A2: DY | B2: Dividend Yield | C2: Dividendos (12 meses) / Preço da Ação
A3: LPA | B3: Lucro Por Ação | C3: Lucro Líquido / Qtde de Ações
A4: VPA | B4: Valor Patrimonial por Ação | C4: Patrimônio Líquido / Qtde de Ações
A5: CAGR | B5: Taxa de Cresc. Anual Composta | C5: (Valor Final / Valor Inicial)^(1 / Qtde Anos) - 1
A6: DPA | B6: Dividendo por Ação | C6: Payout / LPA
A7: PAYOUT | B7: Percentual Lucro Líquido Distribuído | C7: DPA / LPA

Sheet Ações
AF2: https://ceqef.fgv.br/bancos-de-dados
C3: MONITOR DE VALUATION DO MIRA
C11: IPCA | E11: 0.045
C12: ERP | E12: 0.0903
C13: PRêMIO DE RISCO | E13: 0.1353
B15: AÇÕES | C15: Nome Empresa | D15: Setor | E15: Segmento | F15: CÍCLICO | G15: PREÇO | H15: DY | I15: P/L | J15: LPA | K15: VPA | L15: DPA | M15: RISCO | N15: MARGEM DE DESCONTO | O15: PAYOUT | P15: CRESCIMNETO OU DIVIDENDOS | Q15: ROE | R15: CAGR LUCRO 5A | S15: CRESCIMENTO DAMODARAN | T15: MÉDIA DE CRESCIMENTO | U15: DESC. BAZIN | V15: PREÇO JUSTO BAZIN | W15: PREÇO TETO BAZIN | X15: DESC. GRAHAM | Y15: PREÇO JUSTO GRAHAM | Z15: PREÇO TETO GRAHAM | AA15: DESC. GORDON | AB15: D1 | AC15: PREÇO JUSTO GORDON | AD15: PREÇO TETO GORDON | AE15: ÍNDICE PEG
B16: ='Dados Status Invest'!A2 | C16: =VLOOKUP(Table_1[[#This Row],[AÇÕES]],'Classificação B3'!A:B,2,0) | D16: =VLOOKUP(Table_1[[#This Row],[AÇÕES]],'Classificação B3'!A:D,4,0) | E16: =VLOOKUP(Table_1[[#This Row],[AÇÕES]],'Classificação B3'!A:F,6,0) | F16: =VLOOKUP(Table_1[[#This Row],[AÇÕES]],'Classificação B3'!A:G,7,0) | G16: =VLOOKUP(Table_1[[#This Row],[AÇÕES]],'Dados Status Invest'!A:B,2,0) | H16: =VLOOKUP(Table_1[[#This Row],[AÇÕES]],'Dados Status Invest'!A:C,3,0)/100 | I16: =VLOOKUP(Table_1[[#This Row],[AÇÕES]],'Dados Status Invest'!A:D,4,0)/100 | J16: =VLOOKUP(Table_1[[#This Row],[AÇÕES]],'Dados Status Invest'!A:AB,28,0) | K16: =VLOOKUP(Table_1[[#This Row],[AÇÕES]],'Dados Status Invest'!A:AA,27,0) | L16: =Table_1[[#This Row],[PREÇO]]*Table_1[[#This Row],[DY]] | M16: =$E$13 | N16: 0.3 | O16: =Table_1[[#This Row],[DPA]]/Table_1[[#This Row],[LPA]] | P16: =IF(Table_1[[#This Row],[PAYOUT]]<=40%,"CRESCIMENTO",IF(Table_1[[#This Row],[PAYOUT]]<=60%,"INDEFINIDO","DIVIDENDOS")) | Q16: =VLOOKUP(Table_1[[#This Row],[AÇÕES]],'Dados Status Invest'!A:R,18,0)/100 | R16: =VLOOKUP(Table_1[[#This Row],[AÇÕES]],'Dados Status Invest'!A:Y,25,0)/100 | S16: =(1-Table_1[[#This Row],[PAYOUT]])*Table_1[[#This Row],[ROE]] | T16: =AVERAGE(Table_1[[#This Row],[CAGR LUCRO 5A]],Table_1[[#This Row],[CRESCIMENTO DAMODARAN]]) | U16: =(Table_1[[#This Row],[PREÇO JUSTO BAZIN]]-Table_1[[#This Row],[PREÇO]])/Table_1[[#This Row],[PREÇO JUSTO BAZIN]] | V16: =Table_1[[#This Row],[DPA]]/6% | W16: =Table_1[[#This Row],[PREÇO JUSTO BAZIN]]/(1+Table_1[[#This Row],[MARGEM DE DESCONTO]]) | X16: =(Table_1[[#This Row],[PREÇO JUSTO GRAHAM]]-Table_1[[#This Row],[PREÇO]])/Table_1[[#This Row],[PREÇO JUSTO GRAHAM]] | Y16: =(22.5*Table_1[[#This Row],[LPA]]*Table_1[[#This Row],[VPA]])^0.5 | Z16: =Table_1[[#This Row],[PREÇO JUSTO GRAHAM]]/(1+Table_1[[#This Row],[MARGEM DE DESCONTO]]) | AA16: =(Table_1[[#This Row],[PREÇO JUSTO GORDON]]-Table_1[[#This Row],[PREÇO]])/Table_1[[#This Row],[PREÇO JUSTO GORDON]] | AB16: =Table_1[[#This Row],[DPA]]*(1+Table_1[[#This Row],[MÉDIA DE CRESCIMENTO]]) | AC16: =Table_1[[#This Row],[D1]]/(Table_1[[#This Row],[RISCO]]-Table_1[[#This Row],[MÉDIA DE CRESCIMENTO]]) | AD16: =Table_1[[#This Row],[PREÇO JUSTO GORDON]]/(1+Table_1[[#This Row],[MARGEM DE DESCONTO]]) | AE16: =Table_1[[#This Row],[P/L]]/Table_1[[#This Row],[MÉDIA DE CRESCIMENTO]] | AG16: REGRA DE COLORAÇÃO | AH16: BAZIN | AI16: GRAHAM | AJ16: GORDON | AK16: PEG
B17: ='Dados Status Invest'!A3 | C17: =VLOOKUP(Table_1[[#This Row],[AÇÕES]],'Classificação B3'!A:B,2,0) | D17: =VLOOKUP(Table_1[[#This Row],[AÇÕES]],'Classificação B3'!A:D,4,0) | E17: =VLOOKUP(Table_1[[#This Row],[AÇÕES]],'Classificação B3'!A:F,6,0) | F17: =VLOOKUP(Table_1[[#This Row],[AÇÕES]],'Classificação B3'!A:G,7,0) | G17: =VLOOKUP(Table_1[[#This Row],[AÇÕES]],'Dados Status Invest'!A:B,2,0) | H17: =VLOOKUP(Table_1[[#This Row],[AÇÕES]],'Dados Status Invest'!A:C,3,0)/100 | I17: =VLOOKUP(Table_1[[#This Row],[AÇÕES]],'Dados Status Invest'!A:D,4,0)/100 | J17: =VLOOKUP(Table_1[[#This Row],[AÇÕES]],'Dados Status Invest'!A:AB,28,0) | K17: =VLOOKUP(Table_1[[#This Row],[AÇÕES]],'Dados Status Invest'!A:AA,27,0) | L17: =Table_1[[#This Row],[PREÇO]]*Table_1[[#This Row],[DY]] | M17: =$E$13 | N17: 0.3 | O17: =Table_1[[#This Row],[DPA]]/Table_1[[#This Row],[LPA]] | P17: =IF(Table_1[[#This Row],[PAYOUT]]<=40%,"CRESCIMENTO",IF(Table_1[[#This Row],[PAYOUT]]<=60%,"INDEFINIDO","DIVIDENDOS")) | Q17: =VLOOKUP(Table_1[[#This Row],[AÇÕES]],'Dados Status Invest'!A:R,18,0)/100 | R17: =VLOOKUP(Table_1[[#This Row],[AÇÕES]],'Dados Status Invest'!A:Y,25,0)/100 | S17: =(1-Table_1[[#This Row],[PAYOUT]])*Table_1[[#This Row],[ROE]] | T17: =AVERAGE(Table_1[[#This Row],[CAGR LUCRO 5A]],Table_1[[#This Row],[CRESCIMENTO DAMODARAN]]) | U17: =(Table_1[[#This Row],[PREÇO JUSTO BAZIN]]-Table_1[[#This Row],[PREÇO]])/Table_1[[#This Row],[PREÇO JUSTO BAZIN]] | V17: =Table_1[[#This Row],[DPA]]/6% | W17: =Table_1[[#This Row],[PREÇO JUSTO BAZIN]]/(1+Table_1[[#This Row],[MARGEM DE DESCONTO]]) | X17: =(Table_1[[#This Row],[PREÇO JUSTO GRAHAM]]-Table_1[[#This Row],[PREÇO]])/Table_1[[#This Row],[PREÇO JUSTO GRAHAM]] | Y17: =(22.5*Table_1[[#This Row],[LPA]]*Table_1[[#This Row],[VPA]])^0.5 | Z17: =Table_1[[#This Row],[PREÇO JUSTO GRAHAM]]/(1+Table_1[[#This Row],[MARGEM DE DESCONTO]]) | AA17: =(Table_1[[#This Row],[PREÇO JUSTO GORDON]]-Table_1[[#This Row],[PREÇO]])/Table_1[[#This Row],[PREÇO JUSTO GORDON]] | AB17: =Table_1[[#This Row],[DPA]]*(1+Table_1[[#This Row],[MÉDIA DE CRESCIMENTO]]) | AC17: =Table_1[[#This Row],[D1]]/(Table_1[[#This Row],[RISCO]]-Table_1[[#This Row],[MÉDIA DE CRESCIMENTO]]) | AD17: =Table_1[[#This Row],[PREÇO JUSTO GORDON]]/(1+Table_1[[#This Row],[MARGEM DE DESCONTO]]) | AE17: =Table_1[[#This Row],[P/L]]/Table_1[[#This Row],[MÉDIA DE CRESCIMENTO]] | AH17: ACIMA DE 30% | AI17: ACIMA DE 30% | AJ17: ACIMA DE 30% | AK17: ENTRE 0 E 0,5
B18: ='Dados Status Invest'!A4 | C18: =VLOOKUP(Table_1[[#This Row],[AÇÕES]],'Classificação B3'!A:B,2,0) | D18: =VLOOKUP(Table_1[[#This Row],[AÇÕES]],'Classificação B3'!A:D,4,0) | E18: =VLOOKUP(Table_1[[#This Row],[AÇÕES]],'Classificação B3'!A:F,6,0) | F18: =VLOOKUP(Table_1[[#This Row],[AÇÕES]],'Classificação B3'!A:G,7,0) | G18: =VLOOKUP(Table_1[[#This Row],[AÇÕES]],'Dados Status Invest'!A:B,2,0) | H18: =VLOOKUP(Table_1[[#This Row],[AÇÕES]],'Dados Status Invest'!A:C,3,0)/100 | I18: =VLOOKUP(Table_1[[#This Row],[AÇÕES]],'Dados Status Invest'!A:D,4,0)/100 | J18: =VLOOKUP(Table_1[[#This Row],[AÇÕES]],'Dados Status Invest'!A:AB,28,0) | K18: =VLOOKUP(Table_1[[#This Row],[AÇÕES]],'Dados Status Invest'!A:AA,27,0) | L18: =Table_1[[#This Row],[PREÇO]]*Table_1[[#This Row],[DY]] | M18: =$E$13 | N18: 0.3 | O18: =Table_1[[#This Row],[DPA]]/Table_1[[#This Row],[LPA]] | P18: =IF(Table_1[[#This Row],[PAYOUT]]<=40%,"CRESCIMENTO",IF(Table_1[[#This Row],[PAYOUT]]<=60%,"INDEFINIDO","DIVIDENDOS")) | Q18: =VLOOKUP(Table_1[[#This Row],[AÇÕES]],'Dados Status Invest'!A:R,18,0)/100 | R18: =VLOOKUP(Table_1[[#This Row],[AÇÕES]],'Dados Status Invest'!A:Y,25,0)/100 | S18: =(1-Table_1[[#This Row],[PAYOUT]])*Table_1[[#This Row],[ROE]] | T18: =AVERAGE(Table_1[[#This Row],[CAGR LUCRO 5A]],Table_1[[#This Row],[CRESCIMENTO DAMODARAN]]) | U18: =(Table_1[[#This Row],[PREÇO JUSTO BAZIN]]-Table_1[[#This Row],[PREÇO]])/Table_1[[#This Row],[PREÇO JUSTO BAZIN]] | V18: =Table_1[[#This Row],[DPA]]/6% | W18: =Table_1[[#This Row],[PREÇO JUSTO BAZIN]]/(1+Table_1[[#This Row],[MARGEM DE DESCONTO]]) | X18: =(Table_1[[#This Row],[PREÇO JUSTO GRAHAM]]-Table_1[[#This Row],[PREÇO]])/Table_1[[#This Row],[PREÇO JUSTO GRAHAM]] | Y18: =(22.5*Table_1[[#This Row],[LPA]]*Table_1[[#This Row],[VPA]])^0.5 | Z18: =Table_1[[#This Row],[PREÇO JUSTO GRAHAM]]/(1+Table_1[[#This Row],[MARGEM DE DESCONTO]]) | AA18: =(Table_1[[#This Row],[PREÇO JUSTO GORDON]]-Table_1[[#This Row],[PREÇO]])/Table_1[[#This Row],[PREÇO JUSTO GORDON]] | AB18: =Table_1[[#This Row],[DPA]]*(1+Table_1[[#This Row],[MÉDIA DE CRESCIMENTO]]) | AC18: =Table_1[[#This Row],[D1]]/(Table_1[[#This Row],[RISCO]]-Table_1[[#This Row],[MÉDIA DE CRESCIMENTO]]) | AD18: =Table_1[[#This Row],[PREÇO JUSTO GORDON]]/(1+Table_1[[#This Row],[MARGEM DE DESCONTO]]) | AE18: =Table_1[[#This Row],[P/L]]/Table_1[[#This Row],[MÉDIA DE CRESCIMENTO]]
B19: ='Dados Status Invest'!A5 | C19: =VLOOKUP(Table_1[[#This Row],[AÇÕES]],'Classificação B3'!A:B,2,0) | D19: =VLOOKUP(Table_1[[#This Row],[AÇÕES]],'Classificação B3'!A:D,4,0) | E19: =VLOOKUP(Table_1[[#This Row],[AÇÕES]],'Classificação B3'!A:F,6,0) | F19: =VLOOKUP(Table_1[[#This Row],[AÇÕES]],'Classificação B3'!A:G,7,0) | G19: =VLOOKUP(Table_1[[#This Row],[AÇÕES]],'Dados Status Invest'!A:B,2,0) | H19: =VLOOKUP(Table_1[[#This Row],[AÇÕES]],'Dados Status Invest'!A:C,3,0)/100 | I19: =VLOOKUP(Table_1[[#This Row],[AÇÕES]],'Dados Status Invest'!A:D,4,0)/100 | J19: =VLOOKUP(Table_1[[#This Row],[AÇÕES]],'Dados Status Invest'!A:AB,28,0) | K19: =VLOOKUP(Table_1[[#This Row],[AÇÕES]],'Dados Status Invest'!A:AA,27,0) | L19: =Table_1[[#This Row],[PREÇO]]*Table_1[[#This Row],[DY]] | M19: =$E$13 | N19: 0.3 | O19: =Table_1[[#This Row],[DPA]]/Table_1[[#This Row],[LPA]] | P19: =IF(Table_1[[#This Row],[PAYOUT]]<=40%,"CRESCIMENTO",IF(Table_1[[#This Row],[PAYOUT]]<=60%,"INDEFINIDO","DIVIDENDOS")) | Q19: =VLOOKUP(Table_1[[#This Row],[AÇÕES]],'Dados Status Invest'!A:R,18,0)/100 | R19: =VLOOKUP(Table_1[[#This Row],[AÇÕES]],'Dados Status Invest'!A:Y,25,0)/100 | S19: =(1-Table_1[[#This Row],[PAYOUT]])*Table_1[[#This Row],[ROE]] | T19: =AVERAGE(Table_1[[#This Row],[CAGR LUCRO 5A]],Table_1[[#This Row],[CRESCIMENTO DAMODARAN]]) | U19: =(Table_1[[#This Row],[PREÇO JUSTO BAZIN]]-Table_1[[#This Row],[PREÇO]])/Table_1[[#This Row],[PREÇO JUSTO BAZIN]] | V19: =Table_1[[#This Row],[DPA]]/6% | W19: =Table_1[[#This Row],[PREÇO JUSTO BAZIN]]/(1+Table_1[[#This Row],[MARGEM DE DESCONTO]]) | X19: =(Table_1[[#This Row],[PREÇO JUSTO GRAHAM]]-Table_1[[#This Row],[PREÇO]])/Table_1[[#This Row],[PREÇO JUSTO GRAHAM]] | Y19: =(22.5*Table_1[[#This Row],[LPA]]*Table_1[[#This Row],[VPA]])^0.5 | Z19: =Table_1[[#This Row],[PREÇO JUSTO GRAHAM]]/(1+Table_1[[#This Row],[MARGEM DE DESCONTO]]) | AA19: =(Table_1[[#This Row],[PREÇO JUSTO GORDON]]-Table_1[[#This Row],[PREÇO]])/Table_1[[#This Row],[PREÇO JUSTO GORDON]] | AB19: =Table_1[[#This Row],[DPA]]*(1+Table_1[[#This Row],[MÉDIA DE CRESCIMENTO]]) | AC19: =Table_1[[#This Row],[D1]]/(Table_1[[#This Row],[RISCO]]-Table_1[[#This Row],[MÉDIA DE CRESCIMENTO]]) | AD19: =Table_1[[#This Row],[PREÇO JUSTO GORDON]]/(1+Table_1[[#This Row],[MARGEM DE DESCONTO]]) | AE19: =Table_1[[#This Row],[P/L]]/Table_1[[#This Row],[MÉDIA DE CRESCIMENTO]] | AH19: ENTRE 0 E 30% | AI19: ENTRE 0 E 30% | AJ19: ENTRE 0 E 30% | AK19: ENTRE 0,5 E 2
B20: ='Dados Status Invest'!A6 | C20: =VLOOKUP(Table_1[[#This Row],[AÇÕES]],'Classificação B3'!A:B,2,0) | D20: =VLOOKUP(Table_1[[#This Row],[AÇÕES]],'Classificação B3'!A:D,4,0) | E20: =VLOOKUP(Table_1[[#This Row],[AÇÕES]],'Classificação B3'!A:F,6,0) | F20: =VLOOKUP(Table_1[[#This Row],[AÇÕES]],'Classificação B3'!A:G,7,0) | G20: =VLOOKUP(Table_1[[#This Row],[AÇÕES]],'Dados Status Invest'!A:B,2,0) | H20: =VLOOKUP(Table_1[[#This Row],[AÇÕES]],'Dados Status Invest'!A:C,3,0)/100 | I20: =VLOOKUP(Table_1[[#This Row],[AÇÕES]],'Dados Status Invest'!A:D,4,0)/100 | J20: =VLOOKUP(Table_1[[#This Row],[AÇÕES]],'Dados Status Invest'!A:AB,28,0) | K20: =VLOOKUP(Table_1[[#This Row],[AÇÕES]],'Dados Status Invest'!A:AA,27,0) | L20: =Table_1[[#This Row],[PREÇO]]*Table_1[[#This Row],[DY]] | M20: =$E$13 | N20: 0.3 | O20: =Table_1[[#This Row],[DPA]]/Table_1[[#This Row],[LPA]] | P20: =IF(Table_1[[#This Row],[PAYOUT]]<=40%,"CRESCIMENTO",IF(Table_1[[#This Row],[PAYOUT]]<=60%,"INDEFINIDO","DIVIDENDOS")) | Q20: =VLOOKUP(Table_1[[#This Row],[AÇÕES]],'Dados Status Invest'!A:R,18,0)/100 | R20: =VLOOKUP(Table_1[[#This Row],[AÇÕES]],'Dados Status Invest'!A:Y,25,0)/100 | S20: =(1-Table_1[[#This Row],[PAYOUT]])*Table_1[[#This Row],[ROE]] | T20: =AVERAGE(Table_1[[#This Row],[CAGR LUCRO 5A]],Table_1[[#This Row],[CRESCIMENTO DAMODARAN]]) | U20: =(Table_1[[#This Row],[PREÇO JUSTO BAZIN]]-Table_1[[#This Row],[PREÇO]])/Table_1[[#This Row],[PREÇO JUSTO BAZIN]] | V20: =Table_1[[#This Row],[DPA]]/6% | W20: =Table_1[[#This Row],[PREÇO JUSTO BAZIN]]/(1+Table_1[[#This Row],[MARGEM DE DESCONTO]]) | X20: =(Table_1[[#This Row],[PREÇO JUSTO GRAHAM]]-Table_1[[#This Row],[PREÇO]])/Table_1[[#This Row],[PREÇO JUSTO GRAHAM]] | Y20: =(22.5*Table_1[[#This Row],[LPA]]*Table_1[[#This Row],[VPA]])^0.5 | Z20: =Table_1[[#This Row],[PREÇO JUSTO GRAHAM]]/(1+Table_1[[#This Row],[MARGEM DE DESCONTO]]) | AA20: =(Table_1[[#This Row],[PREÇO JUSTO GORDON]]-Table_1[[#This Row],[PREÇO]])/Table_1[[#This Row],[PREÇO JUSTO GORDON]] | AB20: =Table_1[[#This Row],[DPA]]*(1+Table_1[[#This Row],[MÉDIA DE CRESCIMENTO]]) | AC20: =Table_1[[#This Row],[D1]]/(Table_1[[#This Row],[RISCO]]-Table_1[[#This Row],[MÉDIA DE CRESCIMENTO]]) | AD20: =Table_1[[#This Row],[PREÇO JUSTO GORDON]]/(1+Table_1[[#This Row],[MARGEM DE DESCONTO]]) | AE20: =Table_1[[#This Row],[P/L]]/Table_1[[#This Row],[MÉDIA DE CRESCIMENTO]]
B21: ='Dados Status Invest'!A7 | C21: =VLOOKUP(Table_1[[#This Row],[AÇÕES]],'Classificação B3'!A:B,2,0) | D21: =VLOOKUP(Table_1[[#This Row],[AÇÕES]],'Classificação B3'!A:D,4,0) | E21: =VLOOKUP(Table_1[[#This Row],[AÇÕES]],'Classificação B3'!A:F,6,0) | F21: =VLOOKUP(Table_1[[#This Row],[AÇÕES]],'Classificação B3'!A:G,7,0) | G21: =VLOOKUP(Table_1[[#This Row],[AÇÕES]],'Dados Status Invest'!A:B,2,0) | H21: =VLOOKUP(Table_1[[#This Row],[AÇÕES]],'Dados Status Invest'!A:C,3,0)/100 | I21: =VLOOKUP(Table_1[[#This Row],[AÇÕES]],'Dados Status Invest'!A:D,4,0)/100 | J21: =VLOOKUP(Table_1[[#This Row],[AÇÕES]],'Dados Status Invest'!A:AB,28,0) | K21: =VLOOKUP(Table_1[[#This Row],[AÇÕES]],'Dados Status Invest'!A:AA,27,0) | L21: =Table_1[[#This Row],[PREÇO]]*Table_1[[#This Row],[DY]] | M21: =$E$13 | N21: 0.3 | O21: =Table_1[[#This Row],[DPA]]/Table_1[[#This Row],[LPA]] | P21: =IF(Table_1[[#This Row],[PAYOUT]]<=40%,"CRESCIMENTO",IF(Table_1[[#This Row],[PAYOUT]]<=60%,"INDEFINIDO","DIVIDENDOS")) | Q21: =VLOOKUP(Table_1[[#This Row],[AÇÕES]],'Dados Status Invest'!A:R,18,0)/100 | R21: =VLOOKUP(Table_1[[#This Row],[AÇÕES]],'Dados Status Invest'!A:Y,25,0)/100 | S21: =(1-Table_1[[#This Row],[PAYOUT]])*Table_1[[#This Row],[ROE]] | T21: =AVERAGE(Table_1[[#This Row],[CAGR LUCRO 5A]],Table_1[[#This Row],[CRESCIMENTO DAMODARAN]]) | U21: =(Table_1[[#This Row],[PREÇO JUSTO BAZIN]]-Table_1[[#This Row],[PREÇO]])/Table_1[[#This Row],[PREÇO JUSTO BAZIN]] | V21: =Table_1[[#This Row],[DPA]]/6% | W21: =Table_1[[#This Row],[PREÇO JUSTO BAZIN]]/(1+Table_1[[#This Row],[MARGEM DE DESCONTO]]) | X21: =(Table_1[[#This Row],[PREÇO JUSTO GRAHAM]]-Table_1[[#This Row],[PREÇO]])/Table_1[[#This Row],[PREÇO JUSTO GRAHAM]] | Y21: =(22.5*Table_1[[#This Row],[LPA]]*Table_1[[#This Row],[VPA]])^0.5 | Z21: =Table_1[[#This Row],[PREÇO JUSTO GRAHAM]]/(1+Table_1[[#This Row],[MARGEM DE DESCONTO]]) | AA21: =(Table_1[[#This Row],[PREÇO JUSTO GORDON]]-Table_1[[#This Row],[PREÇO]])/Table_1[[#This Row],[PREÇO JUSTO GORDON]] | AB21: =Table_1[[#This Row],[DPA]]*(1+Table_1[[#This Row],[MÉDIA DE CRESCIMENTO]]) | AC21: =Table_1[[#This Row],[D1]]/(Table_1[[#This Row],[RISCO]]-Table_1[[#This Row],[MÉDIA DE CRESCIMENTO]]) | AD21: =Table_1[[#This Row],[PREÇO JUSTO GORDON]]/(1+Table_1[[#This Row],[MARGEM DE DESCONTO]]) | AE21: =Table_1[[#This Row],[P/L]]/Table_1[[#This Row],[MÉDIA DE CRESCIMENTO]]
B22: ='Dados Status Invest'!A8 | C22: =VLOOKUP(Table_1[[#This Row],[AÇÕES]],'Classificação B3'!A:B,2,0) | D22: =VLOOKUP(Table_1[[#This Row],[AÇÕES]],'Classificação B3'!A:D,4,0) | E22: =VLOOKUP(Table_1[[#This Row],[AÇÕES]],'Classificação B3'!A:F,6,0) | F22: =VLOOKUP(Table_1[[#This Row],[AÇÕES]],'Classificação B3'!A:G,7,0) | G22: =VLOOKUP(Table_1[[#This Row],[AÇÕES]],'Dados Status Invest'!A:B,2,0) | H22: =VLOOKUP(Table_1[[#This Row],[AÇÕES]],'Dados Status Invest'!A:C,3,0)/100 | I22: =VLOOKUP(Table_1[[#This Row],[AÇÕES]],'Dados Status Invest'!A:D,4,0)/100 | J22: =VLOOKUP(Table_1[[#This Row],[AÇÕES]],'Dados Status Invest'!A:AB,28,0) | K22: =VLOOKUP(Table_1[[#This Row],[AÇÕES]],'Dados Status Invest'!A:AA,27,0) | L22: =Table_1[[#This Row],[PREÇO]]*Table_1[[#This Row],[DY]] | M22: =$E$13 | N22: 0.3 | O22: =Table_1[[#This Row],[DPA]]/Table_1[[#This Row],[LPA]] | P22: =IF(Table_1[[#This Row],[PAYOUT]]<=40%,"CRESCIMENTO",IF(Table_1[[#This Row],[PAYOUT]]<=60%,"INDEFINIDO","DIVIDENDOS")) | Q22: =VLOOKUP(Table_1[[#This Row],[AÇÕES]],'Dados Status Invest'!A:R,18,0)/100 | R22: =VLOOKUP(Table_1[[#This Row],[AÇÕES]],'Dados Status Invest'!A:Y,25,0)/100 | S22: =(1-Table_1[[#This Row],[PAYOUT]])*Table_1[[#This Row],[ROE]] | T22: =AVERAGE(Table_1[[#This Row],[CAGR LUCRO 5A]],Table_1[[#This Row],[CRESCIMENTO DAMODARAN]]) | U22: =(Table_1[[#This Row],[PREÇO JUSTO BAZIN]]-Table_1[[#This Row],[PREÇO]])/Table_1[[#This Row],[PREÇO JUSTO BAZIN]] | V22: =Table_1[[#This Row],[DPA]]/6% | W22: =Table_1[[#This Row],[PREÇO JUSTO BAZIN]]/(1+Table_1[[#This Row],[MARGEM DE DESCONTO]]) | X22: =(Table_1[[#This Row],[PREÇO JUSTO GRAHAM]]-Table_1[[#This Row],[PREÇO]])/Table_1[[#This Row],[PREÇO JUSTO GRAHAM]] | Y22: =(22.5*Table_1[[#This Row],[LPA]]*Table_1[[#This Row],[VPA]])^0.5 | Z22: =Table_1[[#This Row],[PREÇO JUSTO GRAHAM]]/(1+Table_1[[#This Row],[MARGEM DE DESCONTO]]) | AA22: =(Table_1[[#This Row],[PREÇO JUSTO GORDON]]-Table_1[[#This Row],[PREÇO]])/Table_1[[#This Row],[PREÇO JUSTO GORDON]] | AB22: =Table_1[[#This Row],[DPA]]*(1+Table_1[[#This Row],[MÉDIA DE CRESCIMENTO]]) | AC22: =Table_1[[#This Row],[D1]]/(Table_1[[#This Row],[RISCO]]-Table_1[[#This Row],[MÉDIA DE CRESCIMENTO]]) | AD22: =Table_1[[#This Row],[PREÇO JUSTO GORDON]]/(1+Table_1[[#This Row],[MARGEM DE DESCONTO]]) | AE22: =Table_1[[#This Row],[P/L]]/Table_1[[#This Row],[MÉDIA DE CRESCIMENTO]] | AH22: ABAIXO DE ZERO | AI22: ABAIXO DE ZERO | AJ22: ABAIXO DE ZERO | AK22: ABAIXO DE 0 OU ACIMA DE 2
B23: ='Dados Status Invest'!A9 | C23: =VLOOKUP(Table_1[[#This Row],[AÇÕES]],'Classificação B3'!A:B,2,0) | D23: =VLOOKUP(Table_1[[#This Row],[AÇÕES]],'Classificação B3'!A:D,4,0) | E23: =VLOOKUP(Table_1[[#This Row],[AÇÕES]],'Classificação B3'!A:F,6,0) | F23: =VLOOKUP(Table_1[[#This Row],[AÇÕES]],'Classificação B3'!A:G,7,0) | G23: =VLOOKUP(Table_1[[#This Row],[AÇÕES]],'Dados Status Invest'!A:B,2,0) | H23: =VLOOKUP(Table_1[[#This Row],[AÇÕES]],'Dados Status Invest'!A:C,3,0)/100 | I23: =VLOOKUP(Table_1[[#This Row],[AÇÕES]],'Dados Status Invest'!A:D,4,0)/100 | J23: =VLOOKUP(Table_1[[#This Row],[AÇÕES]],'Dados Status Invest'!A:AB,28,0) | K23: =VLOOKUP(Table_1[[#This Row],[AÇÕES]],'Dados Status Invest'!A:AA,27,0) | L23: =Table_1[[#This Row],[PREÇO]]*Table_1[[#This Row],[DY]] | M23: =$E$13 | N23: 0.3 | O23: =Table_1[[#This Row],[DPA]]/Table_1[[#This Row],[LPA]] | P23: =IF(Table_1[[#This Row],[PAYOUT]]<=40%,"CRESCIMENTO",IF(Table_1[[#This Row],[PAYOUT]]<=60%,"INDEFINIDO","DIVIDENDOS")) | Q23: =VLOOKUP(Table_1[[#This Row],[AÇÕES]],'Dados Status Invest'!A:R,18,0)/100 | R23: =VLOOKUP(Table_1[[#This Row],[AÇÕES]],'Dados Status Invest'!A:Y,25,0)/100 | S23: =(1-Table_1[[#This Row],[PAYOUT]])*Table_1[[#This Row],[ROE]] | T23: =AVERAGE(Table_1[[#This Row],[CAGR LUCRO 5A]],Table_1[[#This Row],[CRESCIMENTO DAMODARAN]]) | U23: =(Table_1[[#This Row],[PREÇO JUSTO BAZIN]]-Table_1[[#This Row],[PREÇO]])/Table_1[[#This Row],[PREÇO JUSTO BAZIN]] | V23: =Table_1[[#This Row],[DPA]]/6% | W23: =Table_1[[#This Row],[PREÇO JUSTO BAZIN]]/(1+Table_1[[#This Row],[MARGEM DE DESCONTO]]) | X23: =(Table_1[[#This Row],[PREÇO JUSTO GRAHAM]]-Table_1[[#This Row],[PREÇO]])/Table_1[[#This Row],[PREÇO JUSTO GRAHAM]] | Y23: =(22.5*Table_1[[#This Row],[LPA]]*Table_1[[#This Row],[VPA]])^0.5 | Z23: =Table_1[[#This Row],[PREÇO JUSTO GRAHAM]]/(1+Table_1[[#This Row],[MARGEM DE DESCONTO]]) | AA23: =(Table_1[[#This Row],[PREÇO JUSTO GORDON]]-Table_1[[#This Row],[PREÇO]])/Table_1[[#This Row],[PREÇO JUSTO GORDON]] | AB23: =Table_1[[#This Row],[DPA]]*(1+Table_1[[#This Row],[MÉDIA DE CRESCIMENTO]]) | AC23: =Table_1[[#This Row],[D1]]/(Table_1[[#This Row],[RISCO]]-Table_1[[#This Row],[MÉDIA DE CRESCIMENTO]]) | AD23: =Table_1[[#This Row],[PREÇO JUSTO GORDON]]/(1+Table_1[[#This Row],[MARGEM DE DESCONTO]]) | AE23: =Table_1[[#This Row],[P/L]]/Table_1[[#This Row],[MÉDIA DE CRESCIMENTO]]
B24: ='Dados Status Invest'!A10 | C24: =VLOOKUP(Table_1[[#This Row],[AÇÕES]],'Classificação B3'!A:B,2,0) | D24: =VLOOKUP(Table_1[[#This Row],[AÇÕES]],'Classificação B3'!A:D,4,0) | E24: =VLOOKUP(Table_1[[#This Row],[AÇÕES]],'Classificação B3'!A:F,6,0) | F24: =VLOOKUP(Table_1[[#This Row],[AÇÕES]],'Classificação B3'!A:G,7,0) | G24: =VLOOKUP(Table_1[[#This Row],[AÇÕES]],'Dados Status Invest'!A:B,2,0) | H24: =VLOOKUP(Table_1[[#This Row],[AÇÕES]],'Dados Status Invest'!A:C,3,0)/100 | I24: =VLOOKUP(Table_1[[#This Row],[AÇÕES]],'Dados Status Invest'!A:D,4,0)/100 | J24: =VLOOKUP(Table_1[[#This Row],[AÇÕES]],'Dados Status Invest'!A:AB,28,0) | K24: =VLOOKUP(Table_1[[#This Row],[AÇÕES]],'Dados Status Invest'!A:AA,27,0) | L24: =Table_1[[#This Row],[PREÇO]]*Table_1[[#This Row],[DY]] | M24: =$E$13 | N24: 0.3 | O24: =Table_1[[#This Row],[DPA]]/Table_1[[#This Row],[LPA]] | P24: =IF(Table_1[[#This Row],[PAYOUT]]<=40%,"CRESCIMENTO",IF(Table_1[[#This Row],[PAYOUT]]<=60%,"INDEFINIDO","DIVIDENDOS")) | Q24: =VLOOKUP(Table_1[[#This Row],[AÇÕES]],'Dados Status Invest'!A:R,18,0)/100 | R24: =VLOOKUP(Table_1[[#This Row],[AÇÕES]],'Dados Status Invest'!A:Y,25,0)/100 | S24: =(1-Table_1[[#This Row],[PAYOUT]])*Table_1[[#This Row],[ROE]] | T24: =AVERAGE(Table_1[[#This Row],[CAGR LUCRO 5A]],Table_1[[#This Row],[CRESCIMENTO DAMODARAN]]) | U24: =(Table_1[[#This Row],[PREÇO JUSTO BAZIN]]-Table_1[[#This Row],[PREÇO]])/Table_1[[#This Row],[PREÇO JUSTO BAZIN]] | V24: =Table_1[[#This Row],[DPA]]/6% | W24: =Table_1[[#This Row],[PREÇO JUSTO BAZIN]]/(1+Table_1[[#This Row],[MARGEM DE DESCONTO]]) | X24: =(Table_1[[#This Row],[PREÇO JUSTO GRAHAM]]-Table_1[[#This Row],[PREÇO]])/Table_1[[#This Row],[PREÇO JUSTO GRAHAM]] | Y24: =(22.5*Table_1[[#This Row],[LPA]]*Table_1[[#This Row],[VPA]])^0.5 | Z24: =Table_1[[#This Row],[PREÇO JUSTO GRAHAM]]/(1+Table_1[[#This Row],[MARGEM DE DESCONTO]]) | AA24: =(Table_1[[#This Row],[PREÇO JUSTO GORDON]]-Table_1[[#This Row],[PREÇO]])/Table_1[[#This Row],[PREÇO JUSTO GORDON]] | AB24: =Table_1[[#This Row],[DPA]]*(1+Table_1[[#This Row],[MÉDIA DE CRESCIMENTO]]) | AC24: =Table_1[[#This Row],[D1]]/(Table_1[[#This Row],[RISCO]]-Table_1[[#This Row],[MÉDIA DE CRESCIMENTO]]) | AD24: =Table_1[[#This Row],[PREÇO JUSTO GORDON]]/(1+Table_1[[#This Row],[MARGEM DE DESCONTO]]) | AE24: =Table_1[[#This Row],[P/L]]/Table_1[[#This Row],[MÉDIA DE CRESCIMENTO]]
B25: ='Dados Status Invest'!A11 | C25: =VLOOKUP(Table_1[[#This Row],[AÇÕES]],'Classificação B3'!A:B,2,0) | D25: =VLOOKUP(Table_1[[#This Row],[AÇÕES]],'Classificação B3'!A:D,4,0) | E25: =VLOOKUP(Table_1[[#This Row],[AÇÕES]],'Classificação B3'!A:F,6,0) | F25: =VLOOKUP(Table_1[[#This Row],[AÇÕES]],'Classificação B3'!A:G,7,0) | G25: =VLOOKUP(Table_1[[#This Row],[AÇÕES]],'Dados Status Invest'!A:B,2,0) | H25: =VLOOKUP(Table_1[[#This Row],[AÇÕES]],'Dados Status Invest'!A:C,3,0)/100 | I25: =VLOOKUP(Table_1[[#This Row],[AÇÕES]],'Dados Status Invest'!A:D,4,0)/100 | J25: =VLOOKUP(Table_1[[#This Row],[AÇÕES]],'Dados Status Invest'!A:AB,28,0) | K25: =VLOOKUP(Table_1[[#This Row],[AÇÕES]],'Dados Status Invest'!A:AA,27,0) | L25: =Table_1[[#This Row],[PREÇO]]*Table_1[[#This Row],[DY]] | M25: =$E$13 | N25: 0.3 | O25: =Table_1[[#This Row],[DPA]]/Table_1[[#This Row],[LPA]] | P25: =IF(Table_1[[#This Row],[PAYOUT]]<=40%,"CRESCIMENTO",IF(Table_1[[#This Row],[PAYOUT]]<=60%,"INDEFINIDO","DIVIDENDOS")) | Q25: =VLOOKUP(Table_1[[#This Row],[AÇÕES]],'Dados Status Invest'!A:R,18,0)/100 | R25: =VLOOKUP(Table_1[[#This Row],[AÇÕES]],'Dados Status Invest'!A:Y,25,0)/100 | S25: =(1-Table_1[[#This Row],[PAYOUT]])*Table_1[[#This Row],[ROE]] | T25: =AVERAGE(Table_1[[#This Row],[CAGR LUCRO 5A]],Table_1[[#This Row],[CRESCIMENTO DAMODARAN]]) | U25: =(Table_1[[#This Row],[PREÇO JUSTO BAZIN]]-Table_1[[#This Row],[PREÇO]])/Table_1[[#This Row],[PREÇO JUSTO BAZIN]] | V25: =Table_1[[#This Row],[DPA]]/6% | W25: =Table_1[[#This Row],[PREÇO JUSTO BAZIN]]/(1+Table_1[[#This Row],[MARGEM DE DESCONTO]]) | X25: =(Table_1[[#This Row],[PREÇO JUSTO GRAHAM]]-Table_1[[#This Row],[PREÇO]])/Table_1[[#This Row],[PREÇO JUSTO GRAHAM]] | Y25: =(22.5*Table_1[[#This Row],[LPA]]*Table_1[[#This Row],[VPA]])^0.5 | Z25: =Table_1[[#This Row],[PREÇO JUSTO GRAHAM]]/(1+Table_1[[#This Row],[MARGEM DE DESCONTO]]) | AA25: =(Table_1[[#This Row],[PREÇO JUSTO GORDON]]-Table_1[[#This Row],[PREÇO]])/Table_1[[#This Row],[PREÇO JUSTO GORDON]] | AB25: =Table_1[[#This Row],[DPA]]*(1+Table_1[[#This Row],[MÉDIA DE CRESCIMENTO]]) | AC25: =Table_1[[#This Row],[D1]]/(Table_1[[#This Row],[RISCO]]-Table_1[[#This Row],[MÉDIA DE CRESCIMENTO]]) | AD25: =Table_1[[#This Row],[PREÇO JUSTO GORDON]]/(1+Table_1[[#This Row],[MARGEM DE DESCONTO]]) | AE25: =Table_1[[#This Row],[P/L]]/Table_1[[#This Row],[MÉDIA DE CRESCIMENTO]] | AG25: MÉDIA CRESCIMENTO
B26: ='Dados Status Invest'!A12 | C26: =VLOOKUP(Table_1[[#This Row],[AÇÕES]],'Classificação B3'!A:B,2,0) | D26: =VLOOKUP(Table_1[[#This Row],[AÇÕES]],'Classificação B3'!A:D,4,0) | E26: =VLOOKUP(Table_1[[#This Row],[AÇÕES]],'Classificação B3'!A:F,6,0) | F26: =VLOOKUP(Table_1[[#This Row],[AÇÕES]],'Classificação B3'!A:G,7,0) | G26: =VLOOKUP(Table_1[[#This Row],[AÇÕES]],'Dados Status Invest'!A:B,2,0) | H26: =VLOOKUP(Table_1[[#This Row],[AÇÕES]],'Dados Status Invest'!A:C,3,0)/100 | I26: =VLOOKUP(Table_1[[#This Row],[AÇÕES]],'Dados Status Invest'!A:D,4,0)/100 | J26: =VLOOKUP(Table_1[[#This Row],[AÇÕES]],'Dados Status Invest'!A:AB,28,0) | K26: =VLOOKUP(Table_1[[#This Row],[AÇÕES]],'Dados Status Invest'!A:AA,27,0) | L26: =Table_1[[#This Row],[PREÇO]]*Table_1[[#This Row],[DY]] | M26: =$E$13 | N26: 0.3 | O26: =Table_1[[#This Row],[DPA]]/Table_1[[#This Row],[LPA]] | P26: =IF(Table_1[[#This Row],[PAYOUT]]<=40%,"CRESCIMENTO",IF(Table_1[[#This Row],[PAYOUT]]<=60%,"INDEFINIDO","DIVIDENDOS")) | Q26: =VLOOKUP(Table_1[[#This Row],[AÇÕES]],'Dados Status Invest'!A:R,18,0)/100 | R26: =VLOOKUP(Table_1[[#This Row],[AÇÕES]],'Dados Status Invest'!A:Y,25,0)/100 | S26: =(1-Table_1[[#This Row],[PAYOUT]])*Table_1[[#This Row],[ROE]] | T26: =AVERAGE(Table_1[[#This Row],[CAGR LUCRO 5A]],Table_1[[#This Row],[CRESCIMENTO DAMODARAN]]) | U26: =(Table_1[[#This Row],[PREÇO JUSTO BAZIN]]-Table_1[[#This Row],[PREÇO]])/Table_1[[#This Row],[PREÇO JUSTO BAZIN]] | V26: =Table_1[[#This Row],[DPA]]/6% | W26: =Table_1[[#This Row],[PREÇO JUSTO BAZIN]]/(1+Table_1[[#This Row],[MARGEM DE DESCONTO]]) | X26: =(Table_1[[#This Row],[PREÇO JUSTO GRAHAM]]-Table_1[[#This Row],[PREÇO]])/Table_1[[#This Row],[PREÇO JUSTO GRAHAM]] | Y26: =(22.5*Table_1[[#This Row],[LPA]]*Table_1[[#This Row],[VPA]])^0.5 | Z26: =Table_1[[#This Row],[PREÇO JUSTO GRAHAM]]/(1+Table_1[[#This Row],[MARGEM DE DESCONTO]]) | AA26: =(Table_1[[#This Row],[PREÇO JUSTO GORDON]]-Table_1[[#This Row],[PREÇO]])/Table_1[[#This Row],[PREÇO JUSTO GORDON]] | AB26: =Table_1[[#This Row],[DPA]]*(1+Table_1[[#This Row],[MÉDIA DE CRESCIMENTO]]) | AC26: =Table_1[[#This Row],[D1]]/(Table_1[[#This Row],[RISCO]]-Table_1[[#This Row],[MÉDIA DE CRESCIMENTO]]) | AD26: =Table_1[[#This Row],[PREÇO JUSTO GORDON]]/(1+Table_1[[#This Row],[MARGEM DE DESCONTO]]) | AE26: =Table_1[[#This Row],[P/L]]/Table_1[[#This Row],[MÉDIA DE CRESCIMENTO]] | AH26: Abaixo de Zero
B27: ='Dados Status Invest'!A13 | C27: =VLOOKUP(Table_1[[#This Row],[AÇÕES]],'Classificação B3'!A:B,2,0) | D27: =VLOOKUP(Table_1[[#This Row],[AÇÕES]],'Classificação B3'!A:D,4,0) | E27: =VLOOKUP(Table_1[[#This Row],[AÇÕES]],'Classificação B3'!A:F,6,0) | F27: =VLOOKUP(Table_1[[#This Row],[AÇÕES]],'Classificação B3'!A:G,7,0) | G27: =VLOOKUP(Table_1[[#This Row],[AÇÕES]],'Dados Status Invest'!A:B,2,0) | H27: =VLOOKUP(Table_1[[#This Row],[AÇÕES]],'Dados Status Invest'!A:C,3,0)/100 | I27: =VLOOKUP(Table_1[[#This Row],[AÇÕES]],'Dados Status Invest'!A:D,4,0)/100 | J27: =VLOOKUP(Table_1[[#This Row],[AÇÕES]],'Dados Status Invest'!A:AB,28,0) | K27: =VLOOKUP(Table_1[[#This Row],[AÇÕES]],'Dados Status Invest'!A:AA,27,0) | L27: =Table_1[[#This Row],[PREÇO]]*Table_1[[#This Row],[DY]] | M27: =$E$13 | N27: 0.3 | O27: =Table_1[[#This Row],[DPA]]/Table_1[[#This Row],[LPA]] | P27: =IF(Table_1[[#This Row],[PAYOUT]]<=40%,"CRESCIMENTO",IF(Table_1[[#This Row],[PAYOUT]]<=60%,"INDEFINIDO","DIVIDENDOS")) | Q27: =VLOOKUP(Table_1[[#This Row],[AÇÕES]],'Dados Status Invest'!A:R,18,0)/100 | R27: =VLOOKUP(Table_1[[#This Row],[AÇÕES]],'Dados Status Invest'!A:Y,25,0)/100 | S27: =(1-Table_1[[#This Row],[PAYOUT]])*Table_1[[#This Row],[ROE]] | T27: =AVERAGE(Table_1[[#This Row],[CAGR LUCRO 5A]],Table_1[[#This Row],[CRESCIMENTO DAMODARAN]]) | U27: =(Table_1[[#This Row],[PREÇO JUSTO BAZIN]]-Table_1[[#This Row],[PREÇO]])/Table_1[[#This Row],[PREÇO JUSTO BAZIN]] | V27: =Table_1[[#This Row],[DPA]]/6% | W27: =Table_1[[#This Row],[PREÇO JUSTO BAZIN]]/(1+Table_1[[#This Row],[MARGEM DE DESCONTO]]) | X27: =(Table_1[[#This Row],[PREÇO JUSTO GRAHAM]]-Table_1[[#This Row],[PREÇO]])/Table_1[[#This Row],[PREÇO JUSTO GRAHAM]] | Y27: =(22.5*Table_1[[#This Row],[LPA]]*Table_1[[#This Row],[VPA]])^0.5 | Z27: =Table_1[[#This Row],[PREÇO JUSTO GRAHAM]]/(1+Table_1[[#This Row],[MARGEM DE DESCONTO]]) | AA27: =(Table_1[[#This Row],[PREÇO JUSTO GORDON]]-Table_1[[#This Row],[PREÇO]])/Table_1[[#This Row],[PREÇO JUSTO GORDON]] | AB27: =Table_1[[#This Row],[DPA]]*(1+Table_1[[#This Row],[MÉDIA DE CRESCIMENTO]]) | AC27: =Table_1[[#This Row],[D1]]/(Table_1[[#This Row],[RISCO]]-Table_1[[#This Row],[MÉDIA DE CRESCIMENTO]]) | AD27: =Table_1[[#This Row],[PREÇO JUSTO GORDON]]/(1+Table_1[[#This Row],[MARGEM DE DESCONTO]]) | AE27: =Table_1[[#This Row],[P/L]]/Table_1[[#This Row],[MÉDIA DE CRESCIMENTO]] | AH27: Entre Zero e 10%
B28: ='Dados Status Invest'!A14 | C28: =VLOOKUP(Table_1[[#This Row],[AÇÕES]],'Classificação B3'!A:B,2,0) | D28: =VLOOKUP(Table_1[[#This Row],[AÇÕES]],'Classificação B3'!A:D,4,0) | E28: =VLOOKUP(Table_1[[#This Row],[AÇÕES]],'Classificação B3'!A:F,6,0) | F28: =VLOOKUP(Table_1[[#This Row],[AÇÕES]],'Classificação B3'!A:G,7,0) | G28: =VLOOKUP(Table_1[[#This Row],[AÇÕES]],'Dados Status Invest'!A:B,2,0) | H28: =VLOOKUP(Table_1[[#This Row],[AÇÕES]],'Dados Status Invest'!A:C,3,0)/100 | I28: =VLOOKUP(Table_1[[#This Row],[AÇÕES]],'Dados Status Invest'!A:D,4,0)/100 | J28: =VLOOKUP(Table_1[[#This Row],[AÇÕES]],'Dados Status Invest'!A:AB,28,0) | K28: =VLOOKUP(Table_1[[#This Row],[AÇÕES]],'Dados Status Invest'!A:AA,27,0) | L28: =Table_1[[#This Row],[PREÇO]]*Table_1[[#This Row],[DY]] | M28: =$E$13 | N28: 0.3 | O28: =Table_1[[#This Row],[DPA]]/Table_1[[#This Row],[LPA]] | P28: =IF(Table_1[[#This Row],[PAYOUT]]<=40%,"CRESCIMENTO",IF(Table_1[[#This Row],[PAYOUT]]<=60%,"INDEFINIDO","DIVIDENDOS")) | Q28: =VLOOKUP(Table_1[[#This Row],[AÇÕES]],'Dados Status Invest'!A:R,18,0)/100 | R28: =VLOOKUP(Table_1[[#This Row],[AÇÕES]],'Dados Status Invest'!A:Y,25,0)/100 | S28: =(1-Table_1[[#This Row],[PAYOUT]])*Table_1[[#This Row],[ROE]] | T28: =AVERAGE(Table_1[[#This Row],[CAGR LUCRO 5A]],Table_1[[#This Row],[CRESCIMENTO DAMODARAN]]) | U28: =(Table_1[[#This Row],[PREÇO JUSTO BAZIN]]-Table_1[[#This Row],[PREÇO]])/Table_1[[#This Row],[PREÇO JUSTO BAZIN]] | V28: =Table_1[[#This Row],[DPA]]/6% | W28: =Table_1[[#This Row],[PREÇO JUSTO BAZIN]]/(1+Table_1[[#This Row],[MARGEM DE DESCONTO]]) | X28: =(Table_1[[#This Row],[PREÇO JUSTO GRAHAM]]-Table_1[[#This Row],[PREÇO]])/Table_1[[#This Row],[PREÇO JUSTO GRAHAM]] | Y28: =(22.5*Table_1[[#This Row],[LPA]]*Table_1[[#This Row],[VPA]])^0.5 | Z28: =Table_1[[#This Row],[PREÇO JUSTO GRAHAM]]/(1+Table_1[[#This Row],[MARGEM DE DESCONTO]]) | AA28: =(Table_1[[#This Row],[PREÇO JUSTO GORDON]]-Table_1[[#This Row],[PREÇO]])/Table_1[[#This Row],[PREÇO JUSTO GORDON]] | AB28: =Table_1[[#This Row],[DPA]]*(1+Table_1[[#This Row],[MÉDIA DE CRESCIMENTO]]) | AC28: =Table_1[[#This Row],[D1]]/(Table_1[[#This Row],[RISCO]]-Table_1[[#This Row],[MÉDIA DE CRESCIMENTO]]) | AD28: =Table_1[[#This Row],[PREÇO JUSTO GORDON]]/(1+Table_1[[#This Row],[MARGEM DE DESCONTO]]) | AE28: =Table_1[[#This Row],[P/L]]/Table_1[[#This Row],[MÉDIA DE CRESCIMENTO]] | AH28: Entre 10% e 20%
B29: ='Dados Status Invest'!A15 | C29: =VLOOKUP(Table_1[[#This Row],[AÇÕES]],'Classificação B3'!A:B,2,0) | D29: =VLOOKUP(Table_1[[#This Row],[AÇÕES]],'Classificação B3'!A:D,4,0) | E29: =VLOOKUP(Table_1[[#This Row],[AÇÕES]],'Classificação B3'!A:F,6,0) | F29: =VLOOKUP(Table_1[[#This Row],[AÇÕES]],'Classificação B3'!A:G,7,0) | G29: =VLOOKUP(Table_1[[#This Row],[AÇÕES]],'Dados Status Invest'!A:B,2,0) | H29: =VLOOKUP(Table_1[[#This Row],[AÇÕES]],'Dados Status Invest'!A:C,3,0)/100 | I29: =VLOOKUP(Table_1[[#This Row],[AÇÕES]],'Dados Status Invest'!A:D,4,0)/100 | J29: =VLOOKUP(Table_1[[#This Row],[AÇÕES]],'Dados Status Invest'!A:AB,28,0) | K29: =VLOOKUP(Table_1[[#This Row],[AÇÕES]],'Dados Status Invest'!A:AA,27,0) | L29: =Table_1[[#This Row],[PREÇO]]*Table_1[[#This Row],[DY]] | M29: =$E$13 | N29: 0.3 | O29: =Table_1[[#This Row],[DPA]]/Table_1[[#This Row],[LPA]] | P29: =IF(Table_1[[#This Row],[PAYOUT]]<=40%,"CRESCIMENTO",IF(Table_1[[#This Row],[PAYOUT]]<=60%,"INDEFINIDO","DIVIDENDOS")) | Q29: =VLOOKUP(Table_1[[#This Row],[AÇÕES]],'Dados Status Invest'!A:R,18,0)/100 | R29: =VLOOKUP(Table_1[[#This Row],[AÇÕES]],'Dados Status Invest'!A:Y,25,0)/100 | S29: =(1-Table_1[[#This Row],[PAYOUT]])*Table_1[[#This Row],[ROE]] | T29: =AVERAGE(Table_1[[#This Row],[CAGR LUCRO 5A]],Table_1[[#This Row],[CRESCIMENTO DAMODARAN]]) | U29: =(Table_1[[#This Row],[PREÇO JUSTO BAZIN]]-Table_1[[#This Row],[PREÇO]])/Table_1[[#This Row],[PREÇO JUSTO BAZIN]] | V29: =Table_1[[#This Row],[DPA]]/6% | W29: =Table_1[[#This Row],[PREÇO JUSTO BAZIN]]/(1+Table_1[[#This Row],[MARGEM DE DESCONTO]]) | X29: =(Table_1[[#This Row],[PREÇO JUSTO GRAHAM]]-Table_1[[#This Row],[PREÇO]])/Table_1[[#This Row],[PREÇO JUSTO GRAHAM]] | Y29: =(22.5*Table_1[[#This Row],[LPA]]*Table_1[[#This Row],[VPA]])^0.5 | Z29: =Table_1[[#This Row],[PREÇO JUSTO GRAHAM]]/(1+Table_1[[#This Row],[MARGEM DE DESCONTO]]) | AA29: =(Table_1[[#This Row],[PREÇO JUSTO GORDON]]-Table_1[[#This Row],[PREÇO]])/Table_1[[#This Row],[PREÇO JUSTO GORDON]] | AB29: =Table_1[[#This Row],[DPA]]*(1+Table_1[[#This Row],[MÉDIA DE CRESCIMENTO]]) | AC29: =Table_1[[#This Row],[D1]]/(Table_1[[#This Row],[RISCO]]-Table_1[[#This Row],[MÉDIA DE CRESCIMENTO]]) | AD29: =Table_1[[#This Row],[PREÇO JUSTO GORDON]]/(1+Table_1[[#This Row],[MARGEM DE DESCONTO]]) | AE29: =Table_1[[#This Row],[P/L]]/Table_1[[#This Row],[MÉDIA DE CRESCIMENTO]] | AH29: Acima de 20%
B30: ='Dados Status Invest'!A16 | C30: =VLOOKUP(Table_1[[#This Row],[AÇÕES]],'Classificação B3'!A:B,2,0) | D30: =VLOOKUP(Table_1[[#This Row],[AÇÕES]],'Classificação B3'!A:D,4,0) | E30: =VLOOKUP(Table_1[[#This Row],[AÇÕES]],'Classificação B3'!A:F,6,0) | F30: =VLOOKUP(Table_1[[#This Row],[AÇÕES]],'Classificação B3'!A:G,7,0) | G30: =VLOOKUP(Table_1[[#This Row],[AÇÕES]],'Dados Status Invest'!A:B,2,0) | H30: =VLOOKUP(Table_1[[#This Row],[AÇÕES]],'Dados Status Invest'!A:C,3,0)/100 | I30: =VLOOKUP(Table_1[[#This Row],[AÇÕES]],'Dados Status Invest'!A:D,4,0)/100 | J30: =VLOOKUP(Table_1[[#This Row],[AÇÕES]],'Dados Status Invest'!A:AB,28,0) | K30: =VLOOKUP(Table_1[[#This Row],[AÇÕES]],'Dados Status Invest'!A:AA,27,0) | L30: =Table_1[[#This Row],[PREÇO]]*Table_1[[#This Row],[DY]] | M30: =$E$13 | N30: 0.3 | O30: =Table_1[[#This Row],[DPA]]/Table_1[[#This Row],[LPA]] | P30: =IF(Table_1[[#This Row],[PAYOUT]]<=40%,"CRESCIMENTO",IF(Table_1[[#This Row],[PAYOUT]]<=60%,"INDEFINIDO","DIVIDENDOS")) | Q30: =VLOOKUP(Table_1[[#This Row],[AÇÕES]],'Dados Status Invest'!A:R,18,0)/100 | R30: =VLOOKUP(Table_1[[#This Row],[AÇÕES]],'Dados Status Invest'!A:Y,25,0)/100 | S30: =(1-Table_1[[#This Row],[PAYOUT]])*Table_1[[#This Row],[ROE]] | T30: =AVERAGE(Table_1[[#This Row],[CAGR LUCRO 5A]],Table_1[[#This Row],[CRESCIMENTO DAMODARAN]]) | U30: =(Table_1[[#This Row],[PREÇO JUSTO BAZIN]]-Table_1[[#This Row],[PREÇO]])/Table_1[[#This Row],[PREÇO JUSTO BAZIN]] | V30: =Table_1[[#This Row],[DPA]]/6% | W30: =Table_1[[#This Row],[PREÇO JUSTO BAZIN]]/(1+Table_1[[#This Row],[MARGEM DE DESCONTO]]) | X30: =(Table_1[[#This Row],[PREÇO JUSTO GRAHAM]]-Table_1[[#This Row],[PREÇO]])/Table_1[[#This Row],[PREÇO JUSTO GRAHAM]] | Y30: =(22.5*Table_1[[#This Row],[LPA]]*Table_1[[#This Row],[VPA]])^0.5 | Z30: =Table_1[[#This Row],[PREÇO JUSTO GRAHAM]]/(1+Table_1[[#This Row],[MARGEM DE DESCONTO]]) | AA30: =(Table_1[[#This Row],[PREÇO JUSTO GORDON]]-Table_1[[#This Row],[PREÇO]])/Table_1[[#This Row],[PREÇO JUSTO GORDON]] | AB30: =Table_1[[#This Row],[DPA]]*(1+Table_1[[#This Row],[MÉDIA DE CRESCIMENTO]]) | AC30: =Table_1[[#This Row],[D1]]/(Table_1[[#This Row],[RISCO]]-Table_1[[#This Row],[MÉDIA DE CRESCIMENTO]]) | AD30: =Table_1[[#This Row],[PREÇO JUSTO GORDON]]/(1+Table_1[[#This Row],[MARGEM DE DESCONTO]]) | AE30: =Table_1[[#This Row],[P/L]]/Table_1[[#This Row],[MÉDIA DE CRESCIMENTO]]
B31: ='Dados Status Invest'!A17 | C31: =VLOOKUP(Table_1[[#This Row],[AÇÕES]],'Classificação B3'!A:B,2,0) | D31: =VLOOKUP(Table_1[[#This Row],[AÇÕES]],'Classificação B3'!A:D,4,0) | E31: =VLOOKUP(Table_1[[#This Row],[AÇÕES]],'Classificação B3'!A:F,6,0) | F31: =VLOOKUP(Table_1[[#This Row],[AÇÕES]],'Classificação B3'!A:G,7,0) | G31: =VLOOKUP(Table_1[[#This Row],[AÇÕES]],'Dados Status Invest'!A:B,2,0) | H31: =VLOOKUP(Table_1[[#This Row],[AÇÕES]],'Dados Status Invest'!A:C,3,0)/100 | I31: =VLOOKUP(Table_1[[#This Row],[AÇÕES]],'Dados Status Invest'!A:D,4,0)/100 | J31: =VLOOKUP(Table_1[[#This Row],[AÇÕES]],'Dados Status Invest'!A:AB,28,0) | K31: =VLOOKUP(Table_1[[#This Row],[AÇÕES]],'Dados Status Invest'!A:AA,27,0) | L31: =Table_1[[#This Row],[PREÇO]]*Table_1[[#This Row],[DY]] | M31: =$E$13 | N31: 0.3 | O31: =Table_1[[#This Row],[DPA]]/Table_1[[#This Row],[LPA]] | P31: =IF(Table_1[[#This Row],[PAYOUT]]<=40%,"CRESCIMENTO",IF(Table_1[[#This Row],[PAYOUT]]<=60%,"INDEFINIDO","DIVIDENDOS")) | Q31: =VLOOKUP(Table_1[[#This Row],[AÇÕES]],'Dados Status Invest'!A:R,18,0)/100 | R31: =VLOOKUP(Table_1[[#This Row],[AÇÕES]],'Dados Status Invest'!A:Y,25,0)/100 | S31: =(1-Table_1[[#This Row],[PAYOUT]])*Table_1[[#This Row],[ROE]] | T31: =AVERAGE(Table_1[[#This Row],[CAGR LUCRO 5A]],Table_1[[#This Row],[CRESCIMENTO DAMODARAN]]) | U31: =(Table_1[[#This Row],[PREÇO JUSTO BAZIN]]-Table_1[[#This Row],[PREÇO]])/Table_1[[#This Row],[PREÇO JUSTO BAZIN]] | V31: =Table_1[[#This Row],[DPA]]/6% | W31: =Table_1[[#This Row],[PREÇO JUSTO BAZIN]]/(1+Table_1[[#This Row],[MARGEM DE DESCONTO]]) | X31: =(Table_1[[#This Row],[PREÇO JUSTO GRAHAM]]-Table_1[[#This Row],[PREÇO]])/Table_1[[#This Row],[PREÇO JUSTO GRAHAM]] | Y31: =(22.5*Table_1[[#This Row],[LPA]]*Table_1[[#This Row],[VPA]])^0.5 | Z31: =Table_1[[#This Row],[PREÇO JUSTO GRAHAM]]/(1+Table_1[[#This Row],[MARGEM DE DESCONTO]]) | AA31: =(Table_1[[#This Row],[PREÇO JUSTO GORDON]]-Table_1[[#This Row],[PREÇO]])/Table_1[[#This Row],[PREÇO JUSTO GORDON]] | AB31: =Table_1[[#This Row],[DPA]]*(1+Table_1[[#This Row],[MÉDIA DE CRESCIMENTO]]) | AC31: =Table_1[[#This Row],[D1]]/(Table_1[[#This Row],[RISCO]]-Table_1[[#This Row],[MÉDIA DE CRESCIMENTO]]) | AD31: =Table_1[[#This Row],[PREÇO JUSTO GORDON]]/(1+Table_1[[#This Row],[MARGEM DE DESCONTO]]) | AE31: =Table_1[[#This Row],[P/L]]/Table_1[[#This Row],[MÉDIA DE CRESCIMENTO]] | AG31: CRESCIMENTO X DIVIDENDOS
B32: ='Dados Status Invest'!A18 | C32: =VLOOKUP(Table_1[[#This Row],[AÇÕES]],'Classificação B3'!A:B,2,0) | D32: =VLOOKUP(Table_1[[#This Row],[AÇÕES]],'Classificação B3'!A:D,4,0) | E32: =VLOOKUP(Table_1[[#This Row],[AÇÕES]],'Classificação B3'!A:F,6,0) | F32: =VLOOKUP(Table_1[[#This Row],[AÇÕES]],'Classificação B3'!A:G,7,0) | G32: =VLOOKUP(Table_1[[#This Row],[AÇÕES]],'Dados Status Invest'!A:B,2,0) | H32: =VLOOKUP(Table_1[[#This Row],[AÇÕES]],'Dados Status Invest'!A:C,3,0)/100 | I32: =VLOOKUP(Table_1[[#This Row],[AÇÕES]],'Dados Status Invest'!A:D,4,0)/100 | J32: =VLOOKUP(Table_1[[#This Row],[AÇÕES]],'Dados Status Invest'!A:AB,28,0) | K32: =VLOOKUP(Table_1[[#This Row],[AÇÕES]],'Dados Status Invest'!A:AA,27,0) | L32: =Table_1[[#This Row],[PREÇO]]*Table_1[[#This Row],[DY]] | M32: =$E$13 | N32: 0.3 | O32: =Table_1[[#This Row],[DPA]]/Table_1[[#This Row],[LPA]] | P32: =IF(Table_1[[#This Row],[PAYOUT]]<=40%,"CRESCIMENTO",IF(Table_1[[#This Row],[PAYOUT]]<=60%,"INDEFINIDO","DIVIDENDOS")) | Q32: =VLOOKUP(Table_1[[#This Row],[AÇÕES]],'Dados Status Invest'!A:R,18,0)/100 | R32: =VLOOKUP(Table_1[[#This Row],[AÇÕES]],'Dados Status Invest'!A:Y,25,0)/100 | S32: =(1-Table_1[[#This Row],[PAYOUT]])*Table_1[[#This Row],[ROE]] | T32: =AVERAGE(Table_1[[#This Row],[CAGR LUCRO 5A]],Table_1[[#This Row],[CRESCIMENTO DAMODARAN]]) | U32: =(Table_1[[#This Row],[PREÇO JUSTO BAZIN]]-Table_1[[#This Row],[PREÇO]])/Table_1[[#This Row],[PREÇO JUSTO BAZIN]] | V32: =Table_1[[#This Row],[DPA]]/6% | W32: =Table_1[[#This Row],[PREÇO JUSTO BAZIN]]/(1+Table_1[[#This Row],[MARGEM DE DESCONTO]]) | X32: =(Table_1[[#This Row],[PREÇO JUSTO GRAHAM]]-Table_1[[#This Row],[PREÇO]])/Table_1[[#This Row],[PREÇO JUSTO GRAHAM]] | Y32: =(22.5*Table_1[[#This Row],[LPA]]*Table_1[[#This Row],[VPA]])^0.5 | Z32: =Table_1[[#This Row],[PREÇO JUSTO GRAHAM]]/(1+Table_1[[#This Row],[MARGEM DE DESCONTO]]) | AA32: =(Table_1[[#This Row],[PREÇO JUSTO GORDON]]-Table_1[[#This Row],[PREÇO]])/Table_1[[#This Row],[PREÇO JUSTO GORDON]] | AB32: =Table_1[[#This Row],[DPA]]*(1+Table_1[[#This Row],[MÉDIA DE CRESCIMENTO]]) | AC32: =Table_1[[#This Row],[D1]]/(Table_1[[#This Row],[RISCO]]-Table_1[[#This Row],[MÉDIA DE CRESCIMENTO]]) | AD32: =Table_1[[#This Row],[PREÇO JUSTO GORDON]]/(1+Table_1[[#This Row],[MARGEM DE DESCONTO]]) | AE32: =Table_1[[#This Row],[P/L]]/Table_1[[#This Row],[MÉDIA DE CRESCIMENTO]] | AG32: DIVIDENDOS | AH32: PAYOUT MAIOR OU IGUAL A 60%
B33: ='Dados Status Invest'!A19 | C33: =VLOOKUP(Table_1[[#This Row],[AÇÕES]],'Classificação B3'!A:B,2,0) | D33: =VLOOKUP(Table_1[[#This Row],[AÇÕES]],'Classificação B3'!A:D,4,0) | E33: =VLOOKUP(Table_1[[#This Row],[AÇÕES]],'Classificação B3'!A:F,6,0) | F33: =VLOOKUP(Table_1[[#This Row],[AÇÕES]],'Classificação B3'!A:G,7,0) | G33: =VLOOKUP(Table_1[[#This Row],[AÇÕES]],'Dados Status Invest'!A:B,2,0) | H33: =VLOOKUP(Table_1[[#This Row],[AÇÕES]],'Dados Status Invest'!A:C,3,0)/100 | I33: =VLOOKUP(Table_1[[#This Row],[AÇÕES]],'Dados Status Invest'!A:D,4,0)/100 | J33: =VLOOKUP(Table_1[[#This Row],[AÇÕES]],'Dados Status Invest'!A:AB,28,0) | K33: =VLOOKUP(Table_1[[#This Row],[AÇÕES]],'Dados Status Invest'!A:AA,27,0) | L33: =Table_1[[#This Row],[PREÇO]]*Table_1[[#This Row],[DY]] | M33: =$E$13 | N33: 0.3 | O33: =Table_1[[#This Row],[DPA]]/Table_1[[#This Row],[LPA]] | P33: =IF(Table_1[[#This Row],[PAYOUT]]<=40%,"CRESCIMENTO",IF(Table_1[[#This Row],[PAYOUT]]<=60%,"INDEFINIDO","DIVIDENDOS")) | Q33: =VLOOKUP(Table_1[[#This Row],[AÇÕES]],'Dados Status Invest'!A:R,18,0)/100 | R33: =VLOOKUP(Table_1[[#This Row],[AÇÕES]],'Dados Status Invest'!A:Y,25,0)/100 | S33: =(1-Table_1[[#This Row],[PAYOUT]])*Table_1[[#This Row],[ROE]] | T33: =AVERAGE(Table_1[[#This Row],[CAGR LUCRO 5A]],Table_1[[#This Row],[CRESCIMENTO DAMODARAN]]) | U33: =(Table_1[[#This Row],[PREÇO JUSTO BAZIN]]-Table_1[[#This Row],[PREÇO]])/Table_1[[#This Row],[PREÇO JUSTO BAZIN]] | V33: =Table_1[[#This Row],[DPA]]/6% | W33: =Table_1[[#This Row],[PREÇO JUSTO BAZIN]]/(1+Table_1[[#This Row],[MARGEM DE DESCONTO]]) | X33: =(Table_1[[#This Row],[PREÇO JUSTO GRAHAM]]-Table_1[[#This Row],[PREÇO]])/Table_1[[#This Row],[PREÇO JUSTO GRAHAM]] | Y33: =(22.5*Table_1[[#This Row],[LPA]]*Table_1[[#This Row],[VPA]])^0.5 | Z33: =Table_1[[#This Row],[PREÇO JUSTO GRAHAM]]/(1+Table_1[[#This Row],[MARGEM DE DESCONTO]]) | AA33: =(Table_1[[#This Row],[PREÇO JUSTO GORDON]]-Table_1[[#This Row],[PREÇO]])/Table_1[[#This Row],[PREÇO JUSTO GORDON]] | AB33: =Table_1[[#This Row],[DPA]]*(1+Table_1[[#This Row],[MÉDIA DE CRESCIMENTO]]) | AC33: =Table_1[[#This Row],[D1]]/(Table_1[[#This Row],[RISCO]]-Table_1[[#This Row],[MÉDIA DE CRESCIMENTO]]) | AD33: =Table_1[[#This Row],[PREÇO JUSTO GORDON]]/(1+Table_1[[#This Row],[MARGEM DE DESCONTO]]) | AE33: =Table_1[[#This Row],[P/L]]/Table_1[[#This Row],[MÉDIA DE CRESCIMENTO]] | AG33: CRESCIMENTO | AH33: PAYOUT MENOR OU IGUAL A 40%
B34: ='Dados Status Invest'!A20 | C34: =VLOOKUP(Table_1[[#This Row],[AÇÕES]],'Classificação B3'!A:B,2,0) | D34: =VLOOKUP(Table_1[[#This Row],[AÇÕES]],'Classificação B3'!A:D,4,0) | E34: =VLOOKUP(Table_1[[#This Row],[AÇÕES]],'Classificação B3'!A:F,6,0) | F34: =VLOOKUP(Table_1[[#This Row],[AÇÕES]],'Classificação B3'!A:G,7,0) | G34: =VLOOKUP(Table_1[[#This Row],[AÇÕES]],'Dados Status Invest'!A:B,2,0) | H34: =VLOOKUP(Table_1[[#This Row],[AÇÕES]],'Dados Status Invest'!A:C,3,0)/100 | I34: =VLOOKUP(Table_1[[#This Row],[AÇÕES]],'Dados Status Invest'!A:D,4,0)/100 | J34: =VLOOKUP(Table_1[[#This Row],[AÇÕES]],'Dados Status Invest'!A:AB,28,0) | K34: =VLOOKUP(Table_1[[#This Row],[AÇÕES]],'Dados Status Invest'!A:AA,27,0) | L34: =Table_1[[#This Row],[PREÇO]]*Table_1[[#This Row],[DY]] | M34: =$E$13 | N34: 0.3 | O34: =Table_1[[#This Row],[DPA]]/Table_1[[#This Row],[LPA]] | P34: =IF(Table_1[[#This Row],[PAYOUT]]<=40%,"CRESCIMENTO",IF(Table_1[[#This Row],[PAYOUT]]<=60%,"INDEFINIDO","DIVIDENDOS")) | Q34: =VLOOKUP(Table_1[[#This Row],[AÇÕES]],'Dados Status Invest'!A:R,18,0)/100 | R34: =VLOOKUP(Table_1[[#This Row],[AÇÕES]],'Dados Status Invest'!A:Y,25,0)/100 | S34: =(1-Table_1[[#This Row],[PAYOUT]])*Table_1[[#This Row],[ROE]] | T34: =AVERAGE(Table_1[[#This Row],[CAGR LUCRO 5A]],Table_1[[#This Row],[CRESCIMENTO DAMODARAN]]) | U34: =(Table_1[[#This Row],[PREÇO JUSTO BAZIN]]-Table_1[[#This Row],[PREÇO]])/Table_1[[#This Row],[PREÇO JUSTO BAZIN]] | V34: =Table_1[[#This Row],[DPA]]/6% | W34: =Table_1[[#This Row],[PREÇO JUSTO BAZIN]]/(1+Table_1[[#This Row],[MARGEM DE DESCONTO]]) | X34: =(Table_1[[#This Row],[PREÇO JUSTO GRAHAM]]-Table_1[[#This Row],[PREÇO]])/Table_1[[#This Row],[PREÇO JUSTO GRAHAM]] | Y34: =(22.5*Table_1[[#This Row],[LPA]]*Table_1[[#This Row],[VPA]])^0.5 | Z34: =Table_1[[#This Row],[PREÇO JUSTO GRAHAM]]/(1+Table_1[[#This Row],[MARGEM DE DESCONTO]]) | AA34: =(Table_1[[#This Row],[PREÇO JUSTO GORDON]]-Table_1[[#This Row],[PREÇO]])/Table_1[[#This Row],[PREÇO JUSTO GORDON]] | AB34: =Table_1[[#This Row],[DPA]]*(1+Table_1[[#This Row],[MÉDIA DE CRESCIMENTO]]) | AC34: =Table_1[[#This Row],[D1]]/(Table_1[[#This Row],[RISCO]]-Table_1[[#This Row],[MÉDIA DE CRESCIMENTO]]) | AD34: =Table_1[[#This Row],[PREÇO JUSTO GORDON]]/(1+Table_1[[#This Row],[MARGEM DE DESCONTO]]) | AE34: =Table_1[[#This Row],[P/L]]/Table_1[[#This Row],[MÉDIA DE CRESCIMENTO]] | AG34: INDEFINIDO | AH34: PAYOUT ENTRE 40 E 60%
B35: ='Dados Status Invest'!A21 | C35: =VLOOKUP(Table_1[[#This Row],[AÇÕES]],'Classificação B3'!A:B,2,0) | D35: =VLOOKUP(Table_1[[#This Row],[AÇÕES]],'Classificação B3'!A:D,4,0) | E35: =VLOOKUP(Table_1[[#This Row],[AÇÕES]],'Classificação B3'!A:F,6,0) | F35: =VLOOKUP(Table_1[[#This Row],[AÇÕES]],'Classificação B3'!A:G,7,0) | G35: =VLOOKUP(Table_1[[#This Row],[AÇÕES]],'Dados Status Invest'!A:B,2,0) | H35: =VLOOKUP(Table_1[[#This Row],[AÇÕES]],'Dados Status Invest'!A:C,3,0)/100 | I35: =VLOOKUP(Table_1[[#This Row],[AÇÕES]],'Dados Status Invest'!A:D,4,0)/100 | J35: =VLOOKUP(Table_1[[#This Row],[AÇÕES]],'Dados Status Invest'!A:AB,28,0) | K35: =VLOOKUP(Table_1[[#This Row],[AÇÕES]],'Dados Status Invest'!A:AA,27,0) | L35: =Table_1[[#This Row],[PREÇO]]*Table_1[[#This Row],[DY]] | M35: =$E$13 | N35: 0.3 | O35: =Table_1[[#This Row],[DPA]]/Table_1[[#This Row],[LPA]] | P35: =IF(Table_1[[#This Row],[PAYOUT]]<=40%,"CRESCIMENTO",IF(Table_1[[#This Row],[PAYOUT]]<=60%,"INDEFINIDO","DIVIDENDOS")) | Q35: =VLOOKUP(Table_1[[#This Row],[AÇÕES]],'Dados Status Invest'!A:R,18,0)/100 | R35: =VLOOKUP(Table_1[[#This Row],[AÇÕES]],'Dados Status Invest'!A:Y,25,0)/100 | S35: =(1-Table_1[[#This Row],[PAYOUT]])*Table_1[[#This Row],[ROE]] | T35: =AVERAGE(Table_1[[#This Row],[CAGR LUCRO 5A]],Table_1[[#This Row],[CRESCIMENTO DAMODARAN]]) | U35: =(Table_1[[#This Row],[PREÇO JUSTO BAZIN]]-Table_1[[#This Row],[PREÇO]])/Table_1[[#This Row],[PREÇO JUSTO BAZIN]] | V35: =Table_1[[#This Row],[DPA]]/6% | W35: =Table_1[[#This Row],[PREÇO JUSTO BAZIN]]/(1+Table_1[[#This Row],[MARGEM DE DESCONTO]]) | X35: =(Table_1[[#This Row],[PREÇO JUSTO GRAHAM]]-Table_1[[#This Row],[PREÇO]])/Table_1[[#This Row],[PREÇO JUSTO GRAHAM]] | Y35: =(22.5*Table_1[[#This Row],[LPA]]*Table_1[[#This Row],[VPA]])^0.5 | Z35: =Table_1[[#This Row],[PREÇO JUSTO GRAHAM]]/(1+Table_1[[#This Row],[MARGEM DE DESCONTO]]) | AA35: =(Table_1[[#This Row],[PREÇO JUSTO GORDON]]-Table_1[[#This Row],[PREÇO]])/Table_1[[#This Row],[PREÇO JUSTO GORDON]] | AB35: =Table_1[[#This Row],[DPA]]*(1+Table_1[[#This Row],[MÉDIA DE CRESCIMENTO]]) | AC35: =Table_1[[#This Row],[D1]]/(Table_1[[#This Row],[RISCO]]-Table_1[[#This Row],[MÉDIA DE CRESCIMENTO]]) | AD35: =Table_1[[#This Row],[PREÇO JUSTO GORDON]]/(1+Table_1[[#This Row],[MARGEM DE DESCONTO]]) | AE35: =Table_1[[#This Row],[P/L]]/Table_1[[#This Row],[MÉDIA DE CRESCIMENTO]]
B36: ='Dados Status Invest'!A22 | C36: =VLOOKUP(Table_1[[#This Row],[AÇÕES]],'Classificação B3'!A:B,2,0) | D36: =VLOOKUP(Table_1[[#This Row],[AÇÕES]],'Classificação B3'!A:D,4,0) | E36: =VLOOKUP(Table_1[[#This Row],[AÇÕES]],'Classificação B3'!A:F,6,0) | F36: =VLOOKUP(Table_1[[#This Row],[AÇÕES]],'Classificação B3'!A:G,7,0) | G36: =VLOOKUP(Table_1[[#This Row],[AÇÕES]],'Dados Status Invest'!A:B,2,0) | H36: =VLOOKUP(Table_1[[#This Row],[AÇÕES]],'Dados Status Invest'!A:C,3,0)/100 | I36: =VLOOKUP(Table_1[[#This Row],[AÇÕES]],'Dados Status Invest'!A:D,4,0)/100 | J36: =VLOOKUP(Table_1[[#This Row],[AÇÕES]],'Dados Status Invest'!A:AB,28,0) | K36: =VLOOKUP(Table_1[[#This Row],[AÇÕES]],'Dados Status Invest'!A:AA,27,0) | L36: =Table_1[[#This Row],[PREÇO]]*Table_1[[#This Row],[DY]] | M36: =$E$13 | N36: 0.3 | O36: =Table_1[[#This Row],[DPA]]/Table_1[[#This Row],[LPA]] | P36: =IF(Table_1[[#This Row],[PAYOUT]]<=40%,"CRESCIMENTO",IF(Table_1[[#This Row],[PAYOUT]]<=60%,"INDEFINIDO","DIVIDENDOS")) | Q36: =VLOOKUP(Table_1[[#This Row],[AÇÕES]],'Dados Status Invest'!A:R,18,0)/100 | R36: =VLOOKUP(Table_1[[#This Row],[AÇÕES]],'Dados Status Invest'!A:Y,25,0)/100 | S36: =(1-Table_1[[#This Row],[PAYOUT]])*Table_1[[#This Row],[ROE]] | T36: =AVERAGE(Table_1[[#This Row],[CAGR LUCRO 5A]],Table_1[[#This Row],[CRESCIMENTO DAMODARAN]]) | U36: =(Table_1[[#This Row],[PREÇO JUSTO BAZIN]]-Table_1[[#This Row],[PREÇO]])/Table_1[[#This Row],[PREÇO JUSTO BAZIN]] | V36: =Table_1[[#This Row],[DPA]]/6% | W36: =Table_1[[#This Row],[PREÇO JUSTO BAZIN]]/(1+Table_1[[#This Row],[MARGEM DE DESCONTO]]) | X36: =(Table_1[[#This Row],[PREÇO JUSTO GRAHAM]]-Table_1[[#This Row],[PREÇO]])/Table_1[[#This Row],[PREÇO JUSTO GRAHAM]] | Y36: =(22.5*Table_1[[#This Row],[LPA]]*Table_1[[#This Row],[VPA]])^0.5 | Z36: =Table_1[[#This Row],[PREÇO JUSTO GRAHAM]]/(1+Table_1[[#This Row],[MARGEM DE DESCONTO]]) | AA36: =(Table_1[[#This Row],[PREÇO JUSTO GORDON]]-Table_1[[#This Row],[PREÇO]])/Table_1[[#This Row],[PREÇO JUSTO GORDON]] | AB36: =Table_1[[#This Row],[DPA]]*(1+Table_1[[#This Row],[MÉDIA DE CRESCIMENTO]]) | AC36: =Table_1[[#This Row],[D1]]/(Table_1[[#This Row],[RISCO]]-Table_1[[#This Row],[MÉDIA DE CRESCIMENTO]]) | AD36: =Table_1[[#This Row],[PREÇO JUSTO GORDON]]/(1+Table_1[[#This Row],[MARGEM DE DESCONTO]]) | AE36: =Table_1[[#This Row],[P/L]]/Table_1[[#This Row],[MÉDIA DE CRESCIMENTO]]
B37: ='Dados Status Invest'!A23 | C37: =VLOOKUP(Table_1[[#This Row],[AÇÕES]],'Classificação B3'!A:B,2,0) | D37: =VLOOKUP(Table_1[[#This Row],[AÇÕES]],'Classificação B3'!A:D,4,0) | E37: =VLOOKUP(Table_1[[#This Row],[AÇÕES]],'Classificação B3'!A:F,6,0) | F37: =VLOOKUP(Table_1[[#This Row],[AÇÕES]],'Classificação B3'!A:G,7,0) | G37: =VLOOKUP(Table_1[[#This Row],[AÇÕES]],'Dados Status Invest'!A:B,2,0) | H37: =VLOOKUP(Table_1[[#This Row],[AÇÕES]],'Dados Status Invest'!A:C,3,0)/100 | I37: =VLOOKUP(Table_1[[#This Row],[AÇÕES]],'Dados Status Invest'!A:D,4,0)/100 | J37: =VLOOKUP(Table_1[[#This Row],[AÇÕES]],'Dados Status Invest'!A:AB,28,0) | K37: =VLOOKUP(Table_1[[#This Row],[AÇÕES]],'Dados Status Invest'!A:AA,27,0) | L37: =Table_1[[#This Row],[PREÇO]]*Table_1[[#This Row],[DY]] | M37: =$E$13 | N37: 0.3 | O37: =Table_1[[#This Row],[DPA]]/Table_1[[#This Row],[LPA]] | P37: =IF(Table_1[[#This Row],[PAYOUT]]<=40%,"CRESCIMENTO",IF(Table_1[[#This Row],[PAYOUT]]<=60%,"INDEFINIDO","DIVIDENDOS")) | Q37: =VLOOKUP(Table_1[[#This Row],[AÇÕES]],'Dados Status Invest'!A:R,18,0)/100 | R37: =VLOOKUP(Table_1[[#This Row],[AÇÕES]],'Dados Status Invest'!A:Y,25,0)/100 | S37: =(1-Table_1[[#This Row],[PAYOUT]])*Table_1[[#This Row],[ROE]] | T37: =AVERAGE(Table_1[[#This Row],[CAGR LUCRO 5A]],Table_1[[#This Row],[CRESCIMENTO DAMODARAN]]) | U37: =(Table_1[[#This Row],[PREÇO JUSTO BAZIN]]-Table_1[[#This Row],[PREÇO]])/Table_1[[#This Row],[PREÇO JUSTO BAZIN]] | V37: =Table_1[[#This Row],[DPA]]/6% | W37: =Table_1[[#This Row],[PREÇO JUSTO BAZIN]]/(1+Table_1[[#This Row],[MARGEM DE DESCONTO]]) | X37: =(Table_1[[#This Row],[PREÇO JUSTO GRAHAM]]-Table_1[[#This Row],[PREÇO]])/Table_1[[#This Row],[PREÇO JUSTO GRAHAM]] | Y37: =(22.5*Table_1[[#This Row],[LPA]]*Table_1[[#This Row],[VPA]])^0.5 | Z37: =Table_1[[#This Row],[PREÇO JUSTO GRAHAM]]/(1+Table_1[[#This Row],[MARGEM DE DESCONTO]]) | AA37: =(Table_1[[#This Row],[PREÇO JUSTO GORDON]]-Table_1[[#This Row],[PREÇO]])/Table_1[[#This Row],[PREÇO JUSTO GORDON]] | AB37: =Table_1[[#This Row],[DPA]]*(1+Table_1[[#This Row],[MÉDIA DE CRESCIMENTO]]) | AC37: =Table_1[[#This Row],[D1]]/(Table_1[[#This Row],[RISCO]]-Table_1[[#This Row],[MÉDIA DE CRESCIMENTO]]) | AD37: =Table_1[[#This Row],[PREÇO JUSTO GORDON]]/(1+Table_1[[#This Row],[MARGEM DE DESCONTO]]) | AE37: =Table_1[[#This Row],[P/L]]/Table_1[[#This Row],[MÉDIA DE CRESCIMENTO]]
B38: ='Dados Status Invest'!A24 | C38: =VLOOKUP(Table_1[[#This Row],[AÇÕES]],'Classificação B3'!A:B,2,0) | D38: =VLOOKUP(Table_1[[#This Row],[AÇÕES]],'Classificação B3'!A:D,4,0) | E38: =VLOOKUP(Table_1[[#This Row],[AÇÕES]],'Classificação B3'!A:F,6,0) | F38: =VLOOKUP(Table_1[[#This Row],[AÇÕES]],'Classificação B3'!A:G,7,0) | G38: =VLOOKUP(Table_1[[#This Row],[AÇÕES]],'Dados Status Invest'!A:B,2,0) | H38: =VLOOKUP(Table_1[[#This Row],[AÇÕES]],'Dados Status Invest'!A:C,3,0)/100 | I38: =VLOOKUP(Table_1[[#This Row],[AÇÕES]],'Dados Status Invest'!A:D,4,0)/100 | J38: =VLOOKUP(Table_1[[#This Row],[AÇÕES]],'Dados Status Invest'!A:AB,28,0) | K38: =VLOOKUP(Table_1[[#This Row],[AÇÕES]],'Dados Status Invest'!A:AA,27,0) | L38: =Table_1[[#This Row],[PREÇO]]*Table_1[[#This Row],[DY]] | M38: =$E$13 | N38: 0.3 | O38: =Table_1[[#This Row],[DPA]]/Table_1[[#This Row],[LPA]] | P38: =IF(Table_1[[#This Row],[PAYOUT]]<=40%,"CRESCIMENTO",IF(Table_1[[#This Row],[PAYOUT]]<=60%,"INDEFINIDO","DIVIDENDOS")) | Q38: =VLOOKUP(Table_1[[#This Row],[AÇÕES]],'Dados Status Invest'!A:R,18,0)/100 | R38: =VLOOKUP(Table_1[[#This Row],[AÇÕES]],'Dados Status Invest'!A:Y,25,0)/100 | S38: =(1-Table_1[[#This Row],[PAYOUT]])*Table_1[[#This Row],[ROE]] | T38: =AVERAGE(Table_1[[#This Row],[CAGR LUCRO 5A]],Table_1[[#This Row],[CRESCIMENTO DAMODARAN]]) | U38: =(Table_1[[#This Row],[PREÇO JUSTO BAZIN]]-Table_1[[#This Row],[PREÇO]])/Table_1[[#This Row],[PREÇO JUSTO BAZIN]] | V38: =Table_1[[#This Row],[DPA]]/6% | W38: =Table_1[[#This Row],[PREÇO JUSTO BAZIN]]/(1+Table_1[[#This Row],[MARGEM DE DESCONTO]]) | X38: =(Table_1[[#This Row],[PREÇO JUSTO GRAHAM]]-Table_1[[#This Row],[PREÇO]])/Table_1[[#This Row],[PREÇO JUSTO GRAHAM]] | Y38: =(22.5*Table_1[[#This Row],[LPA]]*Table_1[[#This Row],[VPA]])^0.5 | Z38: =Table_1[[#This Row],[PREÇO JUSTO GRAHAM]]/(1+Table_1[[#This Row],[MARGEM DE DESCONTO]]) | AA38: =(Table_1[[#This Row],[PREÇO JUSTO GORDON]]-Table_1[[#This Row],[PREÇO]])/Table_1[[#This Row],[PREÇO JUSTO GORDON]] | AB38: =Table_1[[#This Row],[DPA]]*(1+Table_1[[#This Row],[MÉDIA DE CRESCIMENTO]]) | AC38: =Table_1[[#This Row],[D1]]/(Table_1[[#This Row],[RISCO]]-Table_1[[#This Row],[MÉDIA DE CRESCIMENTO]]) | AD38: =Table_1[[#This Row],[PREÇO JUSTO GORDON]]/(1+Table_1[[#This Row],[MARGEM DE DESCONTO]]) | AE38: =Table_1[[#This Row],[P/L]]/Table_1[[#This Row],[MÉDIA DE CRESCIMENTO]]
B39: ='Dados Status Invest'!A25 | C39: =VLOOKUP(Table_1[[#This Row],[AÇÕES]],'Classificação B3'!A:B,2,0) | D39: =VLOOKUP(Table_1[[#This Row],[AÇÕES]],'Classificação B3'!A:D,4,0) | E39: =VLOOKUP(Table_1[[#This Row],[AÇÕES]],'Classificação B3'!A:F,6,0) | F39: =VLOOKUP(Table_1[[#This Row],[AÇÕES]],'Classificação B3'!A:G,7,0) | G39: =VLOOKUP(Table_1[[#This Row],[AÇÕES]],'Dados Status Invest'!A:B,2,0) | H39: =VLOOKUP(Table_1[[#This Row],[AÇÕES]],'Dados Status Invest'!A:C,3,0)/100 | I39: =VLOOKUP(Table_1[[#This Row],[AÇÕES]],'Dados Status Invest'!A:D,4,0)/100 | J39: =VLOOKUP(Table_1[[#This Row],[AÇÕES]],'Dados Status Invest'!A:AB,28,0) | K39: =VLOOKUP(Table_1[[#This Row],[AÇÕES]],'Dados Status Invest'!A:AA,27,0) | L39: =Table_1[[#This Row],[PREÇO]]*Table_1[[#This Row],[DY]] | M39: =$E$13 | N39: 0.3 | O39: =Table_1[[#This Row],[DPA]]/Table_1[[#This Row],[LPA]] | P39: =IF(Table_1[[#This Row],[PAYOUT]]<=40%,"CRESCIMENTO",IF(Table_1[[#This Row],[PAYOUT]]<=60%,"INDEFINIDO","DIVIDENDOS")) | Q39: =VLOOKUP(Table_1[[#This Row],[AÇÕES]],'Dados Status Invest'!A:R,18,0)/100 | R39: =VLOOKUP(Table_1[[#This Row],[AÇÕES]],'Dados Status Invest'!A:Y,25,0)/100 | S39: =(1-Table_1[[#This Row],[PAYOUT]])*Table_1[[#This Row],[ROE]] | T39: =AVERAGE(Table_1[[#This Row],[CAGR LUCRO 5A]],Table_1[[#This Row],[CRESCIMENTO DAMODARAN]]) | U39: =(Table_1[[#This Row],[PREÇO JUSTO BAZIN]]-Table_1[[#This Row],[PREÇO]])/Table_1[[#This Row],[PREÇO JUSTO BAZIN]] | V39: =Table_1[[#This Row],[DPA]]/6% | W39: =Table_1[[#This Row],[PREÇO JUSTO BAZIN]]/(1+Table_1[[#This Row],[MARGEM DE DESCONTO]]) | X39: =(Table_1[[#This Row],[PREÇO JUSTO GRAHAM]]-Table_1[[#This Row],[PREÇO]])/Table_1[[#This Row],[PREÇO JUSTO GRAHAM]] | Y39: =(22.5*Table_1[[#This Row],[LPA]]*Table_1[[#This Row],[VPA]])^0.5 | Z39: =Table_1[[#This Row],[PREÇO JUSTO GRAHAM]]/(1+Table_1[[#This Row],[MARGEM DE DESCONTO]]) | AA39: =(Table_1[[#This Row],[PREÇO JUSTO GORDON]]-Table_1[[#This Row],[PREÇO]])/Table_1[[#This Row],[PREÇO JUSTO GORDON]] | AB39: =Table_1[[#This Row],[DPA]]*(1+Table_1[[#This Row],[MÉDIA DE CRESCIMENTO]]) | AC39: =Table_1[[#This Row],[D1]]/(Table_1[[#This Row],[RISCO]]-Table_1[[#This Row],[MÉDIA DE CRESCIMENTO]]) | AD39: =Table_1[[#This Row],[PREÇO JUSTO GORDON]]/(1+Table_1[[#This Row],[MARGEM DE DESCONTO]]) | AE39: =Table_1[[#This Row],[P/L]]/Table_1[[#This Row],[MÉDIA DE CRESCIMENTO]]
B40: ='Dados Status Invest'!A26 | C40: =VLOOKUP(Table_1[[#This Row],[AÇÕES]],'Classificação B3'!A:B,2,0) | D40: =VLOOKUP(Table_1[[#This Row],[AÇÕES]],'Classificação B3'!A:D,4,0) | E40: =VLOOKUP(Table_1[[#This Row],[AÇÕES]],'Classificação B3'!A:F,6,0) | F40: =VLOOKUP(Table_1[[#This Row],[AÇÕES]],'Classificação B3'!A:G,7,0) | G40: =VLOOKUP(Table_1[[#This Row],[AÇÕES]],'Dados Status Invest'!A:B,2,0) | H40: =VLOOKUP(Table_1[[#This Row],[AÇÕES]],'Dados Status Invest'!A:C,3,0)/100 | I40: =VLOOKUP(Table_1[[#This Row],[AÇÕES]],'Dados Status Invest'!A:D,4,0)/100 | J40: =VLOOKUP(Table_1[[#This Row],[AÇÕES]],'Dados Status Invest'!A:AB,28,0) | K40: =VLOOKUP(Table_1[[#This Row],[AÇÕES]],'Dados Status Invest'!A:AA,27,0) | L40: =Table_1[[#This Row],[PREÇO]]*Table_1[[#This Row],[DY]] | M40: =$E$13 | N40: 0.3 | O40: =Table_1[[#This Row],[DPA]]/Table_1[[#This Row],[LPA]] | P40: =IF(Table_1[[#This Row],[PAYOUT]]<=40%,"CRESCIMENTO",IF(Table_1[[#This Row],[PAYOUT]]<=60%,"INDEFINIDO","DIVIDENDOS")) | Q40: =VLOOKUP(Table_1[[#This Row],[AÇÕES]],'Dados Status Invest'!A:R,18,0)/100 | R40: =VLOOKUP(Table_1[[#This Row],[AÇÕES]],'Dados Status Invest'!A:Y,25,0)/100 | S40: =(1-Table_1[[#This Row],[PAYOUT]])*Table_1[[#This Row],[ROE]] | T40: =AVERAGE(Table_1[[#This Row],[CAGR LUCRO 5A]],Table_1[[#This Row],[CRESCIMENTO DAMODARAN]]) | U40: =(Table_1[[#This Row],[PREÇO JUSTO BAZIN]]-Table_1[[#This Row],[PREÇO]])/Table_1[[#This Row],[PREÇO JUSTO BAZIN]] | V40: =Table_1[[#This Row],[DPA]]/6% | W40: =Table_1[[#This Row],[PREÇO JUSTO BAZIN]]/(1+Table_1[[#This Row],[MARGEM DE DESCONTO]]) | X40: =(Table_1[[#This Row],[PREÇO JUSTO GRAHAM]]-Table_1[[#This Row],[PREÇO]])/Table_1[[#This Row],[PREÇO JUSTO GRAHAM]] | Y40: =(22.5*Table_1[[#This Row],[LPA]]*Table_1[[#This Row],[VPA]])^0.5 | Z40: =Table_1[[#This Row],[PREÇO JUSTO GRAHAM]]/(1+Table_1[[#This Row],[MARGEM DE DESCONTO]]) | AA40: =(Table_1[[#This Row],[PREÇO JUSTO GORDON]]-Table_1[[#This Row],[PREÇO]])/Table_1[[#This Row],[PREÇO JUSTO GORDON]] | AB40: =Table_1[[#This Row],[DPA]]*(1+Table_1[[#This Row],[MÉDIA DE CRESCIMENTO]]) | AC40: =Table_1[[#This Row],[D1]]/(Table_1[[#This Row],[RISCO]]-Table_1[[#This Row],[MÉDIA DE CRESCIMENTO]]) | AD40: =Table_1[[#This Row],[PREÇO JUSTO GORDON]]/(1+Table_1[[#This Row],[MARGEM DE DESCONTO]]) | AE40: =Table_1[[#This Row],[P/L]]/Table_1[[#This Row],[MÉDIA DE CRESCIMENTO]]
B41: ='Dados Status Invest'!A27 | C41: =VLOOKUP(Table_1[[#This Row],[AÇÕES]],'Classificação B3'!A:B,2,0) | D41: =VLOOKUP(Table_1[[#This Row],[AÇÕES]],'Classificação B3'!A:D,4,0) | E41: =VLOOKUP(Table_1[[#This Row],[AÇÕES]],'Classificação B3'!A:F,6,0) | F41: =VLOOKUP(Table_1[[#This Row],[AÇÕES]],'Classificação B3'!A:G,7,0) | G41: =VLOOKUP(Table_1[[#This Row],[AÇÕES]],'Dados Status Invest'!A:B,2,0) | H41: =VLOOKUP(Table_1[[#This Row],[AÇÕES]],'Dados Status Invest'!A:C,3,0)/100 | I41: =VLOOKUP(Table_1[[#This Row],[AÇÕES]],'Dados Status Invest'!A:D,4,0)/100 | J41: =VLOOKUP(Table_1[[#This Row],[AÇÕES]],'Dados Status Invest'!A:AB,28,0) | K41: =VLOOKUP(Table_1[[#This Row],[AÇÕES]],'Dados Status Invest'!A:AA,27,0) | L41: =Table_1[[#This Row],[PREÇO]]*Table_1[[#This Row],[DY]] | M41: =$E$13 | N41: 0.3 | O41: =Table_1[[#This Row],[DPA]]/Table_1[[#This Row],[LPA]] | P41: =IF(Table_1[[#This Row],[PAYOUT]]<=40%,"CRESCIMENTO",IF(Table_1[[#This Row],[PAYOUT]]<=60%,"INDEFINIDO","DIVIDENDOS")) | Q41: =VLOOKUP(Table_1[[#This Row],[AÇÕES]],'Dados Status Invest'!A:R,18,0)/100 | R41: =VLOOKUP(Table_1[[#This Row],[AÇÕES]],'Dados Status Invest'!A:Y,25,0)/100 | S41: =(1-Table_1[[#This Row],[PAYOUT]])*Table_1[[#This Row],[ROE]] | T41: =AVERAGE(Table_1[[#This Row],[CAGR LUCRO 5A]],Table_1[[#This Row],[CRESCIMENTO DAMODARAN]]) | U41: =(Table_1[[#This Row],[PREÇO JUSTO BAZIN]]-Table_1[[#This Row],[PREÇO]])/Table_1[[#This Row],[PREÇO JUSTO BAZIN]] | V41: =Table_1[[#This Row],[DPA]]/6% | W41: =Table_1[[#This Row],[PREÇO JUSTO BAZIN]]/(1+Table_1[[#This Row],[MARGEM DE DESCONTO]]) | X41: =(Table_1[[#This Row],[PREÇO JUSTO GRAHAM]]-Table_1[[#This Row],[PREÇO]])/Table_1[[#This Row],[PREÇO JUSTO GRAHAM]] | Y41: =(22.5*Table_1[[#This Row],[LPA]]*Table_1[[#This Row],[VPA]])^0.5 | Z41: =Table_1[[#This Row],[PREÇO JUSTO GRAHAM]]/(1+Table_1[[#This Row],[MARGEM DE DESCONTO]]) | AA41: =(Table_1[[#This Row],[PREÇO JUSTO GORDON]]-Table_1[[#This Row],[PREÇO]])/Table_1[[#This Row],[PREÇO JUSTO GORDON]] | AB41: =Table_1[[#This Row],[DPA]]*(1+Table_1[[#This Row],[MÉDIA DE CRESCIMENTO]]) | AC41: =Table_1[[#This Row],[D1]]/(Table_1[[#This Row],[RISCO]]-Table_1[[#This Row],[MÉDIA DE CRESCIMENTO]]) | AD41: =Table_1[[#This Row],[PREÇO JUSTO GORDON]]/(1+Table_1[[#This Row],[MARGEM DE DESCONTO]]) | AE41: =Table_1[[#This Row],[P/L]]/Table_1[[#This Row],[MÉDIA DE CRESCIMENTO]]
B42: ='Dados Status Invest'!A28 | C42: =VLOOKUP(Table_1[[#This Row],[AÇÕES]],'Classificação B3'!A:B,2,0) | D42: =VLOOKUP(Table_1[[#This Row],[AÇÕES]],'Classificação B3'!A:D,4,0) | E42: =VLOOKUP(Table_1[[#This Row],[AÇÕES]],'Classificação B3'!A:F,6,0) | F42: =VLOOKUP(Table_1[[#This Row],[AÇÕES]],'Classificação B3'!A:G,7,0) | G42: =VLOOKUP(Table_1[[#This Row],[AÇÕES]],'Dados Status Invest'!A:B,2,0) | H42: =VLOOKUP(Table_1[[#This Row],[AÇÕES]],'Dados Status Invest'!A:C,3,0)/100 | I42: =VLOOKUP(Table_1[[#This Row],[AÇÕES]],'Dados Status Invest'!A:D,4,0)/100 | J42: =VLOOKUP(Table_1[[#This Row],[AÇÕES]],'Dados Status Invest'!A:AB,28,0) | K42: =VLOOKUP(Table_1[[#This Row],[AÇÕES]],'Dados Status Invest'!A:AA,27,0) | L42: =Table_1[[#This Row],[PREÇO]]*Table_1[[#This Row],[DY]] | M42: =$E$13 | N42: 0.3 | O42: =Table_1[[#This Row],[DPA]]/Table_1[[#This Row],[LPA]] | P42: =IF(Table_1[[#This Row],[PAYOUT]]<=40%,"CRESCIMENTO",IF(Table_1[[#This Row],[PAYOUT]]<=60%,"INDEFINIDO","DIVIDENDOS")) | Q42: =VLOOKUP(Table_1[[#This Row],[AÇÕES]],'Dados Status Invest'!A:R,18,0)/100 | R42: =VLOOKUP(Table_1[[#This Row],[AÇÕES]],'Dados Status Invest'!A:Y,25,0)/100 | S42: =(1-Table_1[[#This Row],[PAYOUT]])*Table_1[[#This Row],[ROE]] | T42: =AVERAGE(Table_1[[#This Row],[CAGR LUCRO 5A]],Table_1[[#This Row],[CRESCIMENTO DAMODARAN]]) | U42: =(Table_1[[#This Row],[PREÇO JUSTO BAZIN]]-Table_1[[#This Row],[PREÇO]])/Table_1[[#This Row],[PREÇO JUSTO BAZIN]] | V42: =Table_1[[#This Row],[DPA]]/6% | W42: =Table_1[[#This Row],[PREÇO JUSTO BAZIN]]/(1+Table_1[[#This Row],[MARGEM DE DESCONTO]]) | X42: =(Table_1[[#This Row],[PREÇO JUSTO GRAHAM]]-Table_1[[#This Row],[PREÇO]])/Table_1[[#This Row],[PREÇO JUSTO GRAHAM]] | Y42: =(22.5*Table_1[[#This Row],[LPA]]*Table_1[[#This Row],[VPA]])^0.5 | Z42: =Table_1[[#This Row],[PREÇO JUSTO GRAHAM]]/(1+Table_1[[#This Row],[MARGEM DE DESCONTO]]) | AA42: =(Table_1[[#This Row],[PREÇO JUSTO GORDON]]-Table_1[[#This Row],[PREÇO]])/Table_1[[#This Row],[PREÇO JUSTO GORDON]] | AB42: =Table_1[[#This Row],[DPA]]*(1+Table_1[[#This Row],[MÉDIA DE CRESCIMENTO]]) | AC42: =Table_1[[#This Row],[D1]]/(Table_1[[#This Row],[RISCO]]-Table_1[[#This Row],[MÉDIA DE CRESCIMENTO]]) | AD42: =Table_1[[#This Row],[PREÇO JUSTO GORDON]]/(1+Table_1[[#This Row],[MARGEM DE DESCONTO]]) | AE42: =Table_1[[#This Row],[P/L]]/Table_1[[#This Row],[MÉDIA DE CRESCIMENTO]]
B43: ='Dados Status Invest'!A29 | C43: =VLOOKUP(Table_1[[#This Row],[AÇÕES]],'Classificação B3'!A:B,2,0) | D43: =VLOOKUP(Table_1[[#This Row],[AÇÕES]],'Classificação B3'!A:D,4,0) | E43: =VLOOKUP(Table_1[[#This Row],[AÇÕES]],'Classificação B3'!A:F,6,0) | F43: =VLOOKUP(Table_1[[#This Row],[AÇÕES]],'Classificação B3'!A:G,7,0) | G43: =VLOOKUP(Table_1[[#This Row],[AÇÕES]],'Dados Status Invest'!A:B,2,0) | H43: =VLOOKUP(Table_1[[#This Row],[AÇÕES]],'Dados Status Invest'!A:C,3,0)/100 | I43: =VLOOKUP(Table_1[[#This Row],[AÇÕES]],'Dados Status Invest'!A:D,4,0)/100 | J43: =VLOOKUP(Table_1[[#This Row],[AÇÕES]],'Dados Status Invest'!A:AB,28,0) | K43: =VLOOKUP(Table_1[[#This Row],[AÇÕES]],'Dados Status Invest'!A:AA,27,0) | L43: =Table_1[[#This Row],[PREÇO]]*Table_1[[#This Row],[DY]] | M43: =$E$13 | N43: 0.3 | O43: =Table_1[[#This Row],[DPA]]/Table_1[[#This Row],[LPA]] | P43: =IF(Table_1[[#This Row],[PAYOUT]]<=40%,"CRESCIMENTO",IF(Table_1[[#This Row],[PAYOUT]]<=60%,"INDEFINIDO","DIVIDENDOS")) | Q43: =VLOOKUP(Table_1[[#This Row],[AÇÕES]],'Dados Status Invest'!A:R,18,0)/100 | R43: =VLOOKUP(Table_1[[#This Row],[AÇÕES]],'Dados Status Invest'!A:Y,25,0)/100 | S43: =(1-Table_1[[#This Row],[PAYOUT]])*Table_1[[#This Row],[ROE]] | T43: =AVERAGE(Table_1[[#This Row],[CAGR LUCRO 5A]],Table_1[[#This Row],[CRESCIMENTO DAMODARAN]]) | U43: =(Table_1[[#This Row],[PREÇO JUSTO BAZIN]]-Table_1[[#This Row],[PREÇO]])/Table_1[[#This Row],[PREÇO JUSTO BAZIN]] | V43: =Table_1[[#This Row],[DPA]]/6% | W43: =Table_1[[#This Row],[PREÇO JUSTO BAZIN]]/(1+Table_1[[#This Row],[MARGEM DE DESCONTO]]) | X43: =(Table_1[[#This Row],[PREÇO JUSTO GRAHAM]]-Table_1[[#This Row],[PREÇO]])/Table_1[[#This Row],[PREÇO JUSTO GRAHAM]] | Y43: =(22.5*Table_1[[#This Row],[LPA]]*Table_1[[#This Row],[VPA]])^0.5 | Z43: =Table_1[[#This Row],[PREÇO JUSTO GRAHAM]]/(1+Table_1[[#This Row],[MARGEM DE DESCONTO]]) | AA43: =(Table_1[[#This Row],[PREÇO JUSTO GORDON]]-Table_1[[#This Row],[PREÇO]])/Table_1[[#This Row],[PREÇO JUSTO GORDON]] | AB43: =Table_1[[#This Row],[DPA]]*(1+Table_1[[#This Row],[MÉDIA DE CRESCIMENTO]]) | AC43: =Table_1[[#This Row],[D1]]/(Table_1[[#This Row],[RISCO]]-Table_1[[#This Row],[MÉDIA DE CRESCIMENTO]]) | AD43: =Table_1[[#This Row],[PREÇO JUSTO GORDON]]/(1+Table_1[[#This Row],[MARGEM DE DESCONTO]]) | AE43: =Table_1[[#This Row],[P/L]]/Table_1[[#This Row],[MÉDIA DE CRESCIMENTO]]
B44: ='Dados Status Invest'!A30 | C44: =VLOOKUP(Table_1[[#This Row],[AÇÕES]],'Classificação B3'!A:B,2,0) | D44: =VLOOKUP(Table_1[[#This Row],[AÇÕES]],'Classificação B3'!A:D,4,0) | E44: =VLOOKUP(Table_1[[#This Row],[AÇÕES]],'Classificação B3'!A:F,6,0) | F44: =VLOOKUP(Table_1[[#This Row],[AÇÕES]],'Classificação B3'!A:G,7,0) | G44: =VLOOKUP(Table_1[[#This Row],[AÇÕES]],'Dados Status Invest'!A:B,2,0) | H44: =VLOOKUP(Table_1[[#This Row],[AÇÕES]],'Dados Status Invest'!A:C,3,0)/100 | I44: =VLOOKUP(Table_1[[#This Row],[AÇÕES]],'Dados Status Invest'!A:D,4,0)/100 | J44: =VLOOKUP(Table_1[[#This Row],[AÇÕES]],'Dados Status Invest'!A:AB,28,0) | K44: =VLOOKUP(Table_1[[#This Row],[AÇÕES]],'Dados Status Invest'!A:AA,27,0) | L44: =Table_1[[#This Row],[PREÇO]]*Table_1[[#This Row],[DY]] | M44: =$E$13 | N44: 0.3 | O44: =Table_1[[#This Row],[DPA]]/Table_1[[#This Row],[LPA]] | P44: =IF(Table_1[[#This Row],[PAYOUT]]<=40%,"CRESCIMENTO",IF(Table_1[[#This Row],[PAYOUT]]<=60%,"INDEFINIDO","DIVIDENDOS")) | Q44: =VLOOKUP(Table_1[[#This Row],[AÇÕES]],'Dados Status Invest'!A:R,18,0)/100 | R44: =VLOOKUP(Table_1[[#This Row],[AÇÕES]],'Dados Status Invest'!A:Y,25,0)/100 | S44: =(1-Table_1[[#This Row],[PAYOUT]])*Table_1[[#This Row],[ROE]] | T44: =AVERAGE(Table_1[[#This Row],[CAGR LUCRO 5A]],Table_1[[#This Row],[CRESCIMENTO DAMODARAN]]) | U44: =(Table_1[[#This Row],[PREÇO JUSTO BAZIN]]-Table_1[[#This Row],[PREÇO]])/Table_1[[#This Row],[PREÇO JUSTO BAZIN]] | V44: =Table_1[[#This Row],[DPA]]/6% | W44: =Table_1[[#This Row],[PREÇO JUSTO BAZIN]]/(1+Table_1[[#This Row],[MARGEM DE DESCONTO]]) | X44: =(Table_1[[#This Row],[PREÇO JUSTO GRAHAM]]-Table_1[[#This Row],[PREÇO]])/Table_1[[#This Row],[PREÇO JUSTO GRAHAM]] | Y44: =(22.5*Table_1[[#This Row],[LPA]]*Table_1[[#This Row],[VPA]])^0.5 | Z44: =Table_1[[#This Row],[PREÇO JUSTO GRAHAM]]/(1+Table_1[[#This Row],[MARGEM DE DESCONTO]]) | AA44: =(Table_1[[#This Row],[PREÇO JUSTO GORDON]]-Table_1[[#This Row],[PREÇO]])/Table_1[[#This Row],[PREÇO JUSTO GORDON]] | AB44: =Table_1[[#This Row],[DPA]]*(1+Table_1[[#This Row],[MÉDIA DE CRESCIMENTO]]) | AC44: =Table_1[[#This Row],[D1]]/(Table_1[[#This Row],[RISCO]]-Table_1[[#This Row],[MÉDIA DE CRESCIMENTO]]) | AD44: =Table_1[[#This Row],[PREÇO JUSTO GORDON]]/(1+Table_1[[#This Row],[MARGEM DE DESCONTO]]) | AE44: =Table_1[[#This Row],[P/L]]/Table_1[[#This Row],[MÉDIA DE CRESCIMENTO]]
B45: ='Dados Status Invest'!A31 | C45: =VLOOKUP(Table_1[[#This Row],[AÇÕES]],'Classificação B3'!A:B,2,0) | D45: =VLOOKUP(Table_1[[#This Row],[AÇÕES]],'Classificação B3'!A:D,4,0) | E45: =VLOOKUP(Table_1[[#This Row],[AÇÕES]],'Classificação B3'!A:F,6,0) | F45: =VLOOKUP(Table_1[[#This Row],[AÇÕES]],'Classificação B3'!A:G,7,0) | G45: =VLOOKUP(Table_1[[#This Row],[AÇÕES]],'Dados Status Invest'!A:B,2,0) | H45: =VLOOKUP(Table_1[[#This Row],[AÇÕES]],'Dados Status Invest'!A:C,3,0)/100 | I45: =VLOOKUP(Table_1[[#This Row],[AÇÕES]],'Dados Status Invest'!A:D,4,0)/100 | J45: =VLOOKUP(Table_1[[#This Row],[AÇÕES]],'Dados Status Invest'!A:AB,28,0) | K45: =VLOOKUP(Table_1[[#This Row],[AÇÕES]],'Dados Status Invest'!A:AA,27,0) | L45: =Table_1[[#This Row],[PREÇO]]*Table_1[[#This Row],[DY]] | M45: =$E$13 | N45: 0.3 | O45: =Table_1[[#This Row],[DPA]]/Table_1[[#This Row],[LPA]] | P45: =IF(Table_1[[#This Row],[PAYOUT]]<=40%,"CRESCIMENTO",IF(Table_1[[#This Row],[PAYOUT]]<=60%,"INDEFINIDO","DIVIDENDOS")) | Q45: =VLOOKUP(Table_1[[#This Row],[AÇÕES]],'Dados Status Invest'!A:R,18,0)/100 | R45: =VLOOKUP(Table_1[[#This Row],[AÇÕES]],'Dados Status Invest'!A:Y,25,0)/100 | S45: =(1-Table_1[[#This Row],[PAYOUT]])*Table_1[[#This Row],[ROE]] | T45: =AVERAGE(Table_1[[#This Row],[CAGR LUCRO 5A]],Table_1[[#This Row],[CRESCIMENTO DAMODARAN]]) | U45: =(Table_1[[#This Row],[PREÇO JUSTO BAZIN]]-Table_1[[#This Row],[PREÇO]])/Table_1[[#This Row],[PREÇO JUSTO BAZIN]] | V45: =Table_1[[#This Row],[DPA]]/6% | W45: =Table_1[[#This Row],[PREÇO JUSTO BAZIN]]/(1+Table_1[[#This Row],[MARGEM DE DESCONTO]]) | X45: =(Table_1[[#This Row],[PREÇO JUSTO GRAHAM]]-Table_1[[#This Row],[PREÇO]])/Table_1[[#This Row],[PREÇO JUSTO GRAHAM]] | Y45: =(22.5*Table_1[[#This Row],[LPA]]*Table_1[[#This Row],[VPA]])^0.5 | Z45: =Table_1[[#This Row],[PREÇO JUSTO GRAHAM]]/(1+Table_1[[#This Row],[MARGEM DE DESCONTO]]) | AA45: =(Table_1[[#This Row],[PREÇO JUSTO GORDON]]-Table_1[[#This Row],[PREÇO]])/Table_1[[#This Row],[PREÇO JUSTO GORDON]] | AB45: =Table_1[[#This Row],[DPA]]*(1+Table_1[[#This Row],[MÉDIA DE CRESCIMENTO]]) | AC45: =Table_1[[#This Row],[D1]]/(Table_1[[#This Row],[RISCO]]-Table_1[[#This Row],[MÉDIA DE CRESCIMENTO]]) | AD45: =Table_1[[#This Row],[PREÇO JUSTO GORDON]]/(1+Table_1[[#This Row],[MARGEM DE DESCONTO]]) | AE45: =Table_1[[#This Row],[P/L]]/Table_1[[#This Row],[MÉDIA DE CRESCIMENTO]]
B46: ='Dados Status Invest'!A32 | C46: =VLOOKUP(Table_1[[#This Row],[AÇÕES]],'Classificação B3'!A:B,2,0) | D46: =VLOOKUP(Table_1[[#This Row],[AÇÕES]],'Classificação B3'!A:D,4,0) | E46: =VLOOKUP(Table_1[[#This Row],[AÇÕES]],'Classificação B3'!A:F,6,0) | F46: =VLOOKUP(Table_1[[#This Row],[AÇÕES]],'Classificação B3'!A:G,7,0) | G46: =VLOOKUP(Table_1[[#This Row],[AÇÕES]],'Dados Status Invest'!A:B,2,0) | H46: =VLOOKUP(Table_1[[#This Row],[AÇÕES]],'Dados Status Invest'!A:C,3,0)/100 | I46: =VLOOKUP(Table_1[[#This Row],[AÇÕES]],'Dados Status Invest'!A:D,4,0)/100 | J46: =VLOOKUP(Table_1[[#This Row],[AÇÕES]],'Dados Status Invest'!A:AB,28,0) | K46: =VLOOKUP(Table_1[[#This Row],[AÇÕES]],'Dados Status Invest'!A:AA,27,0) | L46: =Table_1[[#This Row],[PREÇO]]*Table_1[[#This Row],[DY]] | M46: =$E$13 | N46: 0.3 | O46: =Table_1[[#This Row],[DPA]]/Table_1[[#This Row],[LPA]] | P46: =IF(Table_1[[#This Row],[PAYOUT]]<=40%,"CRESCIMENTO",IF(Table_1[[#This Row],[PAYOUT]]<=60%,"INDEFINIDO","DIVIDENDOS")) | Q46: =VLOOKUP(Table_1[[#This Row],[AÇÕES]],'Dados Status Invest'!A:R,18,0)/100 | R46: =VLOOKUP(Table_1[[#This Row],[AÇÕES]],'Dados Status Invest'!A:Y,25,0)/100 | S46: =(1-Table_1[[#This Row],[PAYOUT]])*Table_1[[#This Row],[ROE]] | T46: =AVERAGE(Table_1[[#This Row],[CAGR LUCRO 5A]],Table_1[[#This Row],[CRESCIMENTO DAMODARAN]]) | U46: =(Table_1[[#This Row],[PREÇO JUSTO BAZIN]]-Table_1[[#This Row],[PREÇO]])/Table_1[[#This Row],[PREÇO JUSTO BAZIN]] | V46: =Table_1[[#This Row],[DPA]]/6% | W46: =Table_1[[#This Row],[PREÇO JUSTO BAZIN]]/(1+Table_1[[#This Row],[MARGEM DE DESCONTO]]) | X46: =(Table_1[[#This Row],[PREÇO JUSTO GRAHAM]]-Table_1[[#This Row],[PREÇO]])/Table_1[[#This Row],[PREÇO JUSTO GRAHAM]] | Y46: =(22.5*Table_1[[#This Row],[LPA]]*Table_1[[#This Row],[VPA]])^0.5 | Z46: =Table_1[[#This Row],[PREÇO JUSTO GRAHAM]]/(1+Table_1[[#This Row],[MARGEM DE DESCONTO]]) | AA46: =(Table_1[[#This Row],[PREÇO JUSTO GORDON]]-Table_1[[#This Row],[PREÇO]])/Table_1[[#This Row],[PREÇO JUSTO GORDON]] | AB46: =Table_1[[#This Row],[DPA]]*(1+Table_1[[#This Row],[MÉDIA DE CRESCIMENTO]]) | AC46: =Table_1[[#This Row],[D1]]/(Table_1[[#This Row],[RISCO]]-Table_1[[#This Row],[MÉDIA DE CRESCIMENTO]]) | AD46: =Table_1[[#This Row],[PREÇO JUSTO GORDON]]/(1+Table_1[[#This Row],[MARGEM DE DESCONTO]]) | AE46: =Table_1[[#This Row],[P/L]]/Table_1[[#This Row],[MÉDIA DE CRESCIMENTO]]
... B702: ='Dados Status Invest'!A688 | C702: =VLOOKUP(Table_1[[#This Row],[AÇÕES]],'Classificação B3'!A:B,2,0) | D702: =VLOOKUP(Table_1[[#This Row],[AÇÕES]],'Classificação B3'!A:D,4,0) | E702: =VLOOKUP(Table_1[[#This Row],[AÇÕES]],'Classificação B3'!A:F,6,0) | F702: =VLOOKUP(Table_1[[#This Row],[AÇÕES]],'Classificação B3'!A:G,7,0) | G702: =VLOOKUP(Table_1[[#This Row],[AÇÕES]],'Dados Status Invest'!A:B,2,0) | H702: =VLOOKUP(Table_1[[#This Row],[AÇÕES]],'Dados Status Invest'!A:C,3,0)/100 | I702: =VLOOKUP(Table_1[[#This Row],[AÇÕES]],'Dados Status Invest'!A:D,4,0)/100 | J702: =VLOOKUP(Table_1[[#This Row],[AÇÕES]],'Dados Status Invest'!A:AB,28,0) | K702: =VLOOKUP(Table_1[[#This Row],[AÇÕES]],'Dados Status Invest'!A:AA,27,0) | L702: =Table_1[[#This Row],[PREÇO]]*Table_1[[#This Row],[DY]] | M702: =$E$13 | N702: 0.3 | O702: =Table_1[[#This Row],[DPA]]/Table_1[[#This Row],[LPA]] | P702: =IF(Table_1[[#This Row],[PAYOUT]]<=40%,"CRESCIMENTO",IF(Table_1[[#This Row],[PAYOUT]]<=60%,"INDEFINIDO","DIVIDENDOS")) | Q702: =VLOOKUP(Table_1[[#This Row],[AÇÕES]],'Dados Status Invest'!A:R,18,0)/100 | R702: =VLOOKUP(Table_1[[#This Row],[AÇÕES]],'Dados Status Invest'!A:Y,25,0)/100 | S702: =(1-Table_1[[#This Row],[PAYOUT]])*Table_1[[#This Row],[ROE]] | T702: =AVERAGE(Table_1[[#This Row],[CAGR LUCRO 5A]],Table_1[[#This Row],[CRESCIMENTO DAMODARAN]]) | U702: =(Table_1[[#This Row],[PREÇO JUSTO BAZIN]]-Table_1[[#This Row],[PREÇO]])/Table_1[[#This Row],[PREÇO JUSTO BAZIN]] | V702: =Table_1[[#This Row],[DPA]]/6% | W702: =Table_1[[#This Row],[PREÇO JUSTO BAZIN]]/(1+Table_1[[#This Row],[MARGEM DE DESCONTO]]) | X702: =(Table_1[[#This Row],[PREÇO JUSTO GRAHAM]]-Table_1[[#This Row],[PREÇO]])/Table_1[[#This Row],[PREÇO JUSTO GRAHAM]] | Y702: =(22.5*Table_1[[#This Row],[LPA]]*Table_1[[#This Row],[VPA]])^0.5 | Z702: =Table_1[[#This Row],[PREÇO JUSTO GRAHAM]]/(1+Table_1[[#This Row],[MARGEM DE DESCONTO]]) | AA702: =(Table_1[[#This Row],[PREÇO JUSTO GORDON]]-Table_1[[#This Row],[PREÇO]])/Table_1[[#This Row],[PREÇO JUSTO GORDON]] | AB702: =Table_1[[#This Row],[DPA]]*(1+Table_1[[#This Row],[MÉDIA DE CRESCIMENTO]]) | AC702: =Table_1[[#This Row],[D1]]/(Table_1[[#This Row],[RISCO]]-Table_1[[#This Row],[MÉDIA DE CRESCIMENTO]]) | AD702: =Table_1[[#This Row],[PREÇO JUSTO GORDON]]/(1+Table_1[[#This Row],[MARGEM DE DESCONTO]]) | AE702: =Table_1[[#This Row],[P/L]]/Table_1[[#This Row],[MÉDIA DE CRESCIMENTO]]

Sheet Dados Status Invest
A1: TICKER | B1: PRECO | C1: DY | D1: P/L | E1: P/VP | F1: P/ATIVOS | G1: MARGEM BRUTA | H1: MARGEM EBIT | I1: MARG. LIQUIDA | J1: P/EBIT | K1: EV/EBIT | L1: DIVIDA LIQUIDA / EBIT | M1: DIV. LIQ. / PATRI. | N1: PSR | O1: P/CAP. GIRO | P1: P. AT CIR. LIQ. | Q1: LIQ. CORRENTE | R1: ROE | S1: ROA | T1: ROIC | U1: PATRIMONIO / ATIVOS | V1: PASSIVOS / ATIVOS | W1: GIRO ATIVOS | X1: CAGR RECEITAS 5 ANOS | Y1: CAGR LUCROS 5 ANOS | Z1: LIQUIDEZ MEDIA DIARIA | AA1: VPA | AB1: LPA | AC1: PEG Ratio | AD1: VALOR DE MERCADO
A2: AALR3 | B2: 3.22 | D2: -6.1 | E2: 0.46 | F2: 0.16 | G2: 26.83 | H2: 9.47 | I2: -6.49 | J2: 4.18 | K2: 7.22 | L2: 3.1 | M2: 0.34 | N2: 0.4 | O2: 112.19 | P2: -0.22 | Q2: 1.01 | R2: -7.54 | S2: -2.66 | T2: 5.63 | U2: 0.35 | V2: 0.64 | W2: 0.41 | X2: 2.55 | Z2: 181348.23 | AA2: 7 | AB2: -0.53 | AC2: 0.12 | AD2: 4.8450315e+08
A3: ABCB4 | B3: 23.7 | C3: 11.39 | D3: 6.14 | E3: 0.86 | F3: 0.09 | G3: 15.81 | H3: 14.7 | I3: 12.2 | J3: 5.09 | K3: 5.09 | N3: 0.75 | O3: -2.01 | P3: -0.09 | Q3: 0.26 | R3: 14.08 | S3: 1.5 | U3: 0.11 | V3: 0.89 | W3: 0.12 | X3: 28.96 | Y3: 24.19 | Z3: 12186035 | AA3: 27.43 | AB3: 3.86 | AC3: 1.82 | AD3: 6.1684276e+09
A4: ABEV3 | B4: 16.06 | C4: 8.15 | D4: 16.24 | E4: 2.81 | F4: 1.77 | G4: 51.48 | H4: 26.87 | I4: 17.66 | J4: 10.68 | K4: 10.02 | L4: -0.7 | M4: -0.18 | N4: 2.87 | O4: 216.41 | P4: -2.53 | Q4: 1.03 | R4: 17.28 | S4: 10.91 | T4: 21.1 | U4: 0.63 | V4: 0.36 | W4: 0.62 | X4: 8.61 | Y4: 6.48 | Z4: 3.802934e+08 | AA4: 5.72 | AB4: 0.99 | AC4: 2.04 | AD4: 2.5395264e+11
A5: ADHM3 | B5: 1.56 | D5: -4.09 | E5: -1.29 | F5: 105.12 | G5: 100 | H5: -13548.48 | I5: -18860.61 | J5: -5.69 | K5: -5.69 | L5: 0 | N5: 770.9 | O5: -1.43 | P5: -116.16 | Q5: 0 | R5: -31.47 | S5: -2571.9 | T5: 22.61 | U5: -81.72 | V5: 82.72 | W5: 0.14 | AA5: -1.21 | AB5: -0.38 | AC5: -0.58 | AD5: 25439770
A6: AERI3 | B6: 2.08 | D6: -0.14 | E6: -0.15 | F6: 0.09 | G6: -6.13 | H6: -83.8 | I6: -147.32 | J6: -0.24 | K6: -3.71 | L6: -3.47 | N6: 0.2 | O6: -0.71 | P6: -0.12 | Q6: 0.69 | R6: -112.94 | S6: -62.35 | T6: -66.14 | U6: -0.55 | V6: 1.55 | W6: 0.42 | X6: -19.51 | Z6: 68440.95 | AA6: -13.47 | AB6: -15.21 | AC6: 0.03 | AD6: 1.2921001e+08
A7: AESB3 | B7: 8.12 | D7: -21.02 | E7: 1.83 | F7: 0.42 | G7: 27.29 | H7: 23.39 | I7: -9.44 | J7: 8.48 | K7: 18.4 | L7: 9.93 | M7: 2.15 | N7: 1.98 | O7: -11.75 | P7: -0.49 | Q7: 0.79 | R7: -8.72 | S7: -2.02 | T7: 4.23 | U7: 0.23 | V7: 0.71 | W7: 0.21 | Z7: 13684494 | AA7: 4.43 | AB7: -0.39 | AC7: 2.77 | AD7: 8.3679142e+09
A8: AFLT3 | B8: 7.17 | C8: 7.25 | D8: 12.69 | E8: 1.86 | F8: 1.23 | G8: 79.2 | H8: 69.95 | I8: 55.98 | J8: 10.15 | K8: 9.51 | L8: -0.64 | M8: -0.12 | N8: 7.1 | O8: 7.24 | P8: -1.94 | Q8: 1.85 | R8: 14.63 | S8: 9.66 | T8: 13.09 | U8: 0.66 | V8: 0.34 | W8: 0.17 | X8: 6.47 | Y8: 13.77 | Z8: 4372.23 | AA8: 3.86 | AB8: 0.57 | AC8: 0.35 | AD8: 452317299
A9: AGRO3 | B9: 18.97 | C9: 3.97 | D9: -131.74 | E9: 0.95 | F9: 0.51 | G9: 12.72 | H9: -1.76 | I9: -1.54 | J9: -115.47 | K9: -195.49 | L9: -80.02 | M9: 0.66 | N9: 2.03 | O9: 5.05 | P9: -0.74 | Q9: 1.47 | R9: -0.72 | S9: -0.39 | T9: -3.64 | U9: 0.53 | V9: 0.47 | W9: 0.25 | X9: 10.7 | Z9: 1804706.8 | AA9: 19.88 | AB9: -0.14 | AC9: 1.26 | AD9: 1.9479049e+09
A10: AGXY3 | B10: 1.73 | D10: 0.03 | E10: -0.18 | F10: 0.02 | G10: -1.14 | H10: 39.74 | I10: 70.06 | J10: 0.05 | K10: 1.41 | L10: 1.36 | N10: 0.02 | O10: 0.07 | P10: -0.03 | Q10: 2.19 | R10: -661.54 | S10: 55.38 | T10: 83.66 | U10: -0.08 | V10: 1.08 | W10: 0.79 | X10: 24.29 | Y10: 123.15 | Z10: 37126.14 | AA10: -9.78 | AB10: 64.68 | AC10: 0 | AD10: 33007054
A11: AHEB3 | B11: 23.9 | D11: 4.12 | E11: 0.7 | F11: 0.34 | G11: 18.5 | H11: 10.33 | I11: 8.96 | J11: 3.57 | K11: 2.2 | L11: -1.44 | M11: -0.28 | N11: 0.37 | O11: 1.34 | P11: -0.6 | Q11: 2.45 | R11: 16.94 | S11: 8.27 | T11: 15.74 | U11: 0.49 | V11: 0.51 | W11: 0.92 | X11: 21.7 | Z11: 2711.47 | AA11: 34.23 | AB11: 5.8 | AC11: -0.07 | AD11: 2.084292e+08
A12: AHEB5 | B12: 58 | D12: 10 | E12: 1.69 | F12: 0.83 | G12: 18.5 | H12: 10.33 | I12: 8.96 | J12: 8.67 | K12: 2.2 | L12: -1.44 | M12: -0.28 | N12: 0.9 | O12: 3.25 | P12: -1.45 | Q12: 2.45 | R12: 16.94 | S12: 8.27 | T12: 15.74 | U12: 0.49 | V12: 0.51 | W12: 0.92 | X12: 21.7 | AA12: 34.23 | AB12: 5.8 | AC12: -0.18 | AD12: 2.084292e+08
A13: AHEB6 | B13: 55 | D13: 9.49 | E13: 1.61 | F13: 0.78 | G13: 18.5 | H13: 10.33 | I13: 8.96 | J13: 8.23 | K13: 2.2 | L13: -1.44 | M13: -0.28 | N13: 0.85 | O13: 3.08 | P13: -1.38 | Q13: 2.45 | R13: 16.94 | S13: 8.27 | T13: 15.74 | U13: 0.49 | V13: 0.51 | W13: 0.92 | X13: 21.7 | AA13: 34.23 | AB13: 5.8 | AC13: -0.17 | AD13: 2.084292e+08
A14: ALLD3 | B14: 4.47 | C14: 25.97 | D14: 1.25 | E14: 0.28 | F14: 0.13 | G14: 11.75 | H14: 9.41 | I14: 6.26 | J14: 0.83 | K14: 1.1 | L14: 0.26 | M14: 0.09 | N14: 0.08 | O14: 0.41 | P14: -0.45 | Q14: 1.74 | R14: 22.27 | S14: 10.1 | T14: 18.12 | U14: 0.45 | V14: 0.55 | W14: 1.61 | X14: 3.11 | Y14: 15.35 | Z14: 1684980.9 | AA14: 16.02 | AB14: 3.57 | AC14: 0.01 | AD14: 4.2990768e+08
A15: ALOS3 | B15: 26.56 | C15: 11.07 | D15: 16.18 | E15: 1.03 | F15: 0.54 | G15: 73.41 | H15: 52.49 | I15: 28.81 | J15: 8.88 | K15: 7.46 | L15: -1.43 | M15: -0.17 | N15: 4.66 | O15: 7.08 | P15: -0.61 | Q15: 2.81 | R15: 6.39 | S15: 3.33 | T15: 11.37 | U15: 0.52 | V15: 0.48 | W15: 0.12 | X15: 29.09 | Y15: 37.4 | Z15: 95348489 | AA15: 25.71 | AB15: 1.64 | AC15: -4.06 | AD15: 1.3411479e+10
A16: ALPA3 | B16: 8.64 | C16: 5.69 | D16: 9.53 | E16: 1.71 | F16: 0.94 | G16: 52.49 | H16: 14.46 | I16: 13.17 | J16: 8.68 | K16: 10.85 | L16: 0.71 | M16: 0.14 | N16: 1.26 | O16: 4.64 | P16: -1.81 | Q16: 1.73 | R16: 17.9 | S16: 9.85 | T16: 13.55 | U16: 0.55 | V16: 0.45 | W16: 0.75 | X16: 6.29 | Y16: 34.59 | Z16: 68152.82 | AA16: 5.06 | AB16: 0.91 | AC16: 0.04 | AD16: 6.897957e+09
A17: ALPA4 | B17: 11.53 | C17: 4.68 | D17: 12.75 | E17: 2.28 | F17: 1.26 | G17: 52.49 | H17: 14.46 | I17: 13.17 | J17: 11.61 | K17: 10.85 | L17: 0.71 | M17: 0.14 | N17: 1.68 | O17: 6.21 | P17: -2.42 | Q17: 1.73 | R17: 17.9 | S17: 9.85 | T17: 13.55 | U17: 0.55 | V17: 0.45 | W17: 0.75 | X17: 6.29 | Y17: 34.59 | Z17: 13851315 | AA17: 5.06 | AB17: 0.91 | AC17: 0.06 | AD17: 6.897957e+09
A18: ALPK3 | B18: 4.26 | C18: 0.18 | D18: 69.03 | E18: 2.58 | F18: 0.36 | G18: 30.29 | H18: 13.9 | I18: 0.7 | J18: 3.46 | K18: 8.16 | L18: 4.66 | M18: 3.48 | N18: 0.48 | O18: -11.33 | P18: -0.45 | Q18: 0.86 | R18: 3.74 | S18: 0.52 | T18: 13.52 | U18: 0.14 | V18: 0.86 | W18: 0.75 | X18: 23.59 | Z18: 712448.73 | AA18: 1.65 | AB18: 0.06 | AC18: -0.17 | AD18: 9.4520771e+08
A19: ALUP11 | B19: 32.47 | C19: 3.33 | D19: 9.6 | E19: 1.15 | F19: 0.31 | G19: 66.96 | H19: 67.25 | I19: 25.17 | J19: 3.59 | K19: 6.72 | L19: 3.13 | M19: 1 | N19: 2.42 | O19: 1.85 | P19: -0.41 | Q19: 3.3 | R19: 12 | S19: 3.25 | T19: 9.07 | U19: 0.27 | V19: 0.63 | W19: 0.13 | X19: -6.46 | Y19: 3.42 | Z19: 21728657 | AA19: 28.17 | AB19: 3.38 | AC19: -7.2 | AD19: 1.0709577e+10
A20: ALUP3 | B20: 11.57 | C20: 3.11 | D20: 10.26 | E20: 1.23 | F20: 0.33 | G20: 66.96 | H20: 67.25 | I20: 25.17 | J20: 3.84 | K20: 6.72 | L20: 3.13 | M20: 1 | N20: 2.58 | O20: 1.98 | P20: -0.44 | Q20: 3.3 | R20: 12 | S20: 3.25 | T20: 9.07 | U20: 0.27 | V20: 0.63 | W20: 0.13 | X20: -6.46 | Y20: 3.42 | Z20: 75012.32 | AA20: 9.39 | AB20: 1.13 | AC20: -7.69 | AD20: 1.0709577e+10
A21: ALUP4 | B21: 10.51 | C21: 3.43 | D21: 9.32 | E21: 1.12 | F21: 0.3 | G21: 66.96 | H21: 67.25 | I21: 25.17 | J21: 3.49 | K21: 6.72 | L21: 3.13 | M21: 1 | N21: 2.35 | O21: 1.8 | P21: -0.4 | Q21: 3.3 | R21: 12 | S21: 3.25 | T21: 9.07 | U21: 0.27 | V21: 0.63 | W21: 0.13 | X21: -6.46 | Y21: 3.42 | Z21: 105392.95 | AA21: 9.39 | AB21: 1.13 | AC21: -6.99 | AD21: 1.0709577e+10
A22: AMAR3 | B22: 0.58 | D22: -1.92 | E22: 2.35 | F22: 0.15 | G22: 52.58 | H22: 10.01 | I22: -10.75 | J22: 2.06 | K22: 7.5 | L22: 5.48 | M22: 6.27 | N22: 0.21 | O22: -0.69 | P22: -0.21 | Q22: 0.56 | R22: -122.78 | S22: -7.76 | T22: 15.07 | U22: 0.06 | V22: 0.94 | W22: 0.72 | X22: -7.06 | Z22: 124715.86 | AA22: 0.25 | AB22: -0.31 | AC22: 0.46 | AD22: 2.9783946e+08
A23: AMBP3 | B23: 0.16 | D23: -1.04 | E23: 0.24 | F23: 0.02 | G23: 18.22 | H23: 17.36 | I23: -3.54 | J23: 0.21 | K23: 5.27 | L23: 5.06 | M23: 5.81 | N23: 0.04 | O23: 0.06 | P23: -0.03 | Q23: 2.72 | R23: -23.47 | S23: -1.52 | T23: 8.91 | U23: 0.06 | V23: 0.87 | W23: 0.43 | X23: 67.64 | Z23: 823984.05 | AA23: 0.65 | AB23: -0.15 | AC23: 0.05 | AD23: 2.6726699e+08
A24: AMER3 | B24: 4.53 | D24: 1.64 | E24: 0.2 | F24: 0.06 | G24: 26.5 | H24: 3.34 | I24: 4.49 | J24: 2.2 | K24: 5.89 | L24: 3.69 | M24: 0.34 | N24: 0.07 | O24: 0.33 | P24: -0.11 | Q24: 1.56 | R24: 12.51 | S24: 3.43 | T24: 4.51 | U24: 0.27 | V24: 0.73 | W24: 0.76 | X24: 3.98 | Z24: 7981008 | AA24: 22.12 | AB24: 2.77 | AC24: -0.02 | AD24: 9.0711111e+08
A25: AMOB3 | B25: 13.53 | G25: 3.6 | H25: -46.82 | I25: -57.58 | L25: -0.01 | Q25: 0.19 | R25: -2595.29 | S25: -6030.26 | T25: 2660.36 | U25: -2.32 | V25: 3.32 | W25: 104.73 | Z25: 256003.55 | AD25: 0
A26: ANIM3 | B26: 2.24 | C26: 3.65 | D26: 6.71 | E26: 0.38 | F26: 0.09 | G26: 63.13 | H26: 24.93 | I26: 3.27 | J26: 0.88 | K26: 4.94 | L26: 4.05 | M26: 1.73 | N26: 0.22 | O26: 0.7 | P26: -0.11 | Q26: 1.9 | R26: 5.62 | S26: 1.27 | T26: 11.57 | U26: 0.23 | V26: 0.72 | W26: 0.39 | X26: 23.12 | Z26: 29829958 | AA26: 5.92 | AB26: 0.33 | AC26: 0.44 | AD26: 9.0870481e+08
A27: APER3 | B27: 46.75 | D27: -32.82 | E27: 2.02 | F27: 1.01 | G27: 100 | H27: 6.6 | I27: -8.16 | J27: 40.57 | K27: 43.31 | L27: 2.74 | M27: 0.14 | N27: 2.68 | O27: 115.28 | P27: -1.38 | Q27: 1.03 | R27: -6.15 | S27: -3.09 | T27: 2.91 | U27: 0.5 | V27: 0.5 | W27: 0.38 | X27: 29.52 | Z27: 51166 | AA27: 23.16 | AB27: -1.42 | AC27: 0.16 | AD27: 9.5326995e+08
A28: APTI3 | B28: 197.64 | D28: 0.36 | E28: 0.02 | F28: 0.01 | G28: 100 | H28: 37.36 | I28: 22.45 | J28: 0.22 | K28: 0.42 | L28: -1.77 | M28: -0.12 | N28: 0.08 | O28: 0.02 | P28: -0.01 | Q28: 3.99 | R28: 4.24 | S28: 2.03 | T28: 1.8 | U28: 0.48 | V28: 0.52 | W28: 0.09 | X28: 20.51 | Y28: -30.97 | AA28: 13019.79 | AB28: 551.44 | AC28: -0.01 | AD28: 37417457
A29: APTI4 | B29: 2930.92 | D29: 5.32 | E29: 0.23 | F29: 0.11 | G29: 100 | H29: 37.36 | I29: 22.45 | J29: 3.19 | K29: 0.42 | L29: -1.77 | M29: -0.12 | N29: 1.19 | O29: 0.31 | P29: -0.2 | Q29: 3.99 | R29: 4.24 | S29: 2.03 | T29: 1.8 | U29: 0.48 | V29: 0.52 | W29: 0.09 | X29: 20.51 | Y29: -30.97 | AA29: 13019.79 | AB29: 551.44 | AC29: -0.09 | AD29: 37417457
A30: ARML3 | B30: 3.27 | C30: 18.88 | D30: 22.47 | E30: 0.89 | F30: 0.2 | G30: 32.22 | H30: 23.57 | I30: 2.66 | J30: 2.54 | K30: 7.36 | L30: 4.83 | M30: 1.69 | N30: 0.6 | O30: 1.05 | P30: -0.31 | Q30: 2.16 | R30: 3.96 | S30: 0.9 | T30: 8.42 | U30: 0.23 | V30: 0.76 | W30: 0.34 | X30: 76.15 | Y30: 23.61 | Z30: 2218002.2 | AA30: 3.69 | AB30: 0.15 | AC30: -0.37 | AD30: 1.1330357e+09
A31: ARND3 | B31: 0.5 | D31: -0.16 | E31: 0.56 | F31: 0.4 | G31: 91.01 | H31: -748.2 | I31: -764.9 | J31: -0.17 | K31: 0.18 | L31: 0.35 | M31: -1.18 | N31: 1.23 | O31: 0.51 | P31: -53.24 | Q31: 5.15 | R31: -346.26 | S31: -250.83 | T31: -313.74 | U31: 0.72 | V31: 0.2 | W31: 0.33 | X31: 11.16 | Z31: 2738.24 | AA31: 0.89 | AB31: -3.1 | AC31: 0 | AD31: 70495903
A32: ASAI3 | B32: 8.19 | C32: 1.27 | D32: 15.84 | E32: 1.88 | F32: 0.23 | G32: 17.44 | H32: 5.16 | I32: 0.9 | J32: 2.77 | K32: 5.81 | L32: 3 | M32: 2.04 | N32: 0.14 | O32: 6.84 | P32: -0.37 | Q32: 1.1 | R32: 11.89 | S32: 1.48 | T32: 17.18 | U32: 0.12 | V32: 0.88 | W32: 1.64 | X32: 16.49 | Y32: -12.92 | Z32: 69735115 | AA32: 4.35 | AB32: 0.52 | AC32: -1.04 | AD32: 1.1207239e+10
A33: AUAU3 | B33: 3.32 | C33: 0.91 | Z33: 7329943.1 | AD33: 0
A34: AURE3 | B34: 11.15 | D34: -9.05 | E34: 0.98 | F34: 0.25 | G34: 13.55 | H34: 9.24 | I34: -9.73 | J34: 9.53 | K34: 26.05 | L34: 16.5 | M34: 1.7 | N34: 0.88 | O34: 15.87 | P34: -0.29 | Q34: 1.11 | R34: -10.86 | S34: -2.73 | T34: 3.22 | U34: 0.25 | V34: 0.72 | W34: 0.28 | X34: 41.69 | Z34: 29420080 | AA34: 11.34 | AB34: -1.23 | AC34: 0 | AD34: 1.1743226e+10
A35: AVLL3 | B35: 10.84 | D35: -0.63 | E35: -0.38 | F35: 0.06 | G35: 34.7 | H35: 21.53 | I35: -23.55 | J35: 0.69 | K35: 5.35 | L35: 4.66 | N35: 0.15 | O35: -0.77 | P35: -0.11 | Q35: 0.82 | R35: -60.73 | S35: -10.31 | T35: 18.26 | U35: -0.17 | V35: 1.16 | W35: 0.44 | X35: 26.55 | Z35: 4566.27 | AA35: -28.36 | AB35: -17.22 | AC35: 0 | AD35: 84695110
A36: AXIA3 | B36: 51.44 | C36: 7.09 | D36: 15.87 | E36: 1.25 | F36: 0.54 | G36: 47.02 | H36: 15.92 | I36: 21.89 | J36: 21.83 | K36: 29.04 | L36: 6.61 | M36: 0.38 | N36: 3.47 | O36: 5.22 | P36: -0.67 | Q36: 2.11 | R36: 7.88 | S36: 3.41 | T36: -10.23 | U36: 0.43 | V36: 0.57 | W36: 0.16 | X36: 7.26 | Y36: 8.52 | Z36: 529239845 | AA36: 41.16 | AB36: 3.24 | AC36: -9.87 | AD36: 1.5558948e+11
A37: AXIA5 | B37: 55.5 | C37: 6.02 | D37: 17.12 | E37: 1.35 | F37: 0.58 | G37: 47.02 | H37: 15.92 | I37: 21.89 | J37: 23.55 | K37: 29.04 | L37: 6.61 | M37: 0.38 | N37: 3.75 | O37: 5.63 | P37: -0.73 | Q37: 2.11 | R37: 7.88 | S37: 3.41 | T37: -10.23 | U37: 0.43 | V37: 0.57 | W37: 0.16 | X37: 7.26 | Y37: 8.52 | Z37: 0 | AA37: 41.16 | AB37: 3.24 | AC37: -10.65 | AD37: 1.5558948e+11
A38: AXIA6 | B38: 59.2 | C38: 6.78 | D38: 18.26 | E38: 1.44 | F38: 0.62 | G38: 47.02 | H38: 15.92 | I38: 21.89 | J38: 25.12 | K38: 29.04 | L38: 6.61 | M38: 0.38 | N38: 4 | O38: 6 | P38: -0.78 | Q38: 2.11 | R38: 7.88 | S38: 3.41 | T38: -10.23 | U38: 0.43 | V38: 0.57 | W38: 0.16 | X38: 7.26 | Y38: 8.52 | Z38: 48101504 | AA38: 41.16 | AB38: 3.24 | AC38: -11.36 | AD38: 1.5558948e+11
A39: AXIA7 | B39: 50.67 | D39: 15.64 | E39: 1.23 | F39: 0.53 | G39: 47.02 | H39: 15.92 | I39: 21.89 | J39: 21.51 | K39: 29.04 | L39: 6.61 | M39: 0.38 | N39: 3.42 | O39: 5.14 | P39: -0.66 | Q39: 2.11 | R39: 7.88 | S39: 3.41 | T39: -10.23 | U39: 0.43 | V39: 0.57 | W39: 0.16 | X39: 7.26 | Y39: 8.52 | Z39: 64960298 | AA39: 41.16 | AB39: 3.24 | AC39: -9.73 | AD39: 1.5558948e+11
A40: AZEV3 | B40: 3.01 | D40: -0.55 | E40: 2.97 | F40: 0.25 | G40: 15.41 | H40: -83.75 | I40: -135.4 | J40: -0.9 | K40: -1.15 | L40: -0.55 | M40: 1.81 | N40: 0.75 | O40: -1.07 | P40: -0.35 | Q40: 0.55 | R40: -535.98 | S40: -45.37 | T40: -128.7 | U40: 0.08 | V40: 0.92 | W40: 0.34 | X40: 68.75 | Z40: 1322248.7 | AA40: 1.01 | AB40: -5.43 | AC40: 0 | AD40: 2.2553241e+08
A41: AZEV4 | B41: 1.53 | D41: -0.28 | E41: 1.51 | F41: 0.13 | G41: 15.41 | H41: -83.75 | I41: -135.4 | J41: -0.46 | K41: -1.15 | L41: -0.55 | M41: 1.81 | N41: 0.38 | O41: -0.55 | P41: -0.18 | Q41: 0.55 | R41: -535.98 | S41: -45.37 | T41: -128.7 | U41: 0.08 | V41: 0.92 | W41: 0.34 | X41: 68.75 | Z41: 2637002.1 | AA41: 1.01 | AB41: -5.43 | AC41: 0 | AD41: 2.2553241e+08
A42: AZTE3 | B42: 1.3 | Z42: 756651.05 | AD42: 0
A43: AZUL53 | B43: 215 | D43: 17.64 | E43: -20.99 | F43: 2.54 | G43: 23.31 | H43: 22.09 | I43: 20.68 | J43: 16.51 | K43: 3.94 | L43: 3.87 | N43: 3.65 | O43: -10.93 | P43: -3.31 | Q43: 0.5 | R43: -119 | S43: 14.41 | T43: -16.1 | U43: -0.12 | V43: 1.12 | W43: 0.7 | X43: 30.38 | Z43: 55411 | AA43: -10.24 | AB43: 12.19 | AC43: -0.28 | AD43: 3.5627266e+08
A44: AZUL54 | B44: 72.5 | D44: 5.95 | E44: -7.08 | F44: 0.86 | G44: 23.31 | H44: 22.09 | I44: 20.68 | J44: 5.57 | K44: 3.94 | L44: 3.87 | N44: 1.23 | O44: -3.68 | P44: -1.12 | Q44: 0.5 | R44: -119 | S44: 14.41 | T44: -16.1 | U44: -0.12 | V44: 1.12 | W44: 0.7 | X44: 30.38 | Z44: 20945788 | AA44: -10.24 | AB44: 12.19 | AC44: -0.1 | AD44: 3.5627266e+08
A45: AZZA3 | B45: 16.37 | C45: 15.12 | D45: 4.07 | E45: 0.42 | F45: 0.22 | G45: 54.89 | H45: 8.66 | I45: 7.17 | J45: 3.37 | K45: 5.55 | L45: 2.17 | M45: 0.27 | N45: 0.29 | O45: 0.93 | P45: -0.4 | Q45: 2.2 | R45: 10.39 | S45: 5.48 | T45: 1.51 | U45: 0.53 | V45: 0.47 | W45: 0.76 | X45: 49.34 | Y45: 76.49 | Z45: 30924138 | AA45: 38.77 | AB45: 4.03 | AC45: 0.04 | AD45: 3.3926276e+09
A46: B3SA3 | B46: 15.49 | C46: 3.93 | D46: 15.77 | E46: 4.28 | F46: 1.61 | G46: 90.46 | H46: 60.27 | I46: 42.49 | J46: 11.12 | K46: 11.01 | L46: -0.09 | M46: -0.03 | N46: 6.7 | O46: 8.34 | P46: -2.55 | Q46: 2.09 | R46: 27.15 | S46: 10.2 | T46: 6.45 | U46: 0.38 | V46: 0.62 | W46: 0.24 | X46: 3.58 | Y46: 3.6 | Z46: 4.5828155e+08 | AA46: 3.62 | AB46: 0.98 | AC46: 3.34 | AD46: 78018890000
A47: BAHI3 | B47: 4.51 | D47: -2.32 | E47: 7.22 | F47: 0.3 | G47: 46.3 | H47: -3.46 | I47: -15.38 | J47: -10.31 | K47: -13.03 | L47: -2.72 | M47: 1.91 | N47: 0.36 | O47: -0.73 | P47: -0.34 | Q47: 0.24 | R47: -311.28 | S47: -12.87 | T47: -11.93 | U47: 0.04 | V47: 0.86 | W47: 0.84 | X47: 11.13 | Z47: 16499 | AA47: 0.62 | AB47: -1.95 | AC47: 0.08 | AD47: 1.1902152e+08
A48: BALM3 | B48: 26 | C48: 15.38 | D48: 13.23 | E48: 1.6 | F48: 0.9 | G48: 63.15 | H48: 16.37 | I48: 9.07 | J48: 7.33 | K48: 4.58 | L48: -1.38 | M48: -0.3 | N48: 1.2 | O48: 2.12 | P48: -3.4 | Q48: 2.37 | R48: 12.07 | S48: 6.83 | T48: 13.94 | U48: 0.57 | V48: 0.46 | W48: 0.75 | X48: 5.57 | Y48: 2.49 | Z48: 1787.5 | AA48: 16.29 | AB48: 1.97 | AC48: -0.35 | AD48: 207270000
A49: BALM4 | B49: 16.3 | C49: 24.54 | D49: 8.29 | E49: 1 | F49: 0.57 | G49: 63.15 | H49: 16.37 | I49: 9.07 | J49: 4.6 | K49: 4.58 | L49: -1.38 | M49: -0.3 | N49: 0.75 | O49: 1.33 | P49: -2.13 | Q49: 2.37 | R49: 12.07 | S49: 6.83 | T49: 13.94 | U49: 0.57 | V49: 0.46 | W49: 0.75 | X49: 5.57 | Y49: 2.49 | Z49: 12010.14 | AA49: 16.29 | AB49: 1.97 | AC49: -0.22 | AD49: 207270000
A50: BAUH3 | B50: 0 | D50: 0 | E50: 0 | F50: 0 | G50: 24.68 | H50: 8.15 | I50: 7.93 | J50: 0 | L50: -3.27 | M50: -0.52 | N50: 0 | O50: 0 | P50: 0 | Q50: 1.89 | R50: 15.58 | S50: 10.51 | T50: 11.65 | U50: 0.67 | V50: 0.33 | W50: 1.33 | X50: 8.24 | Y50: -0.29 | AA50: 28.37 | AB50: 4.42 | AC50: 0
A51: BAUH4 | B51: 93.9 | D51: 21.24 | E51: 3.31 | F51: 2.23 | G51: 24.68 | H51: 8.15 | I51: 7.93 | J51: 20.67 | L51: -3.27 | M51: -0.52 | N51: 1.68 | O51: 8.32 | P51: -5.19 | Q51: 1.89 | R51: 15.58 | S51: 10.51 | T51: 11.65 | U51: 0.67 | V51: 0.33 | W51: 1.33 | X51: 8.24 | Y51: -0.29 | Z51: 0 | AA51: 28.37 | AB51: 4.42 | AC51: -1.56
A52: BAZA3 | B52: 59 | C52: 20.24 | D52: 3.91 | E52: 0.46 | F52: 0.05 | G52: 1.1 | H52: 6.05 | I52: 12.73 | J52: 8.24 | K52: 8.25 | N52: 0.5 | O52: 57.13 | P52: -0.05 | R52: 11.77 | S52: 1.31 | U52: 0.11 | V52: 0.89 | W52: 0.1 | X52: 46.47 | Y52: 26.06 | Z52: 376538.68 | AA52: 128.13 | AB52: 15.08 | AC52: -0.12 | AD52: 3.3141676e+09
A53: BBAS3 | B53: 20.8 | C53: 2.65 | D53: 7.58 | E53: 0.62 | F53: 0.05 | G53: 30.81 | H53: 1.95 | I53: 4.82 | J53: 18.75 | K53: 18.72 | N53: 0.37 | O53: 2.16 | P53: -0.05 | Q53: 9.47 | R53: 8.2 | S53: 0.6 | U53: 0.07 | V53: 0.92 | W53: 0.12 | X53: 26.49 | Y53: 3.4 | Z53: 3.7502335e+08 | AA53: 33.45 | AB53: 2.74 | AC53: -0.21 | AD53: 1.1897211e+11
A54: BBDC3 | B54: 16.04 | C54: 7.21 | D54: 7.24 | E54: 0.95 | F54: 0.07 | G54: 27.28 | H54: 7.91 | I54: 8.15 | J54: 7.45 | K54: 7.99 | N54: 0.59 | O54: 0.66 | P54: -0.08 | Q54: 10.43 | R54: 13.06 | S54: 0.96 | U54: 0.07 | V54: 0.93 | W54: 0.12 | X54: 22.38 | Y54: 7.93 | Z54: 92012007 | AA54: 16.97 | AB54: 2.22 | AC54: 0.31 | AD54: 1.8205813e+11
A55: BBDC4 | B55: 18.4 | C55: 6.83 | D55: 8.3 | E55: 1.08 | F55: 0.08 | G55: 27.28 | H55: 7.91 | I55: 8.15 | J55: 8.55 | K55: 7.99 | N55: 0.68 | O55: 0.75 | P55: -0.09 | Q55: 10.43 | R55: 13.06 | S55: 0.96 | U55: 0.07 | V55: 0.93 | W55: 0.12 | X55: 22.38 | Y55: 7.93 | Z55: 5.0747599e+08 | AA55: 16.97 | AB55: 2.22 | AC55: 0.35 | AD55: 1.8205813e+11
A56: BBML3 | B56: 3936.42 | D56: -634.49 | E56: -248.41 | F56: 162.14 | G56: 3.31 | H56: -1.54 | I56: -18.79 | J56: -7761.41 | K56: -7785.8 | L56: -24.38 | N56: 119.25 | O56: -145.27 | P56: -226.58 | Q56: 0.2 | R56: -39.15 | S56: -25.55 | T56: 79.45 | U56: -0.65 | V56: 1.65 | W56: 1.36 | X56: 6.07 | AA56: -15.85 | AB56: -6.2 | AC56: 24.29 | AD56: 1.604517e+11
A57: BBSE3 | B57: 41.31 | C57: 11.01 | D57: 8.73 | E57: 6.35 | F57: 4.09 | J57: 8.02 | K57: 8.04 | O57: 17.46 | P57: -6.77 | Q57: 2.45 | R57: 72.72 | S57: 46.86 | U57: 0.64 | V57: 0.36 | W57: 0 | Y57: 19.01 | Z57: 2.1589816e+08 | AA57: 6.51 | AB57: 4.74 | AC57: 1.38 | AD57: 80393374000
A58: BDLL3 | B58: 4.5 | D58: -0.38 | E58: -0.03 | F58: 0.02 | G58: 7.06 | H58: -66.46 | I58: -46.91 | J58: -0.27 | K58: -6.7 | L58: -6.46 | N58: 0.18 | O58: -0.04 | P58: -0.03 | Q58: 0.41 | R58: -7.55 | S58: -5 | T58: 103.24 | U58: -0.66 | V58: 1.66 | W58: 0.11 | X58: 18.73 | Z58: 1478.56 | AA58: -157.91 | AB58: -11.92 | AC58: 0.01 | AD58: 6614243.3
A59: BDLL4 | B59: 3.91 | D59: -0.33 | E59: -0.02 | F59: 0.02 | G59: 7.06 | H59: -66.46 | I59: -46.91 | J59: -0.23 | K59: -6.7 | L59: -6.46 | N59: 0.15 | O59: -0.03 | P59: -0.03 | Q59: 0.41 | R59: -7.55 | S59: -5 | T59: 103.24 | U59: -0.66 | V59: 1.66 | W59: 0.11 | X59: 18.73 | Z59: 552.48 | AA59: -157.91 | AB59: -11.92 | AC59: 0.01 | AD59: 6614243.3
A60: BEEF3 | B60: 3.46 | C60: 5.64 | D60: 4.88 | E60: 2.75 | F60: 0.08 | G60: 17.06 | H60: 6.99 | I60: 1.25 | J60: 0.87 | K60: 4.3 | L60: 3.43 | M60: 10.86 | N60: 0.06 | O60: 0.59 | P60: -0.2 | Q60: 1.32 | R60: 56.47 | S60: 1.71 | T60: 14.22 | U60: 0.03 | V60: 0.96 | W60: 1.37 | X60: 23.09 | Y60: 0.42 | Z60: 30627650 | AA60: 1.26 | AB60: 0.71 | AC60: -0.03 | AD60: 3.4618716e+09
A61: BEES3 | B61: 8.72 | C61: 7.74 | D61: 9.29 | E61: 1.23 | F61: 0.08 | G61: 28.49 | H61: 5.93 | I61: 5.76 | J61: 9.03 | K61: 9.19 | N61: 0.54 | O61: 0.61 | P61: -0.09 | R61: 13.26 | S61: 0.82 | U61: 0.06 | V61: 0.94 | W61: 0.14 | X61: 28.74 | Y61: 8.03 | Z61: 80469.82 | AA61: 7.08 | AB61: 0.94 | AC61: -0.3 | AD61: 3.082059e+09
A62: BEES4 | B62: 9.03 | C62: 7.54 | D62: 9.62 | E62: 1.28 | F62: 0.08 | G62: 28.49 | H62: 5.93 | I62: 5.76 | J62: 9.35 | K62: 9.19 | N62: 0.55 | O62: 0.63 | P62: -0.09 | R62: 13.26 | S62: 0.82 | U62: 0.06 | V62: 0.94 | W62: 0.14 | X62: 28.74 | Y62: 8.03 | Z62: 37011.68 | AA62: 7.08 | AB62: 0.94 | AC62: -0.31 | AD62: 3.082059e+09
A63: BFRE11 | B63: 0 | D63: 0 | E63: 0 | F63: 0 | G63: 100 | H63: 195.96 | I63: 118.16 | J63: 0 | N63: 0 | O63: 0 | P63: 0 | R63: 6.82 | S63: 5.98 | U63: 0.88 | V63: 0.1 | W63: 0.05 | Y63: 6.26 | AA63: 309815.9 | AB63: 21126.92 | AC63: 0
A64: BFRE12 | B64: 0 | D64: 0 | E64: 0 | F64: 0 | G64: 100 | H64: 195.96 | I64: 118.16 | J64: 0 | N64: 0 | O64: 0 | P64: 0 | R64: 6.82 | S64: 5.98 | U64: 0.88 | V64: 0.1 | W64: 0.05 | Y64: 6.26 | AA64: 309815.9 | AB64: 21126.92 | AC64: 0
A65: BGIP3 | B65: 47.3 | C65: 7.02 | D65: 6.81 | E65: 1.12 | F65: 0.08 | G65: 31.02 | H65: 13.02 | I65: 8.21 | J65: 4.3 | K65: 3.63 | N65: 0.56 | O65: 11.08 | P65: -0.08 | R65: 16.51 | S65: 1.22 | U65: 0.07 | V65: 0.93 | W65: 0.15 | X65: 24.17 | Y65: 24.15 | Z65: 139860.67 | AA65: 42.07 | AB65: 6.94 | AC65: 1.11 | AD65: 922115513
A66: BGIP4 | B66: 32.6 | C66: 13.8 | D66: 4.69 | E66: 0.77 | F66: 0.06 | G66: 31.02 | H66: 13.02 | I66: 8.21 | J66: 2.96 | K66: 3.63 | N66: 0.39 | O66: 7.64 | P66: -0.06 | R66: 16.51 | S66: 1.22 | U66: 0.07 | V66: 0.93 | W66: 0.15 | X66: 24.17 | Y66: 24.15 | Z66: 18516.73 | AA66: 42.07 | AB66: 6.94 | AC66: 0.77 | AD66: 922115513
A67: BHIA3 | B67: 0.78 | D67: -0.49 | E67: 0.24 | F67: 0.03 | G67: 30.06 | H67: -1.82 | I67: -5.98 | J67: -1.61 | K67: -16.01 | L67: -14.38 | M67: 2.15 | N67: 0.03 | O67: -0.19 | P67: -0.04 | Q67: 0.76 | R67: -49.14 | S67: -5.11 | T67: -11.4 | U67: 0.1 | V67: 0.9 | W67: 0.85 | X67: 1.39 | Z67: 4992048.1 | AA67: 3.2 | AB67: -1.57 | AC67: 0.04 | AD67: 7.9073311e+08
A68: BIDI11 | B68: 10.4 | D68: -238.07 | E68: 1.08 | F68: 0.23 | G68: 50.04 | H68: -13.62 | I68: -5.22 | J68: -91.21 | K68: -91.21 | N68: 12.42 | P68: -0.24 | R68: -0.45 | S68: -0.1 | U68: 0.22 | V68: 0.78 | W68: 0.02 | X68: 5.8 | AA68: 9.67 | AB68: -0.04 | AC68: 0.13 | AD68: 8.9911398e+09
A69: BIDI3 | B69: 3.4 | D69: -233.49 | E69: 1.06 | F69: 0.23 | G69: 50.04 | H69: -13.62 | I69: -5.22 | J69: -89.46 | K69: -91.21 | N69: 12.19 | P69: -0.24 | R69: -0.45 | S69: -0.1 | U69: 0.22 | V69: 0.78 | W69: 0.02 | X69: 5.8 | AA69: 3.22 | AB69: -0.01 | AC69: 0.12 | AD69: 8.9911398e+09
A70: BIDI4 | B70: 3.41 | D70: -234.18 | E70: 1.06 | F70: 0.23 | G70: 50.04 | H70: -13.62 | I70: -5.22 | J70: -89.72 | K70: -91.21 | N70: 12.22 | P70: -0.24 | R70: -0.45 | S70: -0.1 | U70: 0.22 | V70: 0.78 | W70: 0.02 | X70: 5.8 | AA70: 3.22 | AB70: -0.01 | AC70: 0.12 | AD70: 8.9911398e+09
A71: BIOM3 | B71: 5.75 | D71: 32.71 | E71: 2.43 | F71: 1.37 | G71: 36.48 | H71: 7.59 | I71: 7.47 | J71: 32.19 | K71: 34.72 | L71: 2.42 | M71: 0.18 | N71: 2.44 | O71: 5.63 | P71: -3.12 | Q71: 1.77 | R71: 7.44 | S71: 4.2 | T71: 5.48 | U71: 0.56 | V71: 0.44 | W71: 0.56 | X71: 35.63 | Z71: 292840.32 | AA71: 2.36 | AB71: 0.18 | AC71: -0.25 | AD71: 7.8963883e+08
A72: BLAU3 | B72: 8.85 | C72: 10.45 | D72: 8.46 | E72: 0.9 | F72: 0.58 | G72: 40.44 | H72: 18.65 | I72: 13.82 | J72: 6.26 | K72: 6.34 | L72: 0.06 | M72: 0.01 | N72: 1.17 | O72: 1.81 | P72: -1.18 | Q72: 2.66 | R72: 10.63 | S72: 6.82 | T72: 6.67 | U72: 0.64 | V72: 0.36 | W72: 0.49 | X72: 7.57 | Y72: -0.84 | Z72: 1970896.8 | AA72: 9.84 | AB72: 1.05 | AC72: -0.93 | AD72: 2.0685915e+09
A73: BLUT3 | B73: 5.14 | D73: -5.63 | E73: 0.46 | F73: 0.14 | J73: -6.17 | K73: -4.91 | L73: -1.59 | M73: 0.12 | O73: -0.76 | P73: -0.14 | Q73: 0 | R73: -8.24 | S73: -2.45 | T73: -6.72 | U73: 0.3 | V73: 0.7 | W73: 0 | AA73: 11.09 | AB73: -0.91 | AC73: 0.2 | AD73: 14115600
A74: BLUT4 | B74: 1.52 | D74: -1.66 | E74: 0.14 | F74: 0.04 | J74: -1.82 | K74: -4.91 | L74: -1.59 | M74: 0.12 | O74: -0.22 | P74: -0.04 | Q74: 0 | R74: -8.24 | S74: -2.45 | T74: -6.72 | U74: 0.3 | V74: 0.7 | W74: 0 | AA74: 11.09 | AB74: -0.91 | AC74: 0.06 | AD74: 14115600
A75: BMEB3 | B75: 49.7 | C75: 3.43 | D75: 7.65 | E75: 2.06 | F75: 0.16 | G75: 47.54 | H75: 2.97 | I75: 8.95 | J75: 23.08 | K75: 24.08 | N75: 0.68 | O75: 0.83 | P75: -0.21 | R75: 26.89 | S75: 2.15 | U75: 0.08 | V75: 0.92 | W75: 0.24 | X75: 29.99 | Y75: 34.51 | Z75: 198252.23 | AA75: 24.16 | AB75: 6.5 | AC75: 0.11 | AD75: 6.4153609e+09
A76: BMEB4 | B76: 55.72 | C76: 3.36 | D76: 8.58 | E76: 2.31 | F76: 0.18 | G76: 47.54 | H76: 2.97 | I76: 8.95 | J76: 25.87 | K76: 24.08 | N76: 0.77 | O76: 0.93 | P76: -0.23 | R76: 26.89 | S76: 2.15 | U76: 0.08 | V76: 0.92 | W76: 0.24 | X76: 29.99 | Y76: 34.51 | Z76: 1923741.7 | AA76: 24.16 | AB76: 6.5 | AC76: 0.13 | AD76: 6.4153609e+09
A77: BMGB4 | B77: 5.18 | C77: 8.63 | D77: 5.67 | E77: 0.67 | F77: 0.07 | G77: 33.14 | H77: 3.52 | I77: 6.79 | J77: 10.92 | K77: 10.94 | N77: 0.38 | O77: -0.14 | P77: -0.07 | Q77: 0.01 | R77: 11.89 | S77: 1.18 | U77: 0.1 | V77: 0.9 | W77: 0.17 | X77: 16.75 | Y77: 13.57 | Z77: 5647692.7 | AA77: 7.68 | AB77: 0.91 | AC77: 0.05 | AD77: 3.3645924e+09
A78: BMIN3 | B78: 21.49 | C78: 2.38 | D78: 9.14 | E78: 0.71 | F78: 0.16 | G78: -0.28 | H78: 17.5 | I78: 15.93 | J78: 8.32 | K78: 8.17 | N78: 1.46 | O78: 98.01 | P78: -0.16 | R78: 7.82 | S78: 1.79 | U78: 0.23 | V78: 0.77 | W78: 0.11 | X78: 44.93 | Y78: 35.83 | Z78: 0 | AA78: 30.06 | AB78: 2.35 | AC78: 0.25 | AD78: 1.0184718e+08
A79: BMIN4 | B79: 18.89 | C79: 7.41 | D79: 8.03 | E79: 0.63 | F79: 0.14 | G79: -0.28 | H79: 17.5 | I79: 15.93 | J79: 7.31 | K79: 8.17 | N79: 1.28 | O79: 86.15 | P79: -0.14 | R79: 7.82 | S79: 1.79 | U79: 0.23 | V79: 0.77 | W79: 0.11 | X79: 44.93 | Y79: 35.83 | Z79: 1300.71 | AA79: 30.06 | AB79: 2.35 | AC79: 0.22 | AD79: 1.0184718e+08
A80: BMKS3 | B80: 377.03 | C80: 34.5 | D80: 2.88 | E80: 0.83 | F80: 0.68 | G80: 28.02 | H80: -188.07 | I80: 445.49 | J80: -6.82 | K80: -0.36 | L80: 6.46 | M80: -0.79 | N80: 12.82 | O80: 1.05 | P80: -2.45 | Q80: 9.61 | R80: 28.82 | S80: 23.68 | T80: -29.61 | U80: 0.82 | V80: 0.18 | W80: 0.05 | X80: -7.83 | Y80: 76.45 | Z80: 9691.27 | AA80: 454.44 | AB80: 130.97 | AC80: 0.01 | AD80: 1.7145439e+08
A81: BMOB3 | B81: 22.73 | C81: 9.39 | D81: 12.18 | E81: 2 | F81: 0.96 | G81: 26.29 | H81: 8.83 | I81: 8.91 | J81: 12.3 | K81: 10.38 | L81: -1.95 | M81: -0.32 | N81: 1.09 | O81: 3.08 | P81: -3.34 | Q81: 1.78 | R81: 16.39 | S81: 7.88 | T81: 12.15 | U81: 0.48 | V81: 0.51 | W81: 0.88 | X81: 58.14 | Y81: 34.91 | Z81: 5964922.7 | AA81: 11.38 | AB81: 1.87 | AC81: 0.51 | AD81: 1.9501592e+09
A82: BNBR3 | B82: 118.5 | C82: 5.93 | D82: 3.62 | E82: 0.7 | F82: 0.15 | G82: 50.15 | H82: 48.49 | I82: 30.82 | J82: 2.3 | K82: 2.3 | N82: 1.12 | O82: 2.27 | P82: -0.17 | R82: 19.46 | S82: 4.27 | U82: 0.22 | V82: 0.78 | W82: 0.14 | X82: 20.69 | Y82: 25.95 | Z82: 18273.48 | AA82: 168.19 | AB82: 32.73 | AC82: 0.08 | AD82: 1.169592e+10
A83: BOAS3 | B83: 7.95 | D83: 15.22 | E83: 1.83 | F83: 1.7 | G83: 56.53 | H83: 19.25 | I83: 32.39 | J83: 25.6 | K83: 18.69 | L83: -6.92 | M83: -0.5 | N83: 4.93 | O83: 3.34 | P83: -3.8 | Q83: 12.37 | R83: 12.04 | S83: 11.16 | T83: 0.99 | U83: 0.93 | V83: 0.07 | W83: 0.34 | X83: 8.81 | Y83: 74.34 | AA83: 4.34 | AB83: 0.52 | AC83: 5.59 | AD83: 4.2122506e+09
A84: BOBR3 | B84: 1 | D84: 3.83 | E84: -0.17 | F84: 0.29 | G84: 40.32 | H84: 11.06 | I84: 3.93 | J84: 1.36 | K84: 2.19 | L84: 0.68 | N84: 0.15 | O84: -1.73 | P84: -0.54 | Q84: 0.74 | R84: -4.42 | S84: 7.48 | T84: -11.64 | U84: -1.69 | V84: 2.69 | W84: 1.9 | X84: 8.44 | Y84: 11.22 | AA84: -5.91 | AB84: 0.26 | AC84: -0.04 | AD84: 2.8877551e+08
A85: BOBR4 | B85: 1.23 | D85: 4.71 | E85: -0.21 | F85: 0.35 | G85: 40.32 | H85: 11.06 | I85: 3.93 | J85: 1.68 | K85: 2.19 | L85: 0.68 | N85: 0.19 | O85: -2.13 | P85: -0.67 | Q85: 0.74 | R85: -4.42 | S85: 7.48 | T85: -11.64 | U85: -1.69 | V85: 2.69 | W85: 1.9 | X85: 8.44 | Y85: 11.22 | Z85: 3370.05 | AA85: -5.91 | AB85: 0.26 | AC85: -0.05 | AD85: 2.8877551e+08
A86: BPAC11 | B86: 55.03 | C86: 2.27 | D86: 12.18 | E86: 2.74 | F86: 0.25 | G86: 21.43 | H86: 29.09 | I86: 26.78 | J86: 11.21 | K86: 11.2 | N86: 3.26 | O86: -0.34 | P86: -0.25 | Q86: 0.01 | R86: 22.52 | S86: 2.07 | U86: 0.09 | V86: 0.9 | W86: 0.08 | X86: 16.36 | Y86: 39.92 | Z86: 4.3499241e+08 | AA86: 20.08 | AB86: 4.52 | AC86: 0.22 | AD86: 2.1391226e+11
A87: BPAC3 | B87: 21.72 | C87: 1.91 | D87: 14.41 | E87: 3.25 | F87: 0.3 | G87: 21.43 | H87: 29.09 | I87: 26.78 | J87: 13.27 | K87: 11.2 | N87: 3.86 | O87: -0.4 | P87: -0.3 | Q87: 0.01 | R87: 22.52 | S87: 2.07 | U87: 0.09 | V87: 0.9 | W87: 0.08 | X87: 16.36 | Y87: 39.92 | Z87: 429722.27 | AA87: 6.69 | AB87: 1.51 | AC87: 0.26 | AD87: 2.1391226e+11
A88: BPAC5 | B88: 17.65 | C88: 2.36 | D88: 11.71 | E88: 2.64 | F88: 0.24 | G88: 21.43 | H88: 29.09 | I88: 26.78 | J88: 10.78 | K88: 11.2 | N88: 3.14 | O88: -0.32 | P88: -0.24 | Q88: 0.01 | R88: 22.52 | S88: 2.07 | U88: 0.09 | V88: 0.9 | W88: 0.08 | X88: 16.36 | Y88: 39.92 | Z88: 291331.36 | AA88: 6.69 | AB88: 1.51 | AC88: 0.21 | AD88: 2.1391226e+11
A89: BPAN4 | B89: 12.71 | D89: 41.58 | E89: 2.12 | F89: 0.23 | G89: 34.9 | H89: 0.19 | I89: 2.58 | J89: 565.76 | K89: 565.76 | N89: 1.07 | O89: -523.71 | P89: -0.23 | Q89: 0.05 | R89: 5.1 | S89: 0.56 | U89: 0.11 | V89: 0.89 | W89: 0.22 | X89: 10.77 | Y89: -9 | Z89: 114514167 | AA89: 5.99 | AB89: 0.31 | AC89: -1.09 | AD89: 1.6129881e+10
A90: BPAR3 | B90: 180 | C90: 4.45 | D90: 9.16 | E90: 0.77 | F90: 0.09 | G90: 46.04 | H90: 10.7 | I90: 4.81 | J90: 4.11 | K90: 4.11 | N90: 0.44 | O90: 7.61 | P90: -0.09 | R90: 8.41 | S90: 0.96 | U90: 0.11 | V90: 0.89 | W90: 0.2 | X90: 19.38 | Y90: -4.95 | AA90: 233.59 | AB90: 19.66 | AC90: -0.2 | AD90: 1713896820
A91: BPAT33 | B91: 44.05 | D91: 6.98 | E91: 0.66 | F91: 0.09 | G91: 51.56 | H91: 21.77 | I91: 5.61 | J91: 1.8 | K91: 1.8 | N91: 0.39 | P91: -0.12 | R91: 9.46 | S91: 1.35 | U91: 0.14 | V91: 0.86 | W91: 0.24 | X91: 14.99 | Y91: -18.89 | AA91: 66.71 | AB91: 6.31 | AC91: -0.11 | AD91: 1533769021
A92: BPHA3 | B92: 0.62 | D92: 0.06 | E92: -0.24 | F92: 0.99 | G92: 98.02 | H92: 1029.99 | I92: 13896.67 | J92: 0.8 | K92: 1.66 | L92: 0.85 | N92: 8.28 | O92: -0.38 | P92: -1.18 | Q92: 0.06 | R92: -402.5 | S92: 1669.02 | T92: -36.75 | U92: -4.15 | V92: 5.15 | W92: 0.12 | X92: -68.85 | AA92: -2.58 | AB92: 10.4 | AC92: 0 | AD92: 70110299
A93: BRAP3 | B93: 18.49 | C93: 11.59 | D93: 9.29 | E93: 0.93 | F93: 0.92 | J93: 10.25 | K93: 11.03 | L93: -0.36 | M93: -0.03 | O93: 34.02 | P93: -0.95 | Q93: 5.99 | R93: 10 | S93: 9.94 | T93: 9.06 | U93: 0.99 | V93: 0.01 | W93: 0 | Y93: -11.82 | Z93: 602502.09 | AA93: 19.9 | AB93: 1.99 | AC93: -0.28 | AD93: 8.071525e+09
A94: BRAP4 | B94: 21.69 | C94: 10.87 | D94: 10.9 | E94: 1.09 | F94: 1.08 | J94: 12.03 | K94: 11.03 | L94: -0.36 | M94: -0.03 | O94: 39.9 | P94: -1.12 | Q94: 5.99 | R94: 10 | S94: 9.94 | T94: 9.06 | U94: 0.99 | V94: 0.01 | W94: 0 | Y94: -11.82 | Z94: 37240298 | AA94: 19.9 | AB94: 1.99 | AC94: -0.33 | AD94: 8.071525e+09
A95: BRAV3 | B95: 20.78 | C95: 0.6 | D95: 41.52 | E95: 0.85 | F95: 0.23 | G95: 27.81 | H95: 21.05 | I95: 1.96 | J95: 3.86 | K95: 8.12 | L95: 4.25 | M95: 0.93 | N95: 0.81 | O95: 10.76 | P95: -0.28 | Q95: 1.12 | R95: 2.04 | S95: 0.55 | T95: 3.26 | U95: 0.27 | V95: 0.73 | W95: 0.28 | X95: 124.4 | Z95: 1.291838e+08 | AA95: 24.56 | AB95: 0.5 | AC95: 0.83 | AD95: 9.6906646e+09
A96: BRBI11 | B96: 14.1 | C96: 11.06 | D96: 8.73 | E96: 1.87 | F96: 0.08 | G96: 100 | H96: 2.94 | I96: 52.02 | J96: 154.26 | K96: 27.69 | L96: -126.79 | M96: -1.53 | N96: 4.54 | O96: 2.55 | P96: -6.93 | Q96: 1.03 | R96: 21.38 | S96: 0.93 | T96: -0.23 | U96: 0.04 | V96: 0.96 | W96: 0.02 | X96: -23.54 | Y96: 13.84 | Z96: 2995893 | AA96: 7.56 | AB96: 1.62 | AC96: -0.93 | AD96: 1.4825393e+09
A97: BRBI3 | B97: 0 | D97: 0 | E97: 0 | F97: 0 | G97: 100 | H97: 2.94 | I97: 52.02 | J97: 0 | K97: 27.69 | L97: -126.79 | M97: -1.53 | N97: 0 | O97: 0 | P97: 0 | Q97: 1.03 | R97: 21.38 | S97: 0.93 | T97: -0.23 | U97: 0.04 | V97: 0.96 | W97: 0.02 | X97: -23.54 | Y97: 13.84 | AA97: 2.52 | AB97: 0.54 | AC97: 0 | AD97: 1.4825393e+09
A98: BRBI4 | B98: 0 | D98: 0 | E98: 0 | F98: 0 | G98: 100 | H98: 2.94 | I98: 52.02 | J98: 0 | K98: 27.69 | L98: -126.79 | M98: -1.53 | N98: 0 | O98: 0 | P98: 0 | Q98: 1.03 | R98: 21.38 | S98: 0.93 | T98: -0.23 | U98: 0.04 | V98: 0.96 | W98: 0.02 | X98: -23.54 | Y98: 13.84 | AA98: 2.52 | AB98: 0.54 | AC98: 0 | AD98: 1.4825393e+09
A99: BRFS3 | B99: 17.95 | C99: 11.62 | D99: 10.21 | E99: 2.01 | F99: 0.43 | G99: 24.77 | H99: 9.54 | I99: 4.32 | J99: 4.62 | K99: 6.96 | L99: 2.35 | M99: 1.02 | N99: 0.44 | O99: 3.24 | P99: -0.84 | Q99: 1.38 | R99: 19.69 | S99: 4.23 | T99: 10.48 | U99: 0.21 | V99: 0.77 | W99: 0.98 | X99: 10.51 | Y99: 15.13 | Z99: 377952894 | AA99: 8.93 | AB99: 1.76 | AC99: -0.38 | AD99: 2.8579855e+10
A100: BRGE11 | B100: 13.18 | D100: 33.11 | E100: 0.52 | F100: 0.32 | G100: -4115.33 | H100: -798.17 | I100: 824.67 | J100: -34.21 | K100: 21.81 | L100: 56.17 | M100: -0.85 | N100: 273.04 | O100: 0.85 | P100: -0.75 | Q100: 3.06 | R100: 1.56 | S100: 0.98 | T100: -2.91 | U100: 0.63 | V100: 0.37 | W100: 0 | X100: -32.83 | Y100: -11.18 | AA100: 25.56 | AB100: 0.4 | AC100: -0.51 | AD100: 9.7494039e+08
...

Sheet Classificação B3
A1: Código | B1: Nome | C1: Classe | D1: Setor Econômico Bovespa | E1: Subsetor Bovespa | F1: Segmento Bovespa | G1: CÍCLICO | H1: TIPO
A2: RRRP3 | B2: 3r Petroleum | C2: ON | D2: Petróleo gás e biocombustíveis | E2: Petróleo gás e biocombustíveis | F2: Exploração refino e distribuição | G2: SIM | H2: PETRÓLEO/DÓLAR
A3: TTEN3 | B3: 3tentos | C3: ON | D3: Consumo não cíclico | E3: Agropecuária | F3: Agricultura | G3: SIM | H3: COMMODITIES/DÓLAR
A4: QVQP3 | B4: 524 Particip | C4: ON | D4: Outros | E4: Outros | F4: Outros
A5: ABCB4 | B5: Abc Brasil | C5: PN | D5: Financeiro | E5: Intermediários financeiros | F5: Bancos | G5: NÃO
A6: EALT3 | B6: Aco Altona | C6: ON | D6: Bens industriais | E6: Máquinas e equipamentos | F6: Máq. e equip. industriais | G6: SIM | H6: TAXA DE JUROS/CRESCIMENTO ECONOMICO
A7: EALT4 | B7: Aco Altona | C7: PN | D7: Bens industriais | E7: Máquinas e equipamentos | F7: Máq. e equip. industriais | G7: SIM | H7: TAXA DE JUROS/CRESCIMENTO ECONOMICO
A8: AERI3 | B8: Aeris | C8: ON | D8: Bens industriais | E8: Máquinas e equipamentos | F8: Máq. e equip. industriais | G8: SIM | H8: TAXA DE JUROS/CRESCIMENTO ECONOMICO
A9: AESB3 | B9: AES Brasil | C9: ON | D9: Utilidade pública | E9: Energia elétrica | F9: Energia elétrica | G9: NÃO
A10: AESO3 | B10: Aesoperacoes | C10: ON | D10: Utilidade pública | E10: Energia elétrica | F10: Energia elétrica | G10: NÃO
A11: AFLT3 | B11: Afluente T | C11: ON | D11: Utilidade pública | E11: Energia elétrica | F11: Energia elétrica | G11: NÃO
A12: GRAO3 | B12: Agribrasil | C12: ON | D12: Consumo não cíclico | E12: Agropecuária | F12: Agricultura | G12: SIM | H12: COMMODITIES/DÓLAR
A13: AGXY3 | B13: Agrogalaxy | C13: ON | D13: Consumo não cíclico | E13: Agropecuária | F13: Agricultura | G13: SIM | H13: COMMODITIES/DÓLAR
A14: RPAD3 | B14: Alfa Holding | C14: ON | D14: Financeiro | E14: Intermediários financeiros | F14: Bancos | G14: NÃO
A15: RPAD5 | B15: Alfa Holding | C15: PNA | D15: Financeiro | E15: Intermediários financeiros | F15: Bancos | G15: NÃO
A16: RPAD6 | B16: Alfa Holding | C16: PNB | D16: Financeiro | E16: Intermediários financeiros | F16: Bancos | G16: NÃO
A17: APTI3 | B17: Aliperti | C17: ON | D17: Consumo não cíclico | E17: Agropecuária | F17: Agricultura | G17: SIM | H17: COMMODITIES/DÓLAR
A18: APTI4 | B18: Aliperti | C18: PN | D18: Consumo não cíclico | E18: Agropecuária | F18: Agricultura | G18: SIM | H18: COMMODITIES/DÓLAR
A19: FRRN3B | B19: All Norte | C19: ON | D19: Bens industriais | E19: Transporte | F19: Transporte ferroviário | G19: SIM | H19: TAXA DE JUROS/CRESCIMENTO ECONOMICO
A20: FRRN5B | B20: All Norte | C20: PNA | D20: Bens industriais | E20: Transporte | F20: Transporte ferroviário | G20: SIM | H20: TAXA DE JUROS/CRESCIMENTO ECONOMICO
A21: FRRN6B | B21: All Norte | C21: PNB | D21: Bens industriais | E21: Transporte | F21: Transporte ferroviário | G21: SIM | H21: TAXA DE JUROS/CRESCIMENTO ECONOMICO
A22: AALR3 | B22: Alliar | C22: ON | D22: Saúde | E22: Serviços médico-hospitalares análises e diagnósticos | F22: Serviços médico-hospitalares análises e diagnósticos | G22: NÃO
A23: ALLD3 | B23: Allied | C23: ON | D23: Consumo cíclico | E23: Comércio | F23: Eletrodomésticos | G23: SIM | H23: TAXA DE JUROS/CRESCIMENTO ECONOMICO
A24: ALOS3 | B24: Allos | C24: ON | D24: Financeiro | E24: Exploração de imóveis | F24: Exploração de imóveis | G24: SIM | H24: TAXA DE JUROS/CRESCIMENTO ECONOMICO
A25: ALPA3 | B25: Alpargatas | C25: ON | D25: Consumo cíclico | E25: Tecidos vestuário e calçados | F25: Calçados | G25: SIM | H25: TAXA DE JUROS/CRESCIMENTO ECONOMICO
A26: ALPA4 | B26: Alpargatas | C26: PN | D26: Consumo cíclico | E26: Tecidos vestuário e calçados | F26: Calçados | G26: SIM | H26: TAXA DE JUROS/CRESCIMENTO ECONOMICO
A27: APER3 | B27: Alper S.A. | C27: ON | D27: Financeiro | E27: Previdência e seguros | F27: Corretoras de seguros e resseguros | G27: NÃO
A28: AVLL3 | B28: Alphaville | C28: ON | D28: Consumo cíclico | E28: Construção civil | F28: Incorporações | G28: SIM | H28: TAXA DE JUROS/CRESCIMENTO ECONOMICO
A29: ALUP3 | B29: Alupar | C29: ON | D29: Utilidade pública | E29: Energia elétrica | F29: Energia elétrica | G29: NÃO
A30: ALUP4 | B30: Alupar | C30: PN | D30: Utilidade pública | E30: Energia elétrica | F30: Energia elétrica | G30: NÃO
A31: ALUP11 | B31: Alupar | C31: UNT N2 | D31: Utilidade pública | E31: Energia elétrica | F31: Energia elétrica | G31: NÃO
A32: BAZA3 | B32: Amazonia | C32: ON | D32: Financeiro | E32: Intermediários financeiros | F32: Bancos | G32: NÃO
A33: ABEV3 | B33: Ambev S/A | C33: ON | D33: Consumo não cíclico | E33: Bebidas | F33: Cervejas e refrigerantes | G33: SIM | H33: TAXA DE JUROS/CRESCIMENTO ECONOMICO
A34: AMBP3 | B34: Ambipar | C34: ON | D34: Utilidade pública | E34: Água e saneamento | F34: Água e saneamento | G34: NÃO
A35: AMER3 | B35: Americanas | C35: ON | D35: Consumo cíclico | E35: Comércio | F35: Produtos diversos | G35: SIM | H35: TAXA DE JUROS/CRESCIMENTO ECONOMICO
A36: CBEE3 | B36: Ampla Energ | C36: ON | D36: Utilidade pública | E36: Energia elétrica | F36: Energia elétrica | G36: NÃO
A37: ANIM3 | B37: Anima | C37: ON | D37: Consumo cíclico | E37: Diversos | F37: Serviços educacionais | G37: SIM | H37: TAXA DE JUROS/CRESCIMENTO ECONOMICO
A38: ARML3 | B38: Armac | C38: ON | D38: Bens industriais | E38: Máquinas e equipamentos | F38: Máq. e equip. industriais | G38: SIM | H38: TAXA DE JUROS/CRESCIMENTO ECONOMICO
A39: ASAI3 | B39: Assai | C39: ON | D39: Consumo não cíclico | E39: Comércio e distribuição | F39: Alimentos | G39: SIM | H39: TAXA DE JUROS/CRESCIMENTO ECONOMICO
A40: ATMP3 | B40: Atmasa | C40: ON | D40: Bens industriais | E40: Serviços diversos | F40: Serviços diversos | G40: SIM | H40: TAXA DE JUROS/CRESCIMENTO ECONOMICO
A41: ATOM3 | B41: Atompar | C41: ON | D41: Outros | E41: Outros | F41: Outros
A42: AURA33 | B42: Aura 360 | C42: ON | D42: Materiais básicos | E42: Mineração | F42: Minerais metálicos | G42: SIM | H42: MINÉRIO/DÓLAR
A43: AURE3 | B43: Auren | C43: ON | D43: Utilidade pública | E43: Energia elétrica | F43: Energia elétrica | G43: NÃO
A44: AZEV3 | B44: Azevedo | C44: ON | D44: Bens industriais | E44: Construção e engenharia | F44: Construção pesada | G44: SIM | H44: TAXA DE JUROS/CRESCIMENTO ECONOMICO
A45: AZEV4 | B45: Azevedo | C45: PN | D45: Bens industriais | E45: Construção e engenharia | F45: Construção pesada | G45: SIM | H45: TAXA DE JUROS/CRESCIMENTO ECONOMICO
A46: AZUL4 | B46: Azul | C46: PN | D46: Bens industriais | E46: Transporte | F46: Transporte aéreo | G46: SIM | H46: TAXA DE JUROS/CRESCIMENTO ECONOMICO
A47: AZZA3 | B47: Azzas 2154 | C47: ON | D47: Consumo cíclico | E47: Comércio | F47: Tecidos vestuário e calçados | G47: SIM | H47: TAXA DE JUROS/CRESCIMENTO ECONOMICO
A48: B3SA3 | B48: B3 | C48: ON | D48: Financeiro | E48: Serviços financeiros diversos | F48: Serviços financeiros diversos | G48: SIM | H48: TAXA DE JUROS/CRESCIMENTO ECONOMICO
A49: BAHI3 | B49: Bahema | C49: ON | D49: Consumo cíclico | E49: Diversos | F49: Serviços educacionais | G49: SIM | H49: TAXA DE JUROS/CRESCIMENTO ECONOMICO
A50: BMGB4 | B50: Banco BMG | C50: PN | D50: Financeiro | E50: Intermediários financeiros | F50: Bancos | G50: NÃO
A51: BPAN4 | B51: Banco Pan | C51: PN | D51: Financeiro | E51: Intermediários financeiros | F51: Bancos | G51: NÃO
A52: BGIP3 | B52: Banese | C52: ON | D52: Financeiro | E52: Intermediários financeiros | F52: Bancos | G52: NÃO
A53: BGIP4 | B53: Banese | C53: PN | D53: Financeiro | E53: Intermediários financeiros | F53: Bancos | G53: NÃO
A54: BEES3 | B54: Banestes | C54: ON | D54: Financeiro | E54: Intermediários financeiros | F54: Bancos | G54: NÃO
A55: BEES4 | B55: Banestes | C55: PN | D55: Financeiro | E55: Intermediários financeiros | F55: Bancos | G55: NÃO
A56: BPAR3 | B56: Banpara | C56: ON | D56: Financeiro | E56: Intermediários financeiros | F56: Bancos | G56: NÃO
A57: BRSR3 | B57: Banrisul | C57: ON | D57: Financeiro | E57: Intermediários financeiros | F57: Bancos | G57: NÃO
A58: BRSR5 | B58: Banrisul | C58: PNA | D58: Financeiro | E58: Intermediários financeiros | F58: Bancos | G58: NÃO
A59: BRSR6 | B59: Banrisul | C59: PNB | D59: Financeiro | E59: Intermediários financeiros | F59: Bancos | G59: NÃO
A60: BDLL3 | B60: Bardella | C60: ON | D60: Bens industriais | E60: Máquinas e equipamentos | F60: Máq. e equip. industriais | G60: SIM | H60: TAXA DE JUROS/CRESCIMENTO ECONOMICO
A61: BDLL4 | B61: Bardella | C61: PN | D61: Bens industriais | E61: Máquinas e equipamentos | F61: Máq. e equip. industriais | G61: SIM | H61: TAXA DE JUROS/CRESCIMENTO ECONOMICO
A62: BALM3 | B62: Baumer | C62: ON | D62: Saúde | E62: Equipamentos | F62: Equipamentos | G62: NÃO
A63: BALM4 | B63: Baumer | C63: PN | D63: Saúde | E63: Equipamentos | F63: Equipamentos | G63: NÃO
A64: BBML3 | B64: Bbmlogistica | C64: ON | D64: Bens industriais | E64: Serviços diversos | F64: Serviços diversos | G64: SIM | H64: TAXA DE JUROS/CRESCIMENTO ECONOMICO
A65: BBSE3 | B65: BBSeguridade | C65: ON | D65: Financeiro | E65: Previdência e seguros | F65: Seguradoras | G65: NÃO
A66: BMOB3 | B66: Bemobi Tech | C66: ON | D66: Tecnologia da informação | E66: Programas e serviços | F66: Programas e serviços | G66: SIM | H66: TAXA DE JUROS/CRESCIMENTO ECONOMICO
A67: BETP3 | B67: Betapart | C67: ON | D67: Outros | E67: Outros | F67: Outros
A68: BMKS3 | B68: Bic Monark | C68: ON | D68: Consumo cíclico | E68: Viagens e lazer | F68: Bicicletas | G68: SIM | H68: TAXA DE JUROS/CRESCIMENTO ECONOMICO
A69: BIOM3 | B69: Biomm | C69: ON | D69: Saúde | E69: Medicamentos e outros produtos | F69: Medicamentos e outros produtos | G69: NÃO
A70: BLAU3 | B70: Blau | C70: ON | D70: Saúde | E70: Comércio e distribuição | F70: Medicamentos e outros produtos | G70: NÃO
A71: SOJA3 | B71: Boa Safra | C71: ON | D71: Consumo não cíclico | E71: Agropecuária | F71: Agricultura | G71: SIM | H71: COMMODITIES/DÓLAR
A72: BOBR3 | B72: Bombril | C72: ON | D72: Consumo não cíclico | E72: Produtos de uso pessoal e de limpeza | F72: Produtos de limpeza | G72: SIM | H72: COMMODITIES/DÓLAR
A73: BOBR4 | B73: Bombril | C73: PN | D73: Consumo não cíclico | E73: Produtos de uso pessoal e de limpeza | F73: Produtos de limpeza | G73: SIM | H73: COMMODITIES/DÓLAR
A74: BRBI11 | B74: BR Partners | C74: UNT N2 | D74: Financeiro | E74: Intermediários financeiros | F74: Bancos | G74: NÃO
A75: BBDC3 | B75: Bradesco | C75: ON | D75: Financeiro | E75: Intermediários financeiros | F75: Bancos | G75: NÃO
A76: BBDC4 | B76: Bradesco | C76: PN | D76: Financeiro | E76: Intermediários financeiros | F76: Bancos | G76: NÃO
A77: BRAP3 | B77: Bradespar | C77: ON | D77: Materiais básicos | E77: Mineração | F77: Minerais metálicos | G77: SIM | H77: MINÉRIO/DÓLAR
A78: BRAP4 | B78: Bradespar | C78: PN | D78: Materiais básicos | E78: Mineração | F78: Minerais metálicos | G78: SIM | H78: MINÉRIO/DÓLAR
A79: BBAS3 | B79: Brasil | C79: ON | D79: Financeiro | E79: Intermediários financeiros | F79: Bancos | G79: NÃO
A80: AGRO3 | B80: Brasilagro | C80: ON | D80: Consumo não cíclico | E80: Agropecuária | F80: Agricultura | G80: SIM | H80: COMMODITIES/DÓLAR
A81: BRKM3 | B81: Braskem | C81: ON | D81: Materiais básicos | E81: Químicos | F81: Petroquímicos | G81: SIM | H81: DÓLAR
A82: BRKM5 | B82: Braskem | C82: PNA | D82: Materiais básicos | E82: Químicos | F82: Petroquímicos | G82: SIM | H82: DÓLAR
A83: BRKM6 | B83: Braskem | C83: PNB | D83: Materiais básicos | E83: Químicos | F83: Petroquímicos | G83: SIM | H83: DÓLAR
A84: BSLI3 | B84: BRB Banco | C84: ON | D84: Financeiro | E84: Intermediários financeiros | F84: Bancos | G84: NÃO
A85: BSLI4 | B85: BRB Banco | C85: PN | D85: Financeiro | E85: Intermediários financeiros | F85: Bancos | G85: NÃO
A86: BRFS3 | B86: BRF SA | C86: ON | D86: Consumo não cíclico | E86: Alimentos processados | F86: Carnes e derivados | G86: SIM | H86: COMMODITIES/DÓLAR
A87: BRIT3 | B87: Brisanet | C87: ON | D87: Comunicações | E87: Telecomunicações | F87: Telecomunicações | G87: SIM | H87: TAXA DE JUROS/CRESCIMENTO ECONOMICO
A88: BRQB3 | B88: Brq | C88: ON | D88: Tecnologia da informação | E88: Programas e serviços | F88: Programas e serviços | G88: SIM | H88: TAXA DE JUROS/CRESCIMENTO ECONOMICO
A89: BPAC3 | B89: Btgp Banco | C89: ON | D89: Financeiro | E89: Intermediários financeiros | F89: Bancos | G89: NÃO
A90: BPAC5 | B90: Btgp Banco | C90: PNA | D90: Financeiro | E90: Intermediários financeiros | F90: Bancos | G90: NÃO
A91: BPAC11 | B91: Btgp Banco | C91: UNT | D91: Financeiro | E91: Intermediários financeiros | F91: Bancos | G91: NÃO
A92: CXSE3 | B92: Caixa Seguri | C92: ON | D92: Financeiro | E92: Previdência e seguros | F92: Seguradoras | G92: NÃO
A93: CAMB3 | B93: Cambuci | C93: ON | D93: Consumo cíclico | E93: Tecidos vestuário e calçados | F93: Calçados | G93: SIM | H93: TAXA DE JUROS/CRESCIMENTO ECONOMICO
A94: CAML3 | B94: Camil | C94: ON | D94: Consumo não cíclico | E94: Alimentos processados | F94: Alimentos diversos | G94: SIM | H94: COMMODITIES/DÓLAR
A95: CRFB3 | B95: Carrefour BR | C95: ON | D95: Consumo não cíclico | E95: Comércio e distribuição | F95: Alimentos | G95: SIM | H95: TAXA DE JUROS/CRESCIMENTO ECONOMICO
A96: CASN3 | B96: Casan | C96: ON | D96: Utilidade pública | E96: Água e saneamento | F96: Água e saneamento | G96: NÃO
A97: CASN4 | B97: Casan | C97: PN | D97: Utilidade pública | E97: Água e saneamento | F97: Água e saneamento | G97: NÃO
A98: BHIA3 | B98: Casas Bahia | C98: ON | D98: Consumo cíclico | E98: Comércio | F98: Eletrodomésticos | G98: SIM | H98: TAXA DE JUROS/CRESCIMENTO ECONOMICO
A99: CBAV3 | B99: Cba | C99: ON | D99: Materiais básicos | E99: Mineração | F99: Minerais metálicos | G99: SIM | H99: MINÉRIO/DÓLAR
A100: CCRO3 | B100: CCR SA | C100: ON | D100: Bens industriais | E100: Transporte | F100: Exploração de rodovias | G100: SIM | H100: TAXA DE JUROS/CRESCIMENTO ECONOMICO
...

Sheet Classificacao B3
A1: Ticker | B1: Nome | C1: Setor
A2: RRRP3 | B2: 3r Petroleum | C2: Petróleo e Gas
A3: TTEN3 | B3: 3tentos | C3: Agro e Pesca
A4: QVQP3B | B4: 524 Particip | C4: Energia Elétrica
A5: ABCB4 | B5: Abc Brasil | C5: Finanças e Seguros
A6: EALT3 | B6: Aco Altona | C6: Siderur & Metalur
A7: EALT4 | B7: Aco Altona | C7: Siderur & Metalur
A8: AERI3 | B8: Aeris | C8: Máquinas Indust
A9: AESB3 | B9: AES Brasil | C9: Energia Elétrica
A10: AFLT3 | B10: Afluente T | C10: Energia Elétrica
A11: GRAO3 | B11: Agribrasil | C11: Agro e Pesca
A12: AGXY3 | B12: Agrogalaxy | C12: Agro e Pesca
... A589: YDUQ3 | B589: Yduqs Part | C589: Outros
